Workbook

Sheet Mode d'emploi
A1: Suivi des stocks — version pour Lele (v1)
A2: Proposition de tableau de gestion des stocks — Excel et Google Sheets
A4: L'idée | B4: Ton suivi sur l'année, avec tout ce que tu as demandé : les produits rangés par zone (réserve sèche, chambre froide positive, chambre froide négative, ménager), la date de commande chaque semaine, le tableau de bord avec les tendances, et le registre de réception qui remplace ton cahier.
A6: Comment faire | B6: 1. Onglet Produits : écris chaque produit dans sa zone, avec son fournisseur habituel, l'unité, le stock minimum et le prix unitaire (une seule fois — à changer seulement si le tarif change).
B7: 2. Chaque semaine, dans l'onglet du mois : la date de commande, le stock compté, ce que tu commandes, puis ce que tu reçois à la livraison. Rouge = reçu moins que commandé, orange = sous le minimum.
B8: 3. À chaque livraison : une ligne par produit dans Réceptions (date, produit, fournisseur, quantité, n° de lot, DLC). Le fournisseur peut être différent de l'habituel.
B9: 4. Tableau de bord : choisis le mois, tout se calcule. Année 2026 : le récap mois par mois.
B10: 5. Les chiffres en bleu sont des exemples : efface-les avant de commencer.
A12: Les onglets | B12: Tableau de bord — dépenses, livraisons incomplètes, produits sous le minimum, tendances, top 10.
B13: Produits — ta liste par zone, avec minimum et prix.
B14: Fournisseurs — carnet d'adresses.
B15: Janvier à Décembre — la saisie de chaque semaine.
B16: Année 2026 — reçu, dépenses et stock de fin de mois.
B17: Réceptions — le registre qui remplace le cahier.
A19: Couleurs | B19: Cases jaunes = à remplir. Cases blanches = calculées toutes seules, ne pas y toucher.
B20: Chiffres en bleu = exemple pour montrer le fonctionnement, à effacer.
B21: Rouge = il manque quelque chose (livraison incomplète, stock trop bas).
A23: Google Sheets | B23: Fichier > Importer > Importer ce fichier. Tout fonctionne pareil, y compris sur téléphone.

Sheet Tableau de bord
A1: Tableau de bord
A2: Choisis le mois dans la case jaune — tout se recalcule. Rien d'autre à remplir ici.
A3: Mois : | B3: Octobre | Z3: =MATCH($B$3,$Z$5:$Z$16,0)
AA4: Produit | AB4: S1 | AC4: S2 | AD4: S3 | AE4: S4 | AF4: Commandé | AG4: Reçu | AH4: Écart | AI4: Dernier | AJ4: Mini | AK4: Dépense | AL4: SousMini | AM4: Tri
A5: Dépensé ce mois | C5: Reçu incomplet | E5: Sous le minimum | G5: Produits suivis | Z5: Janvier | AA5: =IF(Produits!$A$6="","",Produits!$A$6) | AB5: =IF(ISNUMBER(CHOOSE($Z$3,'Janvier'!E7,'Février'!E7,'Mars'!E7,'Avril'!E7,'Mai'!E7,'Juin'!E7,'Juillet'!E7,'Août'!E7,'Septembre'!E7,'Octobre'!E7,'Novembre'!E7,'Décembre'!E7)),CHOOSE($Z$3,'Janvier'!E7,'Février'!E7,'Mars'!E7,'Avril'!E7,'Mai'!E7,'Juin'!E7,'Juillet'!E7,'Août'!E7,'Septembre'!E7,'Octobre'!E7,'Novembre'!E7,'Décembre'!E7),"") | AC5: =IF(ISNUMBER(CHOOSE($Z$3,'Janvier'!I7,'Février'!I7,'Mars'!I7,'Avril'!I7,'Mai'!I7,'Juin'!I7,'Juillet'!I7,'Août'!I7,'Septembre'!I7,'Octobre'!I7,'Novembre'!I7,'Décembre'!I7)),CHOOSE($Z$3,'Janvier'!I7,'Février'!I7,'Mars'!I7,'Avril'!I7,'Mai'!I7,'Juin'!I7,'Juillet'!I7,'Août'!I7,'Septembre'!I7,'Octobre'!I7,'Novembre'!I7,'Décembre'!I7),"") | AD5: =IF(ISNUMBER(CHOOSE($Z$3,'Janvier'!M7,'Février'!M7,'Mars'!M7,'Avril'!M7,'Mai'!M7,'Juin'!M7,'Juillet'!M7,'Août'!M7,'Septembre'!M7,'Octobre'!M7,'Novembre'!M7,'Décembre'!M7)),CHOOSE($Z$3,'Janvier'!M7,'Février'!M7,'Mars'!M7,'Avril'!M7,'Mai'!M7,'Juin'!M7,'Juillet'!M7,'Août'!M7,'Septembre'!M7,'Octobre'!M7,'Novembre'!M7,'Décembre'!M7),"") | AE5: =IF(ISNUMBER(CHOOSE($Z$3,'Janvier'!Q7,'Février'!Q7,'Mars'!Q7,'Avril'!Q7,'Mai'!Q7,'Juin'!Q7,'Juillet'!Q7,'Août'!Q7,'Septembre'!Q7,'Octobre'!Q7,'Novembre'!Q7,'Décembre'!Q7)),CHOOSE($Z$3,'Janvier'!Q7,'Février'!Q7,'Mars'!Q7,'Avril'!Q7,'Mai'!Q7,'Juin'!Q7,'Juillet'!Q7,'Août'!Q7,'Septembre'!Q7,'Octobre'!Q7,'Novembre'!Q7,'Décembre'!Q7),"") | AF5: =IF(ISNUMBER(CHOOSE($Z$3,'Janvier'!T7,'Février'!T7,'Mars'!T7,'Avril'!T7,'Mai'!T7,'Juin'!T7,'Juillet'!T7,'Août'!T7,'Septembre'!T7,'Octobre'!T7,'Novembre'!T7,'Décembre'!T7)),CHOOSE($Z$3,'Janvier'!T7,'Février'!T7,'Mars'!T7,'Avril'!T7,'Mai'!T7,'Juin'!T7,'Juillet'!T7,'Août'!T7,'Septembre'!T7,'Octobre'!T7,'Novembre'!T7,'Décembre'!T7),"") | AG5: =IF(ISNUMBER(CHOOSE($Z$3,'Janvier'!U7,'Février'!U7,'Mars'!U7,'Avril'!U7,'Mai'!U7,'Juin'!U7,'Juillet'!U7,'Août'!U7,'Septembre'!U7,'Octobre'!U7,'Novembre'!U7,'Décembre'!U7)),CHOOSE($Z$3,'Janvier'!U7,'Février'!U7,'Mars'!U7,'Avril'!U7,'Mai'!U7,'Juin'!U7,'Juillet'!U7,'Août'!U7,'Septembre'!U7,'Octobre'!U7,'Novembre'!U7,'Décembre'!U7),"") | AH5: =IF(ISNUMBER(CHOOSE($Z$3,'Janvier'!V7,'Février'!V7,'Mars'!V7,'Avril'!V7,'Mai'!V7,'Juin'!V7,'Juillet'!V7,'Août'!V7,'Septembre'!V7,'Octobre'!V7,'Novembre'!V7,'Décembre'!V7)),CHOOSE($Z$3,'Janvier'!V7,'Février'!V7,'Mars'!V7,'Avril'!V7,'Mai'!V7,'Juin'!V7,'Juillet'!V7,'Août'!V7,'Septembre'!V7,'Octobre'!V7,'Novembre'!V7,'Décembre'!V7),"") | AI5: =IF(ISNUMBER(CHOOSE($Z$3,'Janvier'!W7,'Février'!W7,'Mars'!W7,'Avril'!W7,'Mai'!W7,'Juin'!W7,'Juillet'!W7,'Août'!W7,'Septembre'!W7,'Octobre'!W7,'Novembre'!W7,'Décembre'!W7)),CHOOSE($Z$3,'Janvier'!W7,'Février'!W7,'Mars'!W7,'Avril'!W7,'Mai'!W7,'Juin'!W7,'Juillet'!W7,'Août'!W7,'Septembre'!W7,'Octobre'!W7,'Novembre'!W7,'Décembre'!W7),"") | AJ5: =IF(Produits!$A$6="","",Produits!$D$6) | AK5: =IF(ISNUMBER(CHOOSE($Z$3,'Janvier'!X7,'Février'!X7,'Mars'!X7,'Avril'!X7,'Mai'!X7,'Juin'!X7,'Juillet'!X7,'Août'!X7,'Septembre'!X7,'Octobre'!X7,'Novembre'!X7,'Décembre'!X7)),CHOOSE($Z$3,'Janvier'!X7,'Février'!X7,'Mars'!X7,'Avril'!X7,'Mai'!X7,'Juin'!X7,'Juillet'!X7,'Août'!X7,'Septembre'!X7,'Octobre'!X7,'Novembre'!X7,'Décembre'!X7),"") | AL5: =IF(AND(ISNUMBER(AI5),ISNUMBER(AJ5)),IF(AI5<=AJ5,1,0),0) | AM5: =IF(OR(AA5="",AK5=""),-1,AK5+ROW()/1000000)
A6: =SUM(AK5:AK64) | C6: =COUNTIF(AH5:AH64,"<0") | E6: =SUM(AL5:AL64) | G6: =COUNTA(Produits!A6:A20)+COUNTA(Produits!A22:A36)+COUNTA(Produits!A38:A52)+COUNTA(Produits!A54:A68) | Z6: Février | AA6: =IF(Produits!$A$7="","",Produits!$A$7) | AB6: =IF(ISNUMBER(CHOOSE($Z$3,'Janvier'!E8,'Février'!E8,'Mars'!E8,'Avril'!E8,'Mai'!E8,'Juin'!E8,'Juillet'!E8,'Août'!E8,'Septembre'!E8,'Octobre'!E8,'Novembre'!E8,'Décembre'!E8)),CHOOSE($Z$3,'Janvier'!E8,'Février'!E8,'Mars'!E8,'Avril'!E8,'Mai'!E8,'Juin'!E8,'Juillet'!E8,'Août'!E8,'Septembre'!E8,'Octobre'!E8,'Novembre'!E8,'Décembre'!E8),"") | AC6: =IF(ISNUMBER(CHOOSE($Z$3,'Janvier'!I8,'Février'!I8,'Mars'!I8,'Avril'!I8,'Mai'!I8,'Juin'!I8,'Juillet'!I8,'Août'!I8,'Septembre'!I8,'Octobre'!I8,'Novembre'!I8,'Décembre'!I8)),CHOOSE($Z$3,'Janvier'!I8,'Février'!I8,'Mars'!I8,'Avril'!I8,'Mai'!I8,'Juin'!I8,'Juillet'!I8,'Août'!I8,'Septembre'!I8,'Octobre'!I8,'Novembre'!I8,'Décembre'!I8),"") | AD6: =IF(ISNUMBER(CHOOSE($Z$3,'Janvier'!M8,'Février'!M8,'Mars'!M8,'Avril'!M8,'Mai'!M8,'Juin'!M8,'Juillet'!M8,'Août'!M8,'Septembre'!M8,'Octobre'!M8,'Novembre'!M8,'Décembre'!M8)),CHOOSE($Z$3,'Janvier'!M8,'Février'!M8,'Mars'!M8,'Avril'!M8,'Mai'!M8,'Juin'!M8,'Juillet'!M8,'Août'!M8,'Septembre'!M8,'Octobre'!M8,'Novembre'!M8,'Décembre'!M8),"") | AE6: =IF(ISNUMBER(CHOOSE($Z$3,'Janvier'!Q8,'Février'!Q8,'Mars'!Q8,'Avril'!Q8,'Mai'!Q8,'Juin'!Q8,'Juillet'!Q8,'Août'!Q8,'Septembre'!Q8,'Octobre'!Q8,'Novembre'!Q8,'Décembre'!Q8)),CHOOSE($Z$3,'Janvier'!Q8,'Février'!Q8,'Mars'!Q8,'Avril'!Q8,'Mai'!Q8,'Juin'!Q8,'Juillet'!Q8,'Août'!Q8,'Septembre'!Q8,'Octobre'!Q8,'Novembre'!Q8,'Décembre'!Q8),"") | AF6: =IF(ISNUMBER(CHOOSE($Z$3,'Janvier'!T8,'Février'!T8,'Mars'!T8,'Avril'!T8,'Mai'!T8,'Juin'!T8,'Juillet'!T8,'Août'!T8,'Septembre'!T8,'Octobre'!T8,'Novembre'!T8,'Décembre'!T8)),CHOOSE($Z$3,'Janvier'!T8,'Février'!T8,'Mars'!T8,'Avril'!T8,'Mai'!T8,'Juin'!T8,'Juillet'!T8,'Août'!T8,'Septembre'!T8,'Octobre'!T8,'Novembre'!T8,'Décembre'!T8),"") | AG6: =IF(ISNUMBER(CHOOSE($Z$3,'Janvier'!U8,'Février'!U8,'Mars'!U8,'Avril'!U8,'Mai'!U8,'Juin'!U8,'Juillet'!U8,'Août'!U8,'Septembre'!U8,'Octobre'!U8,'Novembre'!U8,'Décembre'!U8)),CHOOSE($Z$3,'Janvier'!U8,'Février'!U8,'Mars'!U8,'Avril'!U8,'Mai'!U8,'Juin'!U8,'Juillet'!U8,'Août'!U8,'Septembre'!U8,'Octobre'!U8,'Novembre'!U8,'Décembre'!U8),"") | AH6: =IF(ISNUMBER(CHOOSE($Z$3,'Janvier'!V8,'Février'!V8,'Mars'!V8,'Avril'!V8,'Mai'!V8,'Juin'!V8,'Juillet'!V8,'Août'!V8,'Septembre'!V8,'Octobre'!V8,'Novembre'!V8,'Décembre'!V8)),CHOOSE($Z$3,'Janvier'!V8,'Février'!V8,'Mars'!V8,'Avril'!V8,'Mai'!V8,'Juin'!V8,'Juillet'!V8,'Août'!V8,'Septembre'!V8,'Octobre'!V8,'Novembre'!V8,'Décembre'!V8),"") | AI6: =IF(ISNUMBER(CHOOSE($Z$3,'Janvier'!W8,'Février'!W8,'Mars'!W8,'Avril'!W8,'Mai'!W8,'Juin'!W8,'Juillet'!W8,'Août'!W8,'Septembre'!W8,'Octobre'!W8,'Novembre'!W8,'Décembre'!W8)),CHOOSE($Z$3,'Janvier'!W8,'Février'!W8,'Mars'!W8,'Avril'!W8,'Mai'!W8,'Juin'!W8,'Juillet'!W8,'Août'!W8,'Septembre'!W8,'Octobre'!W8,'Novembre'!W8,'Décembre'!W8),"") | AJ6: =IF(Produits!$A$7="","",Produits!$D$7) | AK6: =IF(ISNUMBER(CHOOSE($Z$3,'Janvier'!X8,'Février'!X8,'Mars'!X8,'Avril'!X8,'Mai'!X8,'Juin'!X8,'Juillet'!X8,'Août'!X8,'Septembre'!X8,'Octobre'!X8,'Novembre'!X8,'Décembre'!X8)),CHOOSE($Z$3,'Janvier'!X8,'Février'!X8,'Mars'!X8,'Avril'!X8,'Mai'!X8,'Juin'!X8,'Juillet'!X8,'Août'!X8,'Septembre'!X8,'Octobre'!X8,'Novembre'!X8,'Décembre'!X8),"") | AL6: =IF(AND(ISNUMBER(AI6),ISNUMBER(AJ6)),IF(AI6<=AJ6,1,0),0) | AM6: =IF(OR(AA6="",AK6=""),-1,AK6+ROW()/1000000)
Z7: Mars | AA7: =IF(Produits!$A$8="","",Produits!$A$8) | AB7: =IF(ISNUMBER(CHOOSE($Z$3,'Janvier'!E9,'Février'!E9,'Mars'!E9,'Avril'!E9,'Mai'!E9,'Juin'!E9,'Juillet'!E9,'Août'!E9,'Septembre'!E9,'Octobre'!E9,'Novembre'!E9,'Décembre'!E9)),CHOOSE($Z$3,'Janvier'!E9,'Février'!E9,'Mars'!E9,'Avril'!E9,'Mai'!E9,'Juin'!E9,'Juillet'!E9,'Août'!E9,'Septembre'!E9,'Octobre'!E9,'Novembre'!E9,'Décembre'!E9),"") | AC7: =IF(ISNUMBER(CHOOSE($Z$3,'Janvier'!I9,'Février'!I9,'Mars'!I9,'Avril'!I9,'Mai'!I9,'Juin'!I9,'Juillet'!I9,'Août'!I9,'Septembre'!I9,'Octobre'!I9,'Novembre'!I9,'Décembre'!I9)),CHOOSE($Z$3,'Janvier'!I9,'Février'!I9,'Mars'!I9,'Avril'!I9,'Mai'!I9,'Juin'!I9,'Juillet'!I9,'Août'!I9,'Septembre'!I9,'Octobre'!I9,'Novembre'!I9,'Décembre'!I9),"") | AD7: =IF(ISNUMBER(CHOOSE($Z$3,'Janvier'!M9,'Février'!M9,'Mars'!M9,'Avril'!M9,'Mai'!M9,'Juin'!M9,'Juillet'!M9,'Août'!M9,'Septembre'!M9,'Octobre'!M9,'Novembre'!M9,'Décembre'!M9)),CHOOSE($Z$3,'Janvier'!M9,'Février'!M9,'Mars'!M9,'Avril'!M9,'Mai'!M9,'Juin'!M9,'Juillet'!M9,'Août'!M9,'Septembre'!M9,'Octobre'!M9,'Novembre'!M9,'Décembre'!M9),"") | AE7: =IF(ISNUMBER(CHOOSE($Z$3,'Janvier'!Q9,'Février'!Q9,'Mars'!Q9,'Avril'!Q9,'Mai'!Q9,'Juin'!Q9,'Juillet'!Q9,'Août'!Q9,'Septembre'!Q9,'Octobre'!Q9,'Novembre'!Q9,'Décembre'!Q9)),CHOOSE($Z$3,'Janvier'!Q9,'Février'!Q9,'Mars'!Q9,'Avril'!Q9,'Mai'!Q9,'Juin'!Q9,'Juillet'!Q9,'Août'!Q9,'Septembre'!Q9,'Octobre'!Q9,'Novembre'!Q9,'Décembre'!Q9),"") | AF7: =IF(ISNUMBER(CHOOSE($Z$3,'Janvier'!T9,'Février'!T9,'Mars'!T9,'Avril'!T9,'Mai'!T9,'Juin'!T9,'Juillet'!T9,'Août'!T9,'Septembre'!T9,'Octobre'!T9,'Novembre'!T9,'Décembre'!T9)),CHOOSE($Z$3,'Janvier'!T9,'Février'!T9,'Mars'!T9,'Avril'!T9,'Mai'!T9,'Juin'!T9,'Juillet'!T9,'Août'!T9,'Septembre'!T9,'Octobre'!T9,'Novembre'!T9,'Décembre'!T9),"") | AG7: =IF(ISNUMBER(CHOOSE($Z$3,'Janvier'!U9,'Février'!U9,'Mars'!U9,'Avril'!U9,'Mai'!U9,'Juin'!U9,'Juillet'!U9,'Août'!U9,'Septembre'!U9,'Octobre'!U9,'Novembre'!U9,'Décembre'!U9)),CHOOSE($Z$3,'Janvier'!U9,'Février'!U9,'Mars'!U9,'Avril'!U9,'Mai'!U9,'Juin'!U9,'Juillet'!U9,'Août'!U9,'Septembre'!U9,'Octobre'!U9,'Novembre'!U9,'Décembre'!U9),"") | AH7: =IF(ISNUMBER(CHOOSE($Z$3,'Janvier'!V9,'Février'!V9,'Mars'!V9,'Avril'!V9,'Mai'!V9,'Juin'!V9,'Juillet'!V9,'Août'!V9,'Septembre'!V9,'Octobre'!V9,'Novembre'!V9,'Décembre'!V9)),CHOOSE($Z$3,'Janvier'!V9,'Février'!V9,'Mars'!V9,'Avril'!V9,'Mai'!V9,'Juin'!V9,'Juillet'!V9,'Août'!V9,'Septembre'!V9,'Octobre'!V9,'Novembre'!V9,'Décembre'!V9),"") | AI7: =IF(ISNUMBER(CHOOSE($Z$3,'Janvier'!W9,'Février'!W9,'Mars'!W9,'Avril'!W9,'Mai'!W9,'Juin'!W9,'Juillet'!W9,'Août'!W9,'Septembre'!W9,'Octobre'!W9,'Novembre'!W9,'Décembre'!W9)),CHOOSE($Z$3,'Janvier'!W9,'Février'!W9,'Mars'!W9,'Avril'!W9,'Mai'!W9,'Juin'!W9,'Juillet'!W9,'Août'!W9,'Septembre'!W9,'Octobre'!W9,'Novembre'!W9,'Décembre'!W9),"") | AJ7: =IF(Produits!$A$8="","",Produits!$D$8) | AK7: =IF(ISNUMBER(CHOOSE($Z$3,'Janvier'!X9,'Février'!X9,'Mars'!X9,'Avril'!X9,'Mai'!X9,'Juin'!X9,'Juillet'!X9,'Août'!X9,'Septembre'!X9,'Octobre'!X9,'Novembre'!X9,'Décembre'!X9)),CHOOSE($Z$3,'Janvier'!X9,'Février'!X9,'Mars'!X9,'Avril'!X9,'Mai'!X9,'Juin'!X9,'Juillet'!X9,'Août'!X9,'Septembre'!X9,'Octobre'!X9,'Novembre'!X9,'Décembre'!X9),"") | AL7: =IF(AND(ISNUMBER(AI7),ISNUMBER(AJ7)),IF(AI7<=AJ7,1,0),0) | AM7: =IF(OR(AA7="",AK7=""),-1,AK7+ROW()/1000000)
Z8: Avril | AA8: =IF(Produits!$A$9="","",Produits!$A$9) | AB8: =IF(ISNUMBER(CHOOSE($Z$3,'Janvier'!E10,'Février'!E10,'Mars'!E10,'Avril'!E10,'Mai'!E10,'Juin'!E10,'Juillet'!E10,'Août'!E10,'Septembre'!E10,'Octobre'!E10,'Novembre'!E10,'Décembre'!E10)),CHOOSE($Z$3,'Janvier'!E10,'Février'!E10,'Mars'!E10,'Avril'!E10,'Mai'!E10,'Juin'!E10,'Juillet'!E10,'Août'!E10,'Septembre'!E10,'Octobre'!E10,'Novembre'!E10,'Décembre'!E10),"") | AC8: =IF(ISNUMBER(CHOOSE($Z$3,'Janvier'!I10,'Février'!I10,'Mars'!I10,'Avril'!I10,'Mai'!I10,'Juin'!I10,'Juillet'!I10,'Août'!I10,'Septembre'!I10,'Octobre'!I10,'Novembre'!I10,'Décembre'!I10)),CHOOSE($Z$3,'Janvier'!I10,'Février'!I10,'Mars'!I10,'Avril'!I10,'Mai'!I10,'Juin'!I10,'Juillet'!I10,'Août'!I10,'Septembre'!I10,'Octobre'!I10,'Novembre'!I10,'Décembre'!I10),"") | AD8: =IF(ISNUMBER(CHOOSE($Z$3,'Janvier'!M10,'Février'!M10,'Mars'!M10,'Avril'!M10,'Mai'!M10,'Juin'!M10,'Juillet'!M10,'Août'!M10,'Septembre'!M10,'Octobre'!M10,'Novembre'!M10,'Décembre'!M10)),CHOOSE($Z$3,'Janvier'!M10,'Février'!M10,'Mars'!M10,'Avril'!M10,'Mai'!M10,'Juin'!M10,'Juillet'!M10,'Août'!M10,'Septembre'!M10,'Octobre'!M10,'Novembre'!M10,'Décembre'!M10),"") | AE8: =IF(ISNUMBER(CHOOSE($Z$3,'Janvier'!Q10,'Février'!Q10,'Mars'!Q10,'Avril'!Q10,'Mai'!Q10,'Juin'!Q10,'Juillet'!Q10,'Août'!Q10,'Septembre'!Q10,'Octobre'!Q10,'Novembre'!Q10,'Décembre'!Q10)),CHOOSE($Z$3,'Janvier'!Q10,'Février'!Q10,'Mars'!Q10,'Avril'!Q10,'Mai'!Q10,'Juin'!Q10,'Juillet'!Q10,'Août'!Q10,'Septembre'!Q10,'Octobre'!Q10,'Novembre'!Q10,'Décembre'!Q10),"") | AF8: =IF(ISNUMBER(CHOOSE($Z$3,'Janvier'!T10,'Février'!T10,'Mars'!T10,'Avril'!T10,'Mai'!T10,'Juin'!T10,'Juillet'!T10,'Août'!T10,'Septembre'!T10,'Octobre'!T10,'Novembre'!T10,'Décembre'!T10)),CHOOSE($Z$3,'Janvier'!T10,'Février'!T10,'Mars'!T10,'Avril'!T10,'Mai'!T10,'Juin'!T10,'Juillet'!T10,'Août'!T10,'Septembre'!T10,'Octobre'!T10,'Novembre'!T10,'Décembre'!T10),"") | AG8: =IF(ISNUMBER(CHOOSE($Z$3,'Janvier'!U10,'Février'!U10,'Mars'!U10,'Avril'!U10,'Mai'!U10,'Juin'!U10,'Juillet'!U10,'Août'!U10,'Septembre'!U10,'Octobre'!U10,'Novembre'!U10,'Décembre'!U10)),CHOOSE($Z$3,'Janvier'!U10,'Février'!U10,'Mars'!U10,'Avril'!U10,'Mai'!U10,'Juin'!U10,'Juillet'!U10,'Août'!U10,'Septembre'!U10,'Octobre'!U10,'Novembre'!U10,'Décembre'!U10),"") | AH8: =IF(ISNUMBER(CHOOSE($Z$3,'Janvier'!V10,'Février'!V10,'Mars'!V10,'Avril'!V10,'Mai'!V10,'Juin'!V10,'Juillet'!V10,'Août'!V10,'Septembre'!V10,'Octobre'!V10,'Novembre'!V10,'Décembre'!V10)),CHOOSE($Z$3,'Janvier'!V10,'Février'!V10,'Mars'!V10,'Avril'!V10,'Mai'!V10,'Juin'!V10,'Juillet'!V10,'Août'!V10,'Septembre'!V10,'Octobre'!V10,'Novembre'!V10,'Décembre'!V10),"") | AI8: =IF(ISNUMBER(CHOOSE($Z$3,'Janvier'!W10,'Février'!W10,'Mars'!W10,'Avril'!W10,'Mai'!W10,'Juin'!W10,'Juillet'!W10,'Août'!W10,'Septembre'!W10,'Octobre'!W10,'Novembre'!W10,'Décembre'!W10)),CHOOSE($Z$3,'Janvier'!W10,'Février'!W10,'Mars'!W10,'Avril'!W10,'Mai'!W10,'Juin'!W10,'Juillet'!W10,'Août'!W10,'Septembre'!W10,'Octobre'!W10,'Novembre'!W10,'Décembre'!W10),"") | AJ8: =IF(Produits!$A$9="","",Produits!$D$9) | AK8: =IF(ISNUMBER(CHOOSE($Z$3,'Janvier'!X10,'Février'!X10,'Mars'!X10,'Avril'!X10,'Mai'!X10,'Juin'!X10,'Juillet'!X10,'Août'!X10,'Septembre'!X10,'Octobre'!X10,'Novembre'!X10,'Décembre'!X10)),CHOOSE($Z$3,'Janvier'!X10,'Février'!X10,'Mars'!X10,'Avril'!X10,'Mai'!X10,'Juin'!X10,'Juillet'!X10,'Août'!X10,'Septembre'!X10,'Octobre'!X10,'Novembre'!X10,'Décembre'!X10),"") | AL8: =IF(AND(ISNUMBER(AI8),ISNUMBER(AJ8)),IF(AI8<=AJ8,1,0),0) | AM8: =IF(OR(AA8="",AK8=""),-1,AK8+ROW()/1000000)
Z9: Mai | AA9: =IF(Produits!$A$10="","",Produits!$A$10) | AB9: =IF(ISNUMBER(CHOOSE($Z$3,'Janvier'!E11,'Février'!E11,'Mars'!E11,'Avril'!E11,'Mai'!E11,'Juin'!E11,'Juillet'!E11,'Août'!E11,'Septembre'!E11,'Octobre'!E11,'Novembre'!E11,'Décembre'!E11)),CHOOSE($Z$3,'Janvier'!E11,'Février'!E11,'Mars'!E11,'Avril'!E11,'Mai'!E11,'Juin'!E11,'Juillet'!E11,'Août'!E11,'Septembre'!E11,'Octobre'!E11,'Novembre'!E11,'Décembre'!E11),"") | AC9: =IF(ISNUMBER(CHOOSE($Z$3,'Janvier'!I11,'Février'!I11,'Mars'!I11,'Avril'!I11,'Mai'!I11,'Juin'!I11,'Juillet'!I11,'Août'!I11,'Septembre'!I11,'Octobre'!I11,'Novembre'!I11,'Décembre'!I11)),CHOOSE($Z$3,'Janvier'!I11,'Février'!I11,'Mars'!I11,'Avril'!I11,'Mai'!I11,'Juin'!I11,'Juillet'!I11,'Août'!I11,'Septembre'!I11,'Octobre'!I11,'Novembre'!I11,'Décembre'!I11),"") | AD9: =IF(ISNUMBER(CHOOSE($Z$3,'Janvier'!M11,'Février'!M11,'Mars'!M11,'Avril'!M11,'Mai'!M11,'Juin'!M11,'Juillet'!M11,'Août'!M11,'Septembre'!M11,'Octobre'!M11,'Novembre'!M11,'Décembre'!M11)),CHOOSE($Z$3,'Janvier'!M11,'Février'!M11,'Mars'!M11,'Avril'!M11,'Mai'!M11,'Juin'!M11,'Juillet'!M11,'Août'!M11,'Septembre'!M11,'Octobre'!M11,'Novembre'!M11,'Décembre'!M11),"") | AE9: =IF(ISNUMBER(CHOOSE($Z$3,'Janvier'!Q11,'Février'!Q11,'Mars'!Q11,'Avril'!Q11,'Mai'!Q11,'Juin'!Q11,'Juillet'!Q11,'Août'!Q11,'Septembre'!Q11,'Octobre'!Q11,'Novembre'!Q11,'Décembre'!Q11)),CHOOSE($Z$3,'Janvier'!Q11,'Février'!Q11,'Mars'!Q11,'Avril'!Q11,'Mai'!Q11,'Juin'!Q11,'Juillet'!Q11,'Août'!Q11,'Septembre'!Q11,'Octobre'!Q11,'Novembre'!Q11,'Décembre'!Q11),"") | AF9: =IF(ISNUMBER(CHOOSE($Z$3,'Janvier'!T11,'Février'!T11,'Mars'!T11,'Avril'!T11,'Mai'!T11,'Juin'!T11,'Juillet'!T11,'Août'!T11,'Septembre'!T11,'Octobre'!T11,'Novembre'!T11,'Décembre'!T11)),CHOOSE($Z$3,'Janvier'!T11,'Février'!T11,'Mars'!T11,'Avril'!T11,'Mai'!T11,'Juin'!T11,'Juillet'!T11,'Août'!T11,'Septembre'!T11,'Octobre'!T11,'Novembre'!T11,'Décembre'!T11),"") | AG9: =IF(ISNUMBER(CHOOSE($Z$3,'Janvier'!U11,'Février'!U11,'Mars'!U11,'Avril'!U11,'Mai'!U11,'Juin'!U11,'Juillet'!U11,'Août'!U11,'Septembre'!U11,'Octobre'!U11,'Novembre'!U11,'Décembre'!U11)),CHOOSE($Z$3,'Janvier'!U11,'Février'!U11,'Mars'!U11,'Avril'!U11,'Mai'!U11,'Juin'!U11,'Juillet'!U11,'Août'!U11,'Septembre'!U11,'Octobre'!U11,'Novembre'!U11,'Décembre'!U11),"") | AH9: =IF(ISNUMBER(CHOOSE($Z$3,'Janvier'!V11,'Février'!V11,'Mars'!V11,'Avril'!V11,'Mai'!V11,'Juin'!V11,'Juillet'!V11,'Août'!V11,'Septembre'!V11,'Octobre'!V11,'Novembre'!V11,'Décembre'!V11)),CHOOSE($Z$3,'Janvier'!V11,'Février'!V11,'Mars'!V11,'Avril'!V11,'Mai'!V11,'Juin'!V11,'Juillet'!V11,'Août'!V11,'Septembre'!V11,'Octobre'!V11,'Novembre'!V11,'Décembre'!V11),"") | AI9: =IF(ISNUMBER(CHOOSE($Z$3,'Janvier'!W11,'Février'!W11,'Mars'!W11,'Avril'!W11,'Mai'!W11,'Juin'!W11,'Juillet'!W11,'Août'!W11,'Septembre'!W11,'Octobre'!W11,'Novembre'!W11,'Décembre'!W11)),CHOOSE($Z$3,'Janvier'!W11,'Février'!W11,'Mars'!W11,'Avril'!W11,'Mai'!W11,'Juin'!W11,'Juillet'!W11,'Août'!W11,'Septembre'!W11,'Octobre'!W11,'Novembre'!W11,'Décembre'!W11),"") | AJ9: =IF(Produits!$A$10="","",Produits!$D$10) | AK9: =IF(ISNUMBER(CHOOSE($Z$3,'Janvier'!X11,'Février'!X11,'Mars'!X11,'Avril'!X11,'Mai'!X11,'Juin'!X11,'Juillet'!X11,'Août'!X11,'Septembre'!X11,'Octobre'!X11,'Novembre'!X11,'Décembre'!X11)),CHOOSE($Z$3,'Janvier'!X11,'Février'!X11,'Mars'!X11,'Avril'!X11,'Mai'!X11,'Juin'!X11,'Juillet'!X11,'Août'!X11,'Septembre'!X11,'Octobre'!X11,'Novembre'!X11,'Décembre'!X11),"") | AL9: =IF(AND(ISNUMBER(AI9),ISNUMBER(AJ9)),IF(AI9<=AJ9,1,0),0) | AM9: =IF(OR(AA9="",AK9=""),-1,AK9+ROW()/1000000)
A10: Top 10 des dépenses du mois | Z10: Juin | AA10: =IF(Produits!$A$11="","",Produits!$A$11) | AB10: =IF(ISNUMBER(CHOOSE($Z$3,'Janvier'!E12,'Février'!E12,'Mars'!E12,'Avril'!E12,'Mai'!E12,'Juin'!E12,'Juillet'!E12,'Août'!E12,'Septembre'!E12,'Octobre'!E12,'Novembre'!E12,'Décembre'!E12)),CHOOSE($Z$3,'Janvier'!E12,'Février'!E12,'Mars'!E12,'Avril'!E12,'Mai'!E12,'Juin'!E12,'Juillet'!E12,'Août'!E12,'Septembre'!E12,'Octobre'!E12,'Novembre'!E12,'Décembre'!E12),"") | AC10: =IF(ISNUMBER(CHOOSE($Z$3,'Janvier'!I12,'Février'!I12,'Mars'!I12,'Avril'!I12,'Mai'!I12,'Juin'!I12,'Juillet'!I12,'Août'!I12,'Septembre'!I12,'Octobre'!I12,'Novembre'!I12,'Décembre'!I12)),CHOOSE($Z$3,'Janvier'!I12,'Février'!I12,'Mars'!I12,'Avril'!I12,'Mai'!I12,'Juin'!I12,'Juillet'!I12,'Août'!I12,'Septembre'!I12,'Octobre'!I12,'Novembre'!I12,'Décembre'!I12),"") | AD10: =IF(ISNUMBER(CHOOSE($Z$3,'Janvier'!M12,'Février'!M12,'Mars'!M12,'Avril'!M12,'Mai'!M12,'Juin'!M12,'Juillet'!M12,'Août'!M12,'Septembre'!M12,'Octobre'!M12,'Novembre'!M12,'Décembre'!M12)),CHOOSE($Z$3,'Janvier'!M12,'Février'!M12,'Mars'!M12,'Avril'!M12,'Mai'!M12,'Juin'!M12,'Juillet'!M12,'Août'!M12,'Septembre'!M12,'Octobre'!M12,'Novembre'!M12,'Décembre'!M12),"") | AE10: =IF(ISNUMBER(CHOOSE($Z$3,'Janvier'!Q12,'Février'!Q12,'Mars'!Q12,'Avril'!Q12,'Mai'!Q12,'Juin'!Q12,'Juillet'!Q12,'Août'!Q12,'Septembre'!Q12,'Octobre'!Q12,'Novembre'!Q12,'Décembre'!Q12)),CHOOSE($Z$3,'Janvier'!Q12,'Février'!Q12,'Mars'!Q12,'Avril'!Q12,'Mai'!Q12,'Juin'!Q12,'Juillet'!Q12,'Août'!Q12,'Septembre'!Q12,'Octobre'!Q12,'Novembre'!Q12,'Décembre'!Q12),"") | AF10: =IF(ISNUMBER(CHOOSE($Z$3,'Janvier'!T12,'Février'!T12,'Mars'!T12,'Avril'!T12,'Mai'!T12,'Juin'!T12,'Juillet'!T12,'Août'!T12,'Septembre'!T12,'Octobre'!T12,'Novembre'!T12,'Décembre'!T12)),CHOOSE($Z$3,'Janvier'!T12,'Février'!T12,'Mars'!T12,'Avril'!T12,'Mai'!T12,'Juin'!T12,'Juillet'!T12,'Août'!T12,'Septembre'!T12,'Octobre'!T12,'Novembre'!T12,'Décembre'!T12),"") | AG10: =IF(ISNUMBER(CHOOSE($Z$3,'Janvier'!U12,'Février'!U12,'Mars'!U12,'Avril'!U12,'Mai'!U12,'Juin'!U12,'Juillet'!U12,'Août'!U12,'Septembre'!U12,'Octobre'!U12,'Novembre'!U12,'Décembre'!U12)),CHOOSE($Z$3,'Janvier'!U12,'Février'!U12,'Mars'!U12,'Avril'!U12,'Mai'!U12,'Juin'!U12,'Juillet'!U12,'Août'!U12,'Septembre'!U12,'Octobre'!U12,'Novembre'!U12,'Décembre'!U12),"") | AH10: =IF(ISNUMBER(CHOOSE($Z$3,'Janvier'!V12,'Février'!V12,'Mars'!V12,'Avril'!V12,'Mai'!V12,'Juin'!V12,'Juillet'!V12,'Août'!V12,'Septembre'!V12,'Octobre'!V12,'Novembre'!V12,'Décembre'!V12)),CHOOSE($Z$3,'Janvier'!V12,'Février'!V12,'Mars'!V12,'Avril'!V12,'Mai'!V12,'Juin'!V12,'Juillet'!V12,'Août'!V12,'Septembre'!V12,'Octobre'!V12,'Novembre'!V12,'Décembre'!V12),"") | AI10: =IF(ISNUMBER(CHOOSE($Z$3,'Janvier'!W12,'Février'!W12,'Mars'!W12,'Avril'!W12,'Mai'!W12,'Juin'!W12,'Juillet'!W12,'Août'!W12,'Septembre'!W12,'Octobre'!W12,'Novembre'!W12,'Décembre'!W12)),CHOOSE($Z$3,'Janvier'!W12,'Février'!W12,'Mars'!W12,'Avril'!W12,'Mai'!W12,'Juin'!W12,'Juillet'!W12,'Août'!W12,'Septembre'!W12,'Octobre'!W12,'Novembre'!W12,'Décembre'!W12),"") | AJ10: =IF(Produits!$A$11="","",Produits!$D$11) | AK10: =IF(ISNUMBER(CHOOSE($Z$3,'Janvier'!X12,'Février'!X12,'Mars'!X12,'Avril'!X12,'Mai'!X12,'Juin'!X12,'Juillet'!X12,'Août'!X12,'Septembre'!X12,'Octobre'!X12,'Novembre'!X12,'Décembre'!X12)),CHOOSE($Z$3,'Janvier'!X12,'Février'!X12,'Mars'!X12,'Avril'!X12,'Mai'!X12,'Juin'!X12,'Juillet'!X12,'Août'!X12,'Septembre'!X12,'Octobre'!X12,'Novembre'!X12,'Décembre'!X12),"") | AL10: =IF(AND(ISNUMBER(AI10),ISNUMBER(AJ10)),IF(AI10<=AJ10,1,0),0) | AM10: =IF(OR(AA10="",AK10=""),-1,AK10+ROW()/1000000)
A11: Rang | B11: Produit | D11: Reçu | E11: Dépense (€) | Z11: Juillet | AA11: =IF(Produits!$A$12="","",Produits!$A$12) | AB11: =IF(ISNUMBER(CHOOSE($Z$3,'Janvier'!E13,'Février'!E13,'Mars'!E13,'Avril'!E13,'Mai'!E13,'Juin'!E13,'Juillet'!E13,'Août'!E13,'Septembre'!E13,'Octobre'!E13,'Novembre'!E13,'Décembre'!E13)),CHOOSE($Z$3,'Janvier'!E13,'Février'!E13,'Mars'!E13,'Avril'!E13,'Mai'!E13,'Juin'!E13,'Juillet'!E13,'Août'!E13,'Septembre'!E13,'Octobre'!E13,'Novembre'!E13,'Décembre'!E13),"") | AC11: =IF(ISNUMBER(CHOOSE($Z$3,'Janvier'!I13,'Février'!I13,'Mars'!I13,'Avril'!I13,'Mai'!I13,'Juin'!I13,'Juillet'!I13,'Août'!I13,'Septembre'!I13,'Octobre'!I13,'Novembre'!I13,'Décembre'!I13)),CHOOSE($Z$3,'Janvier'!I13,'Février'!I13,'Mars'!I13,'Avril'!I13,'Mai'!I13,'Juin'!I13,'Juillet'!I13,'Août'!I13,'Septembre'!I13,'Octobre'!I13,'Novembre'!I13,'Décembre'!I13),"") | AD11: =IF(ISNUMBER(CHOOSE($Z$3,'Janvier'!M13,'Février'!M13,'Mars'!M13,'Avril'!M13,'Mai'!M13,'Juin'!M13,'Juillet'!M13,'Août'!M13,'Septembre'!M13,'Octobre'!M13,'Novembre'!M13,'Décembre'!M13)),CHOOSE($Z$3,'Janvier'!M13,'Février'!M13,'Mars'!M13,'Avril'!M13,'Mai'!M13,'Juin'!M13,'Juillet'!M13,'Août'!M13,'Septembre'!M13,'Octobre'!M13,'Novembre'!M13,'Décembre'!M13),"") | AE11: =IF(ISNUMBER(CHOOSE($Z$3,'Janvier'!Q13,'Février'!Q13,'Mars'!Q13,'Avril'!Q13,'Mai'!Q13,'Juin'!Q13,'Juillet'!Q13,'Août'!Q13,'Septembre'!Q13,'Octobre'!Q13,'Novembre'!Q13,'Décembre'!Q13)),CHOOSE($Z$3,'Janvier'!Q13,'Février'!Q13,'Mars'!Q13,'Avril'!Q13,'Mai'!Q13,'Juin'!Q13,'Juillet'!Q13,'Août'!Q13,'Septembre'!Q13,'Octobre'!Q13,'Novembre'!Q13,'Décembre'!Q13),"") | AF11: =IF(ISNUMBER(CHOOSE($Z$3,'Janvier'!T13,'Février'!T13,'Mars'!T13,'Avril'!T13,'Mai'!T13,'Juin'!T13,'Juillet'!T13,'Août'!T13,'Septembre'!T13,'Octobre'!T13,'Novembre'!T13,'Décembre'!T13)),CHOOSE($Z$3,'Janvier'!T13,'Février'!T13,'Mars'!T13,'Avril'!T13,'Mai'!T13,'Juin'!T13,'Juillet'!T13,'Août'!T13,'Septembre'!T13,'Octobre'!T13,'Novembre'!T13,'Décembre'!T13),"") | AG11: =IF(ISNUMBER(CHOOSE($Z$3,'Janvier'!U13,'Février'!U13,'Mars'!U13,'Avril'!U13,'Mai'!U13,'Juin'!U13,'Juillet'!U13,'Août'!U13,'Septembre'!U13,'Octobre'!U13,'Novembre'!U13,'Décembre'!U13)),CHOOSE($Z$3,'Janvier'!U13,'Février'!U13,'Mars'!U13,'Avril'!U13,'Mai'!U13,'Juin'!U13,'Juillet'!U13,'Août'!U13,'Septembre'!U13,'Octobre'!U13,'Novembre'!U13,'Décembre'!U13),"") | AH11: =IF(ISNUMBER(CHOOSE($Z$3,'Janvier'!V13,'Février'!V13,'Mars'!V13,'Avril'!V13,'Mai'!V13,'Juin'!V13,'Juillet'!V13,'Août'!V13,'Septembre'!V13,'Octobre'!V13,'Novembre'!V13,'Décembre'!V13)),CHOOSE($Z$3,'Janvier'!V13,'Février'!V13,'Mars'!V13,'Avril'!V13,'Mai'!V13,'Juin'!V13,'Juillet'!V13,'Août'!V13,'Septembre'!V13,'Octobre'!V13,'Novembre'!V13,'Décembre'!V13),"") | AI11: =IF(ISNUMBER(CHOOSE($Z$3,'Janvier'!W13,'Février'!W13,'Mars'!W13,'Avril'!W13,'Mai'!W13,'Juin'!W13,'Juillet'!W13,'Août'!W13,'Septembre'!W13,'Octobre'!W13,'Novembre'!W13,'Décembre'!W13)),CHOOSE($Z$3,'Janvier'!W13,'Février'!W13,'Mars'!W13,'Avril'!W13,'Mai'!W13,'Juin'!W13,'Juillet'!W13,'Août'!W13,'Septembre'!W13,'Octobre'!W13,'Novembre'!W13,'Décembre'!W13),"") | AJ11: =IF(Produits!$A$12="","",Produits!$D$12) | AK11: =IF(ISNUMBER(CHOOSE($Z$3,'Janvier'!X13,'Février'!X13,'Mars'!X13,'Avril'!X13,'Mai'!X13,'Juin'!X13,'Juillet'!X13,'Août'!X13,'Septembre'!X13,'Octobre'!X13,'Novembre'!X13,'Décembre'!X13)),CHOOSE($Z$3,'Janvier'!X13,'Février'!X13,'Mars'!X13,'Avril'!X13,'Mai'!X13,'Juin'!X13,'Juillet'!X13,'Août'!X13,'Septembre'!X13,'Octobre'!X13,'Novembre'!X13,'Décembre'!X13),"") | AL11: =IF(AND(ISNUMBER(AI11),ISNUMBER(AJ11)),IF(AI11<=AJ11,1,0),0) | AM11: =IF(OR(AA11="",AK11=""),-1,AK11+ROW()/1000000)
A12: 1 | B12: =IF(LARGE($AM$5:$AM$64,1)<=0,"",INDEX($AA$5:$AA$64,MATCH(LARGE($AM$5:$AM$64,1),$AM$5:$AM$64,0))) | D12: =IF(B12="","",INDEX($AG$5:$AG$64,MATCH(LARGE($AM$5:$AM$64,1),$AM$5:$AM$64,0))) | E12: =IF(B12="","",INDEX($AK$5:$AK$64,MATCH(LARGE($AM$5:$AM$64,1),$AM$5:$AM$64,0))) | Z12: Août | AA12: =IF(Produits!$A$13="","",Produits!$A$13) | AB12: =IF(ISNUMBER(CHOOSE($Z$3,'Janvier'!E14,'Février'!E14,'Mars'!E14,'Avril'!E14,'Mai'!E14,'Juin'!E14,'Juillet'!E14,'Août'!E14,'Septembre'!E14,'Octobre'!E14,'Novembre'!E14,'Décembre'!E14)),CHOOSE($Z$3,'Janvier'!E14,'Février'!E14,'Mars'!E14,'Avril'!E14,'Mai'!E14,'Juin'!E14,'Juillet'!E14,'Août'!E14,'Septembre'!E14,'Octobre'!E14,'Novembre'!E14,'Décembre'!E14),"") | AC12: =IF(ISNUMBER(CHOOSE($Z$3,'Janvier'!I14,'Février'!I14,'Mars'!I14,'Avril'!I14,'Mai'!I14,'Juin'!I14,'Juillet'!I14,'Août'!I14,'Septembre'!I14,'Octobre'!I14,'Novembre'!I14,'Décembre'!I14)),CHOOSE($Z$3,'Janvier'!I14,'Février'!I14,'Mars'!I14,'Avril'!I14,'Mai'!I14,'Juin'!I14,'Juillet'!I14,'Août'!I14,'Septembre'!I14,'Octobre'!I14,'Novembre'!I14,'Décembre'!I14),"") | AD12: =IF(ISNUMBER(CHOOSE($Z$3,'Janvier'!M14,'Février'!M14,'Mars'!M14,'Avril'!M14,'Mai'!M14,'Juin'!M14,'Juillet'!M14,'Août'!M14,'Septembre'!M14,'Octobre'!M14,'Novembre'!M14,'Décembre'!M14)),CHOOSE($Z$3,'Janvier'!M14,'Février'!M14,'Mars'!M14,'Avril'!M14,'Mai'!M14,'Juin'!M14,'Juillet'!M14,'Août'!M14,'Septembre'!M14,'Octobre'!M14,'Novembre'!M14,'Décembre'!M14),"") | AE12: =IF(ISNUMBER(CHOOSE($Z$3,'Janvier'!Q14,'Février'!Q14,'Mars'!Q14,'Avril'!Q14,'Mai'!Q14,'Juin'!Q14,'Juillet'!Q14,'Août'!Q14,'Septembre'!Q14,'Octobre'!Q14,'Novembre'!Q14,'Décembre'!Q14)),CHOOSE($Z$3,'Janvier'!Q14,'Février'!Q14,'Mars'!Q14,'Avril'!Q14,'Mai'!Q14,'Juin'!Q14,'Juillet'!Q14,'Août'!Q14,'Septembre'!Q14,'Octobre'!Q14,'Novembre'!Q14,'Décembre'!Q14),"") | AF12: =IF(ISNUMBER(CHOOSE($Z$3,'Janvier'!T14,'Février'!T14,'Mars'!T14,'Avril'!T14,'Mai'!T14,'Juin'!T14,'Juillet'!T14,'Août'!T14,'Septembre'!T14,'Octobre'!T14,'Novembre'!T14,'Décembre'!T14)),CHOOSE($Z$3,'Janvier'!T14,'Février'!T14,'Mars'!T14,'Avril'!T14,'Mai'!T14,'Juin'!T14,'Juillet'!T14,'Août'!T14,'Septembre'!T14,'Octobre'!T14,'Novembre'!T14,'Décembre'!T14),"") | AG12: =IF(ISNUMBER(CHOOSE($Z$3,'Janvier'!U14,'Février'!U14,'Mars'!U14,'Avril'!U14,'Mai'!U14,'Juin'!U14,'Juillet'!U14,'Août'!U14,'Septembre'!U14,'Octobre'!U14,'Novembre'!U14,'Décembre'!U14)),CHOOSE($Z$3,'Janvier'!U14,'Février'!U14,'Mars'!U14,'Avril'!U14,'Mai'!U14,'Juin'!U14,'Juillet'!U14,'Août'!U14,'Septembre'!U14,'Octobre'!U14,'Novembre'!U14,'Décembre'!U14),"") | AH12: =IF(ISNUMBER(CHOOSE($Z$3,'Janvier'!V14,'Février'!V14,'Mars'!V14,'Avril'!V14,'Mai'!V14,'Juin'!V14,'Juillet'!V14,'Août'!V14,'Septembre'!V14,'Octobre'!V14,'Novembre'!V14,'Décembre'!V14)),CHOOSE($Z$3,'Janvier'!V14,'Février'!V14,'Mars'!V14,'Avril'!V14,'Mai'!V14,'Juin'!V14,'Juillet'!V14,'Août'!V14,'Septembre'!V14,'Octobre'!V14,'Novembre'!V14,'Décembre'!V14),"") | AI12: =IF(ISNUMBER(CHOOSE($Z$3,'Janvier'!W14,'Février'!W14,'Mars'!W14,'Avril'!W14,'Mai'!W14,'Juin'!W14,'Juillet'!W14,'Août'!W14,'Septembre'!W14,'Octobre'!W14,'Novembre'!W14,'Décembre'!W14)),CHOOSE($Z$3,'Janvier'!W14,'Février'!W14,'Mars'!W14,'Avril'!W14,'Mai'!W14,'Juin'!W14,'Juillet'!W14,'Août'!W14,'Septembre'!W14,'Octobre'!W14,'Novembre'!W14,'Décembre'!W14),"") | AJ12: =IF(Produits!$A$13="","",Produits!$D$13) | AK12: =IF(ISNUMBER(CHOOSE($Z$3,'Janvier'!X14,'Février'!X14,'Mars'!X14,'Avril'!X14,'Mai'!X14,'Juin'!X14,'Juillet'!X14,'Août'!X14,'Septembre'!X14,'Octobre'!X14,'Novembre'!X14,'Décembre'!X14)),CHOOSE($Z$3,'Janvier'!X14,'Février'!X14,'Mars'!X14,'Avril'!X14,'Mai'!X14,'Juin'!X14,'Juillet'!X14,'Août'!X14,'Septembre'!X14,'Octobre'!X14,'Novembre'!X14,'Décembre'!X14),"") | AL12: =IF(AND(ISNUMBER(AI12),ISNUMBER(AJ12)),IF(AI12<=AJ12,1,0),0) | AM12: =IF(OR(AA12="",AK12=""),-1,AK12+ROW()/1000000)
A13: 2 | B13: =IF(LARGE($AM$5:$AM$64,2)<=0,"",INDEX($AA$5:$AA$64,MATCH(LARGE($AM$5:$AM$64,2),$AM$5:$AM$64,0))) | D13: =IF(B13="","",INDEX($AG$5:$AG$64,MATCH(LARGE($AM$5:$AM$64,2),$AM$5:$AM$64,0))) | E13: =IF(B13="","",INDEX($AK$5:$AK$64,MATCH(LARGE($AM$5:$AM$64,2),$AM$5:$AM$64,0))) | Z13: Septembre | AA13: =IF(Produits!$A$14="","",Produits!$A$14) | AB13: =IF(ISNUMBER(CHOOSE($Z$3,'Janvier'!E15,'Février'!E15,'Mars'!E15,'Avril'!E15,'Mai'!E15,'Juin'!E15,'Juillet'!E15,'Août'!E15,'Septembre'!E15,'Octobre'!E15,'Novembre'!E15,'Décembre'!E15)),CHOOSE($Z$3,'Janvier'!E15,'Février'!E15,'Mars'!E15,'Avril'!E15,'Mai'!E15,'Juin'!E15,'Juillet'!E15,'Août'!E15,'Septembre'!E15,'Octobre'!E15,'Novembre'!E15,'Décembre'!E15),"") | AC13: =IF(ISNUMBER(CHOOSE($Z$3,'Janvier'!I15,'Février'!I15,'Mars'!I15,'Avril'!I15,'Mai'!I15,'Juin'!I15,'Juillet'!I15,'Août'!I15,'Septembre'!I15,'Octobre'!I15,'Novembre'!I15,'Décembre'!I15)),CHOOSE($Z$3,'Janvier'!I15,'Février'!I15,'Mars'!I15,'Avril'!I15,'Mai'!I15,'Juin'!I15,'Juillet'!I15,'Août'!I15,'Septembre'!I15,'Octobre'!I15,'Novembre'!I15,'Décembre'!I15),"") | AD13: =IF(ISNUMBER(CHOOSE($Z$3,'Janvier'!M15,'Février'!M15,'Mars'!M15,'Avril'!M15,'Mai'!M15,'Juin'!M15,'Juillet'!M15,'Août'!M15,'Septembre'!M15,'Octobre'!M15,'Novembre'!M15,'Décembre'!M15)),CHOOSE($Z$3,'Janvier'!M15,'Février'!M15,'Mars'!M15,'Avril'!M15,'Mai'!M15,'Juin'!M15,'Juillet'!M15,'Août'!M15,'Septembre'!M15,'Octobre'!M15,'Novembre'!M15,'Décembre'!M15),"") | AE13: =IF(ISNUMBER(CHOOSE($Z$3,'Janvier'!Q15,'Février'!Q15,'Mars'!Q15,'Avril'!Q15,'Mai'!Q15,'Juin'!Q15,'Juillet'!Q15,'Août'!Q15,'Septembre'!Q15,'Octobre'!Q15,'Novembre'!Q15,'Décembre'!Q15)),CHOOSE($Z$3,'Janvier'!Q15,'Février'!Q15,'Mars'!Q15,'Avril'!Q15,'Mai'!Q15,'Juin'!Q15,'Juillet'!Q15,'Août'!Q15,'Septembre'!Q15,'Octobre'!Q15,'Novembre'!Q15,'Décembre'!Q15),"") | AF13: =IF(ISNUMBER(CHOOSE($Z$3,'Janvier'!T15,'Février'!T15,'Mars'!T15,'Avril'!T15,'Mai'!T15,'Juin'!T15,'Juillet'!T15,'Août'!T15,'Septembre'!T15,'Octobre'!T15,'Novembre'!T15,'Décembre'!T15)),CHOOSE($Z$3,'Janvier'!T15,'Février'!T15,'Mars'!T15,'Avril'!T15,'Mai'!T15,'Juin'!T15,'Juillet'!T15,'Août'!T15,'Septembre'!T15,'Octobre'!T15,'Novembre'!T15,'Décembre'!T15),"") | AG13: =IF(ISNUMBER(CHOOSE($Z$3,'Janvier'!U15,'Février'!U15,'Mars'!U15,'Avril'!U15,'Mai'!U15,'Juin'!U15,'Juillet'!U15,'Août'!U15,'Septembre'!U15,'Octobre'!U15,'Novembre'!U15,'Décembre'!U15)),CHOOSE($Z$3,'Janvier'!U15,'Février'!U15,'Mars'!U15,'Avril'!U15,'Mai'!U15,'Juin'!U15,'Juillet'!U15,'Août'!U15,'Septembre'!U15,'Octobre'!U15,'Novembre'!U15,'Décembre'!U15),"") | AH13: =IF(ISNUMBER(CHOOSE($Z$3,'Janvier'!V15,'Février'!V15,'Mars'!V15,'Avril'!V15,'Mai'!V15,'Juin'!V15,'Juillet'!V15,'Août'!V15,'Septembre'!V15,'Octobre'!V15,'Novembre'!V15,'Décembre'!V15)),CHOOSE($Z$3,'Janvier'!V15,'Février'!V15,'Mars'!V15,'Avril'!V15,'Mai'!V15,'Juin'!V15,'Juillet'!V15,'Août'!V15,'Septembre'!V15,'Octobre'!V15,'Novembre'!V15,'Décembre'!V15),"") | AI13: =IF(ISNUMBER(CHOOSE($Z$3,'Janvier'!W15,'Février'!W15,'Mars'!W15,'Avril'!W15,'Mai'!W15,'Juin'!W15,'Juillet'!W15,'Août'!W15,'Septembre'!W15,'Octobre'!W15,'Novembre'!W15,'Décembre'!W15)),CHOOSE($Z$3,'Janvier'!W15,'Février'!W15,'Mars'!W15,'Avril'!W15,'Mai'!W15,'Juin'!W15,'Juillet'!W15,'Août'!W15,'Septembre'!W15,'Octobre'!W15,'Novembre'!W15,'Décembre'!W15),"") | AJ13: =IF(Produits!$A$14="","",Produits!$D$14) | AK13: =IF(ISNUMBER(CHOOSE($Z$3,'Janvier'!X15,'Février'!X15,'Mars'!X15,'Avril'!X15,'Mai'!X15,'Juin'!X15,'Juillet'!X15,'Août'!X15,'Septembre'!X15,'Octobre'!X15,'Novembre'!X15,'Décembre'!X15)),CHOOSE($Z$3,'Janvier'!X15,'Février'!X15,'Mars'!X15,'Avril'!X15,'Mai'!X15,'Juin'!X15,'Juillet'!X15,'Août'!X15,'Septembre'!X15,'Octobre'!X15,'Novembre'!X15,'Décembre'!X15),"") | AL13: =IF(AND(ISNUMBER(AI13),ISNUMBER(AJ13)),IF(AI13<=AJ13,1,0),0) | AM13: =IF(OR(AA13="",AK13=""),-1,AK13+ROW()/1000000)
A14: 3 | B14: =IF(LARGE($AM$5:$AM$64,3)<=0,"",INDEX($AA$5:$AA$64,MATCH(LARGE($AM$5:$AM$64,3),$AM$5:$AM$64,0))) | D14: =IF(B14="","",INDEX($AG$5:$AG$64,MATCH(LARGE($AM$5:$AM$64,3),$AM$5:$AM$64,0))) | E14: =IF(B14="","",INDEX($AK$5:$AK$64,MATCH(LARGE($AM$5:$AM$64,3),$AM$5:$AM$64,0))) | Z14: Octobre | AA14: =IF(Produits!$A$15="","",Produits!$A$15) | AB14: =IF(ISNUMBER(CHOOSE($Z$3,'Janvier'!E16,'Février'!E16,'Mars'!E16,'Avril'!E16,'Mai'!E16,'Juin'!E16,'Juillet'!E16,'Août'!E16,'Septembre'!E16,'Octobre'!E16,'Novembre'!E16,'Décembre'!E16)),CHOOSE($Z$3,'Janvier'!E16,'Février'!E16,'Mars'!E16,'Avril'!E16,'Mai'!E16,'Juin'!E16,'Juillet'!E16,'Août'!E16,'Septembre'!E16,'Octobre'!E16,'Novembre'!E16,'Décembre'!E16),"") | AC14: =IF(ISNUMBER(CHOOSE($Z$3,'Janvier'!I16,'Février'!I16,'Mars'!I16,'Avril'!I16,'Mai'!I16,'Juin'!I16,'Juillet'!I16,'Août'!I16,'Septembre'!I16,'Octobre'!I16,'Novembre'!I16,'Décembre'!I16)),CHOOSE($Z$3,'Janvier'!I16,'Février'!I16,'Mars'!I16,'Avril'!I16,'Mai'!I16,'Juin'!I16,'Juillet'!I16,'Août'!I16,'Septembre'!I16,'Octobre'!I16,'Novembre'!I16,'Décembre'!I16),"") | AD14: =IF(ISNUMBER(CHOOSE($Z$3,'Janvier'!M16,'Février'!M16,'Mars'!M16,'Avril'!M16,'Mai'!M16,'Juin'!M16,'Juillet'!M16,'Août'!M16,'Septembre'!M16,'Octobre'!M16,'Novembre'!M16,'Décembre'!M16)),CHOOSE($Z$3,'Janvier'!M16,'Février'!M16,'Mars'!M16,'Avril'!M16,'Mai'!M16,'Juin'!M16,'Juillet'!M16,'Août'!M16,'Septembre'!M16,'Octobre'!M16,'Novembre'!M16,'Décembre'!M16),"") | AE14: =IF(ISNUMBER(CHOOSE($Z$3,'Janvier'!Q16,'Février'!Q16,'Mars'!Q16,'Avril'!Q16,'Mai'!Q16,'Juin'!Q16,'Juillet'!Q16,'Août'!Q16,'Septembre'!Q16,'Octobre'!Q16,'Novembre'!Q16,'Décembre'!Q16)),CHOOSE($Z$3,'Janvier'!Q16,'Février'!Q16,'Mars'!Q16,'Avril'!Q16,'Mai'!Q16,'Juin'!Q16,'Juillet'!Q16,'Août'!Q16,'Septembre'!Q16,'Octobre'!Q16,'Novembre'!Q16,'Décembre'!Q16),"") | AF14: =IF(ISNUMBER(CHOOSE($Z$3,'Janvier'!T16,'Février'!T16,'Mars'!T16,'Avril'!T16,'Mai'!T16,'Juin'!T16,'Juillet'!T16,'Août'!T16,'Septembre'!T16,'Octobre'!T16,'Novembre'!T16,'Décembre'!T16)),CHOOSE($Z$3,'Janvier'!T16,'Février'!T16,'Mars'!T16,'Avril'!T16,'Mai'!T16,'Juin'!T16,'Juillet'!T16,'Août'!T16,'Septembre'!T16,'Octobre'!T16,'Novembre'!T16,'Décembre'!T16),"") | AG14: =IF(ISNUMBER(CHOOSE($Z$3,'Janvier'!U16,'Février'!U16,'Mars'!U16,'Avril'!U16,'Mai'!U16,'Juin'!U16,'Juillet'!U16,'Août'!U16,'Septembre'!U16,'Octobre'!U16,'Novembre'!U16,'Décembre'!U16)),CHOOSE($Z$3,'Janvier'!U16,'Février'!U16,'Mars'!U16,'Avril'!U16,'Mai'!U16,'Juin'!U16,'Juillet'!U16,'Août'!U16,'Septembre'!U16,'Octobre'!U16,'Novembre'!U16,'Décembre'!U16),"") | AH14: =IF(ISNUMBER(CHOOSE($Z$3,'Janvier'!V16,'Février'!V16,'Mars'!V16,'Avril'!V16,'Mai'!V16,'Juin'!V16,'Juillet'!V16,'Août'!V16,'Septembre'!V16,'Octobre'!V16,'Novembre'!V16,'Décembre'!V16)),CHOOSE($Z$3,'Janvier'!V16,'Février'!V16,'Mars'!V16,'Avril'!V16,'Mai'!V16,'Juin'!V16,'Juillet'!V16,'Août'!V16,'Septembre'!V16,'Octobre'!V16,'Novembre'!V16,'Décembre'!V16),"") | AI14: =IF(ISNUMBER(CHOOSE($Z$3,'Janvier'!W16,'Février'!W16,'Mars'!W16,'Avril'!W16,'Mai'!W16,'Juin'!W16,'Juillet'!W16,'Août'!W16,'Septembre'!W16,'Octobre'!W16,'Novembre'!W16,'Décembre'!W16)),CHOOSE($Z$3,'Janvier'!W16,'Février'!W16,'Mars'!W16,'Avril'!W16,'Mai'!W16,'Juin'!W16,'Juillet'!W16,'Août'!W16,'Septembre'!W16,'Octobre'!W16,'Novembre'!W16,'Décembre'!W16),"") | AJ14: =IF(Produits!$A$15="","",Produits!$D$15) | AK14: =IF(ISNUMBER(CHOOSE($Z$3,'Janvier'!X16,'Février'!X16,'Mars'!X16,'Avril'!X16,'Mai'!X16,'Juin'!X16,'Juillet'!X16,'Août'!X16,'Septembre'!X16,'Octobre'!X16,'Novembre'!X16,'Décembre'!X16)),CHOOSE($Z$3,'Janvier'!X16,'Février'!X16,'Mars'!X16,'Avril'!X16,'Mai'!X16,'Juin'!X16,'Juillet'!X16,'Août'!X16,'Septembre'!X16,'Octobre'!X16,'Novembre'!X16,'Décembre'!X16),"") | AL14: =IF(AND(ISNUMBER(AI14),ISNUMBER(AJ14)),IF(AI14<=AJ14,1,0),0) | AM14: =IF(OR(AA14="",AK14=""),-1,AK14+ROW()/1000000)
A15: 4 | B15: =IF(LARGE($AM$5:$AM$64,4)<=0,"",INDEX($AA$5:$AA$64,MATCH(LARGE($AM$5:$AM$64,4),$AM$5:$AM$64,0))) | D15: =IF(B15="","",INDEX($AG$5:$AG$64,MATCH(LARGE($AM$5:$AM$64,4),$AM$5:$AM$64,0))) | E15: =IF(B15="","",INDEX($AK$5:$AK$64,MATCH(LARGE($AM$5:$AM$64,4),$AM$5:$AM$64,0))) | Z15: Novembre | AA15: =IF(Produits!$A$16="","",Produits!$A$16) | AB15: =IF(ISNUMBER(CHOOSE($Z$3,'Janvier'!E17,'Février'!E17,'Mars'!E17,'Avril'!E17,'Mai'!E17,'Juin'!E17,'Juillet'!E17,'Août'!E17,'Septembre'!E17,'Octobre'!E17,'Novembre'!E17,'Décembre'!E17)),CHOOSE($Z$3,'Janvier'!E17,'Février'!E17,'Mars'!E17,'Avril'!E17,'Mai'!E17,'Juin'!E17,'Juillet'!E17,'Août'!E17,'Septembre'!E17,'Octobre'!E17,'Novembre'!E17,'Décembre'!E17),"") | AC15: =IF(ISNUMBER(CHOOSE($Z$3,'Janvier'!I17,'Février'!I17,'Mars'!I17,'Avril'!I17,'Mai'!I17,'Juin'!I17,'Juillet'!I17,'Août'!I17,'Septembre'!I17,'Octobre'!I17,'Novembre'!I17,'Décembre'!I17)),CHOOSE($Z$3,'Janvier'!I17,'Février'!I17,'Mars'!I17,'Avril'!I17,'Mai'!I17,'Juin'!I17,'Juillet'!I17,'Août'!I17,'Septembre'!I17,'Octobre'!I17,'Novembre'!I17,'Décembre'!I17),"") | AD15: =IF(ISNUMBER(CHOOSE($Z$3,'Janvier'!M17,'Février'!M17,'Mars'!M17,'Avril'!M17,'Mai'!M17,'Juin'!M17,'Juillet'!M17,'Août'!M17,'Septembre'!M17,'Octobre'!M17,'Novembre'!M17,'Décembre'!M17)),CHOOSE($Z$3,'Janvier'!M17,'Février'!M17,'Mars'!M17,'Avril'!M17,'Mai'!M17,'Juin'!M17,'Juillet'!M17,'Août'!M17,'Septembre'!M17,'Octobre'!M17,'Novembre'!M17,'Décembre'!M17),"") | AE15: =IF(ISNUMBER(CHOOSE($Z$3,'Janvier'!Q17,'Février'!Q17,'Mars'!Q17,'Avril'!Q17,'Mai'!Q17,'Juin'!Q17,'Juillet'!Q17,'Août'!Q17,'Septembre'!Q17,'Octobre'!Q17,'Novembre'!Q17,'Décembre'!Q17)),CHOOSE($Z$3,'Janvier'!Q17,'Février'!Q17,'Mars'!Q17,'Avril'!Q17,'Mai'!Q17,'Juin'!Q17,'Juillet'!Q17,'Août'!Q17,'Septembre'!Q17,'Octobre'!Q17,'Novembre'!Q17,'Décembre'!Q17),"") | AF15: =IF(ISNUMBER(CHOOSE($Z$3,'Janvier'!T17,'Février'!T17,'Mars'!T17,'Avril'!T17,'Mai'!T17,'Juin'!T17,'Juillet'!T17,'Août'!T17,'Septembre'!T17,'Octobre'!T17,'Novembre'!T17,'Décembre'!T17)),CHOOSE($Z$3,'Janvier'!T17,'Février'!T17,'Mars'!T17,'Avril'!T17,'Mai'!T17,'Juin'!T17,'Juillet'!T17,'Août'!T17,'Septembre'!T17,'Octobre'!T17,'Novembre'!T17,'Décembre'!T17),"") | AG15: =IF(ISNUMBER(CHOOSE($Z$3,'Janvier'!U17,'Février'!U17,'Mars'!U17,'Avril'!U17,'Mai'!U17,'Juin'!U17,'Juillet'!U17,'Août'!U17,'Septembre'!U17,'Octobre'!U17,'Novembre'!U17,'Décembre'!U17)),CHOOSE($Z$3,'Janvier'!U17,'Février'!U17,'Mars'!U17,'Avril'!U17,'Mai'!U17,'Juin'!U17,'Juillet'!U17,'Août'!U17,'Septembre'!U17,'Octobre'!U17,'Novembre'!U17,'Décembre'!U17),"") | AH15: =IF(ISNUMBER(CHOOSE($Z$3,'Janvier'!V17,'Février'!V17,'Mars'!V17,'Avril'!V17,'Mai'!V17,'Juin'!V17,'Juillet'!V17,'Août'!V17,'Septembre'!V17,'Octobre'!V17,'Novembre'!V17,'Décembre'!V17)),CHOOSE($Z$3,'Janvier'!V17,'Février'!V17,'Mars'!V17,'Avril'!V17,'Mai'!V17,'Juin'!V17,'Juillet'!V17,'Août'!V17,'Septembre'!V17,'Octobre'!V17,'Novembre'!V17,'Décembre'!V17),"") | AI15: =IF(ISNUMBER(CHOOSE($Z$3,'Janvier'!W17,'Février'!W17,'Mars'!W17,'Avril'!W17,'Mai'!W17,'Juin'!W17,'Juillet'!W17,'Août'!W17,'Septembre'!W17,'Octobre'!W17,'Novembre'!W17,'Décembre'!W17)),CHOOSE($Z$3,'Janvier'!W17,'Février'!W17,'Mars'!W17,'Avril'!W17,'Mai'!W17,'Juin'!W17,'Juillet'!W17,'Août'!W17,'Septembre'!W17,'Octobre'!W17,'Novembre'!W17,'Décembre'!W17),"") | AJ15: =IF(Produits!$A$16="","",Produits!$D$16) | AK15: =IF(ISNUMBER(CHOOSE($Z$3,'Janvier'!X17,'Février'!X17,'Mars'!X17,'Avril'!X17,'Mai'!X17,'Juin'!X17,'Juillet'!X17,'Août'!X17,'Septembre'!X17,'Octobre'!X17,'Novembre'!X17,'Décembre'!X17)),CHOOSE($Z$3,'Janvier'!X17,'Février'!X17,'Mars'!X17,'Avril'!X17,'Mai'!X17,'Juin'!X17,'Juillet'!X17,'Août'!X17,'Septembre'!X17,'Octobre'!X17,'Novembre'!X17,'Décembre'!X17),"") | AL15: =IF(AND(ISNUMBER(AI15),ISNUMBER(AJ15)),IF(AI15<=AJ15,1,0),0) | AM15: =IF(OR(AA15="",AK15=""),-1,AK15+ROW()/1000000)
A16: 5 | B16: =IF(LARGE($AM$5:$AM$64,5)<=0,"",INDEX($AA$5:$AA$64,MATCH(LARGE($AM$5:$AM$64,5),$AM$5:$AM$64,0))) | D16: =IF(B16="","",INDEX($AG$5:$AG$64,MATCH(LARGE($AM$5:$AM$64,5),$AM$5:$AM$64,0))) | E16: =IF(B16="","",INDEX($AK$5:$AK$64,MATCH(LARGE($AM$5:$AM$64,5),$AM$5:$AM$64,0))) | Z16: Décembre | AA16: =IF(Produits!$A$17="","",Produits!$A$17) | AB16: =IF(ISNUMBER(CHOOSE($Z$3,'Janvier'!E18,'Février'!E18,'Mars'!E18,'Avril'!E18,'Mai'!E18,'Juin'!E18,'Juillet'!E18,'Août'!E18,'Septembre'!E18,'Octobre'!E18,'Novembre'!E18,'Décembre'!E18)),CHOOSE($Z$3,'Janvier'!E18,'Février'!E18,'Mars'!E18,'Avril'!E18,'Mai'!E18,'Juin'!E18,'Juillet'!E18,'Août'!E18,'Septembre'!E18,'Octobre'!E18,'Novembre'!E18,'Décembre'!E18),"") | AC16: =IF(ISNUMBER(CHOOSE($Z$3,'Janvier'!I18,'Février'!I18,'Mars'!I18,'Avril'!I18,'Mai'!I18,'Juin'!I18,'Juillet'!I18,'Août'!I18,'Septembre'!I18,'Octobre'!I18,'Novembre'!I18,'Décembre'!I18)),CHOOSE($Z$3,'Janvier'!I18,'Février'!I18,'Mars'!I18,'Avril'!I18,'Mai'!I18,'Juin'!I18,'Juillet'!I18,'Août'!I18,'Septembre'!I18,'Octobre'!I18,'Novembre'!I18,'Décembre'!I18),"") | AD16: =IF(ISNUMBER(CHOOSE($Z$3,'Janvier'!M18,'Février'!M18,'Mars'!M18,'Avril'!M18,'Mai'!M18,'Juin'!M18,'Juillet'!M18,'Août'!M18,'Septembre'!M18,'Octobre'!M18,'Novembre'!M18,'Décembre'!M18)),CHOOSE($Z$3,'Janvier'!M18,'Février'!M18,'Mars'!M18,'Avril'!M18,'Mai'!M18,'Juin'!M18,'Juillet'!M18,'Août'!M18,'Septembre'!M18,'Octobre'!M18,'Novembre'!M18,'Décembre'!M18),"") | AE16: =IF(ISNUMBER(CHOOSE($Z$3,'Janvier'!Q18,'Février'!Q18,'Mars'!Q18,'Avril'!Q18,'Mai'!Q18,'Juin'!Q18,'Juillet'!Q18,'Août'!Q18,'Septembre'!Q18,'Octobre'!Q18,'Novembre'!Q18,'Décembre'!Q18)),CHOOSE($Z$3,'Janvier'!Q18,'Février'!Q18,'Mars'!Q18,'Avril'!Q18,'Mai'!Q18,'Juin'!Q18,'Juillet'!Q18,'Août'!Q18,'Septembre'!Q18,'Octobre'!Q18,'Novembre'!Q18,'Décembre'!Q18),"") | AF16: =IF(ISNUMBER(CHOOSE($Z$3,'Janvier'!T18,'Février'!T18,'Mars'!T18,'Avril'!T18,'Mai'!T18,'Juin'!T18,'Juillet'!T18,'Août'!T18,'Septembre'!T18,'Octobre'!T18,'Novembre'!T18,'Décembre'!T18)),CHOOSE($Z$3,'Janvier'!T18,'Février'!T18,'Mars'!T18,'Avril'!T18,'Mai'!T18,'Juin'!T18,'Juillet'!T18,'Août'!T18,'Septembre'!T18,'Octobre'!T18,'Novembre'!T18,'Décembre'!T18),"") | AG16: =IF(ISNUMBER(CHOOSE($Z$3,'Janvier'!U18,'Février'!U18,'Mars'!U18,'Avril'!U18,'Mai'!U18,'Juin'!U18,'Juillet'!U18,'Août'!U18,'Septembre'!U18,'Octobre'!U18,'Novembre'!U18,'Décembre'!U18)),CHOOSE($Z$3,'Janvier'!U18,'Février'!U18,'Mars'!U18,'Avril'!U18,'Mai'!U18,'Juin'!U18,'Juillet'!U18,'Août'!U18,'Septembre'!U18,'Octobre'!U18,'Novembre'!U18,'Décembre'!U18),"") | AH16: =IF(ISNUMBER(CHOOSE($Z$3,'Janvier'!V18,'Février'!V18,'Mars'!V18,'Avril'!V18,'Mai'!V18,'Juin'!V18,'Juillet'!V18,'Août'!V18,'Septembre'!V18,'Octobre'!V18,'Novembre'!V18,'Décembre'!V18)),CHOOSE($Z$3,'Janvier'!V18,'Février'!V18,'Mars'!V18,'Avril'!V18,'Mai'!V18,'Juin'!V18,'Juillet'!V18,'Août'!V18,'Septembre'!V18,'Octobre'!V18,'Novembre'!V18,'Décembre'!V18),"") | AI16: =IF(ISNUMBER(CHOOSE($Z$3,'Janvier'!W18,'Février'!W18,'Mars'!W18,'Avril'!W18,'Mai'!W18,'Juin'!W18,'Juillet'!W18,'Août'!W18,'Septembre'!W18,'Octobre'!W18,'Novembre'!W18,'Décembre'!W18)),CHOOSE($Z$3,'Janvier'!W18,'Février'!W18,'Mars'!W18,'Avril'!W18,'Mai'!W18,'Juin'!W18,'Juillet'!W18,'Août'!W18,'Septembre'!W18,'Octobre'!W18,'Novembre'!W18,'Décembre'!W18),"") | AJ16: =IF(Produits!$A$17="","",Produits!$D$17) | AK16: =IF(ISNUMBER(CHOOSE($Z$3,'Janvier'!X18,'Février'!X18,'Mars'!X18,'Avril'!X18,'Mai'!X18,'Juin'!X18,'Juillet'!X18,'Août'!X18,'Septembre'!X18,'Octobre'!X18,'Novembre'!X18,'Décembre'!X18)),CHOOSE($Z$3,'Janvier'!X18,'Février'!X18,'Mars'!X18,'Avril'!X18,'Mai'!X18,'Juin'!X18,'Juillet'!X18,'Août'!X18,'Septembre'!X18,'Octobre'!X18,'Novembre'!X18,'Décembre'!X18),"") | AL16: =IF(AND(ISNUMBER(AI16),ISNUMBER(AJ16)),IF(AI16<=AJ16,1,0),0) | AM16: =IF(OR(AA16="",AK16=""),-1,AK16+ROW()/1000000)
A17: 6 | B17: =IF(LARGE($AM$5:$AM$64,6)<=0,"",INDEX($AA$5:$AA$64,MATCH(LARGE($AM$5:$AM$64,6),$AM$5:$AM$64,0))) | D17: =IF(B17="","",INDEX($AG$5:$AG$64,MATCH(LARGE($AM$5:$AM$64,6),$AM$5:$AM$64,0))) | E17: =IF(B17="","",INDEX($AK$5:$AK$64,MATCH(LARGE($AM$5:$AM$64,6),$AM$5:$AM$64,0))) | AA17: =IF(Produits!$A$18="","",Produits!$A$18) | AB17: =IF(ISNUMBER(CHOOSE($Z$3,'Janvier'!E19,'Février'!E19,'Mars'!E19,'Avril'!E19,'Mai'!E19,'Juin'!E19,'Juillet'!E19,'Août'!E19,'Septembre'!E19,'Octobre'!E19,'Novembre'!E19,'Décembre'!E19)),CHOOSE($Z$3,'Janvier'!E19,'Février'!E19,'Mars'!E19,'Avril'!E19,'Mai'!E19,'Juin'!E19,'Juillet'!E19,'Août'!E19,'Septembre'!E19,'Octobre'!E19,'Novembre'!E19,'Décembre'!E19),"") | AC17: =IF(ISNUMBER(CHOOSE($Z$3,'Janvier'!I19,'Février'!I19,'Mars'!I19,'Avril'!I19,'Mai'!I19,'Juin'!I19,'Juillet'!I19,'Août'!I19,'Septembre'!I19,'Octobre'!I19,'Novembre'!I19,'Décembre'!I19)),CHOOSE($Z$3,'Janvier'!I19,'Février'!I19,'Mars'!I19,'Avril'!I19,'Mai'!I19,'Juin'!I19,'Juillet'!I19,'Août'!I19,'Septembre'!I19,'Octobre'!I19,'Novembre'!I19,'Décembre'!I19),"") | AD17: =IF(ISNUMBER(CHOOSE($Z$3,'Janvier'!M19,'Février'!M19,'Mars'!M19,'Avril'!M19,'Mai'!M19,'Juin'!M19,'Juillet'!M19,'Août'!M19,'Septembre'!M19,'Octobre'!M19,'Novembre'!M19,'Décembre'!M19)),CHOOSE($Z$3,'Janvier'!M19,'Février'!M19,'Mars'!M19,'Avril'!M19,'Mai'!M19,'Juin'!M19,'Juillet'!M19,'Août'!M19,'Septembre'!M19,'Octobre'!M19,'Novembre'!M19,'Décembre'!M19),"") | AE17: =IF(ISNUMBER(CHOOSE($Z$3,'Janvier'!Q19,'Février'!Q19,'Mars'!Q19,'Avril'!Q19,'Mai'!Q19,'Juin'!Q19,'Juillet'!Q19,'Août'!Q19,'Septembre'!Q19,'Octobre'!Q19,'Novembre'!Q19,'Décembre'!Q19)),CHOOSE($Z$3,'Janvier'!Q19,'Février'!Q19,'Mars'!Q19,'Avril'!Q19,'Mai'!Q19,'Juin'!Q19,'Juillet'!Q19,'Août'!Q19,'Septembre'!Q19,'Octobre'!Q19,'Novembre'!Q19,'Décembre'!Q19),"") | AF17: =IF(ISNUMBER(CHOOSE($Z$3,'Janvier'!T19,'Février'!T19,'Mars'!T19,'Avril'!T19,'Mai'!T19,'Juin'!T19,'Juillet'!T19,'Août'!T19,'Septembre'!T19,'Octobre'!T19,'Novembre'!T19,'Décembre'!T19)),CHOOSE($Z$3,'Janvier'!T19,'Février'!T19,'Mars'!T19,'Avril'!T19,'Mai'!T19,'Juin'!T19,'Juillet'!T19,'Août'!T19,'Septembre'!T19,'Octobre'!T19,'Novembre'!T19,'Décembre'!T19),"") | AG17: =IF(ISNUMBER(CHOOSE($Z$3,'Janvier'!U19,'Février'!U19,'Mars'!U19,'Avril'!U19,'Mai'!U19,'Juin'!U19,'Juillet'!U19,'Août'!U19,'Septembre'!U19,'Octobre'!U19,'Novembre'!U19,'Décembre'!U19)),CHOOSE($Z$3,'Janvier'!U19,'Février'!U19,'Mars'!U19,'Avril'!U19,'Mai'!U19,'Juin'!U19,'Juillet'!U19,'Août'!U19,'Septembre'!U19,'Octobre'!U19,'Novembre'!U19,'Décembre'!U19),"") | AH17: =IF(ISNUMBER(CHOOSE($Z$3,'Janvier'!V19,'Février'!V19,'Mars'!V19,'Avril'!V19,'Mai'!V19,'Juin'!V19,'Juillet'!V19,'Août'!V19,'Septembre'!V19,'Octobre'!V19,'Novembre'!V19,'Décembre'!V19)),CHOOSE($Z$3,'Janvier'!V19,'Février'!V19,'Mars'!V19,'Avril'!V19,'Mai'!V19,'Juin'!V19,'Juillet'!V19,'Août'!V19,'Septembre'!V19,'Octobre'!V19,'Novembre'!V19,'Décembre'!V19),"") | AI17: =IF(ISNUMBER(CHOOSE($Z$3,'Janvier'!W19,'Février'!W19,'Mars'!W19,'Avril'!W19,'Mai'!W19,'Juin'!W19,'Juillet'!W19,'Août'!W19,'Septembre'!W19,'Octobre'!W19,'Novembre'!W19,'Décembre'!W19)),CHOOSE($Z$3,'Janvier'!W19,'Février'!W19,'Mars'!W19,'Avril'!W19,'Mai'!W19,'Juin'!W19,'Juillet'!W19,'Août'!W19,'Septembre'!W19,'Octobre'!W19,'Novembre'!W19,'Décembre'!W19),"") | AJ17: =IF(Produits!$A$18="","",Produits!$D$18) | AK17: =IF(ISNUMBER(CHOOSE($Z$3,'Janvier'!X19,'Février'!X19,'Mars'!X19,'Avril'!X19,'Mai'!X19,'Juin'!X19,'Juillet'!X19,'Août'!X19,'Septembre'!X19,'Octobre'!X19,'Novembre'!X19,'Décembre'!X19)),CHOOSE($Z$3,'Janvier'!X19,'Février'!X19,'Mars'!X19,'Avril'!X19,'Mai'!X19,'Juin'!X19,'Juillet'!X19,'Août'!X19,'Septembre'!X19,'Octobre'!X19,'Novembre'!X19,'Décembre'!X19),"") | AL17: =IF(AND(ISNUMBER(AI17),ISNUMBER(AJ17)),IF(AI17<=AJ17,1,0),0) | AM17: =IF(OR(AA17="",AK17=""),-1,AK17+ROW()/1000000)
A18: 7 | B18: =IF(LARGE($AM$5:$AM$64,7)<=0,"",INDEX($AA$5:$AA$64,MATCH(LARGE($AM$5:$AM$64,7),$AM$5:$AM$64,0))) | D18: =IF(B18="","",INDEX($AG$5:$AG$64,MATCH(LARGE($AM$5:$AM$64,7),$AM$5:$AM$64,0))) | E18: =IF(B18="","",INDEX($AK$5:$AK$64,MATCH(LARGE($AM$5:$AM$64,7),$AM$5:$AM$64,0))) | AA18: =IF(Produits!$A$19="","",Produits!$A$19) | AB18: =IF(ISNUMBER(CHOOSE($Z$3,'Janvier'!E20,'Février'!E20,'Mars'!E20,'Avril'!E20,'Mai'!E20,'Juin'!E20,'Juillet'!E20,'Août'!E20,'Septembre'!E20,'Octobre'!E20,'Novembre'!E20,'Décembre'!E20)),CHOOSE($Z$3,'Janvier'!E20,'Février'!E20,'Mars'!E20,'Avril'!E20,'Mai'!E20,'Juin'!E20,'Juillet'!E20,'Août'!E20,'Septembre'!E20,'Octobre'!E20,'Novembre'!E20,'Décembre'!E20),"") | AC18: =IF(ISNUMBER(CHOOSE($Z$3,'Janvier'!I20,'Février'!I20,'Mars'!I20,'Avril'!I20,'Mai'!I20,'Juin'!I20,'Juillet'!I20,'Août'!I20,'Septembre'!I20,'Octobre'!I20,'Novembre'!I20,'Décembre'!I20)),CHOOSE($Z$3,'Janvier'!I20,'Février'!I20,'Mars'!I20,'Avril'!I20,'Mai'!I20,'Juin'!I20,'Juillet'!I20,'Août'!I20,'Septembre'!I20,'Octobre'!I20,'Novembre'!I20,'Décembre'!I20),"") | AD18: =IF(ISNUMBER(CHOOSE($Z$3,'Janvier'!M20,'Février'!M20,'Mars'!M20,'Avril'!M20,'Mai'!M20,'Juin'!M20,'Juillet'!M20,'Août'!M20,'Septembre'!M20,'Octobre'!M20,'Novembre'!M20,'Décembre'!M20)),CHOOSE($Z$3,'Janvier'!M20,'Février'!M20,'Mars'!M20,'Avril'!M20,'Mai'!M20,'Juin'!M20,'Juillet'!M20,'Août'!M20,'Septembre'!M20,'Octobre'!M20,'Novembre'!M20,'Décembre'!M20),"") | AE18: =IF(ISNUMBER(CHOOSE($Z$3,'Janvier'!Q20,'Février'!Q20,'Mars'!Q20,'Avril'!Q20,'Mai'!Q20,'Juin'!Q20,'Juillet'!Q20,'Août'!Q20,'Septembre'!Q20,'Octobre'!Q20,'Novembre'!Q20,'Décembre'!Q20)),CHOOSE($Z$3,'Janvier'!Q20,'Février'!Q20,'Mars'!Q20,'Avril'!Q20,'Mai'!Q20,'Juin'!Q20,'Juillet'!Q20,'Août'!Q20,'Septembre'!Q20,'Octobre'!Q20,'Novembre'!Q20,'Décembre'!Q20),"") | AF18: =IF(ISNUMBER(CHOOSE($Z$3,'Janvier'!T20,'Février'!T20,'Mars'!T20,'Avril'!T20,'Mai'!T20,'Juin'!T20,'Juillet'!T20,'Août'!T20,'Septembre'!T20,'Octobre'!T20,'Novembre'!T20,'Décembre'!T20)),CHOOSE($Z$3,'Janvier'!T20,'Février'!T20,'Mars'!T20,'Avril'!T20,'Mai'!T20,'Juin'!T20,'Juillet'!T20,'Août'!T20,'Septembre'!T20,'Octobre'!T20,'Novembre'!T20,'Décembre'!T20),"") | AG18: =IF(ISNUMBER(CHOOSE($Z$3,'Janvier'!U20,'Février'!U20,'Mars'!U20,'Avril'!U20,'Mai'!U20,'Juin'!U20,'Juillet'!U20,'Août'!U20,'Septembre'!U20,'Octobre'!U20,'Novembre'!U20,'Décembre'!U20)),CHOOSE($Z$3,'Janvier'!U20,'Février'!U20,'Mars'!U20,'Avril'!U20,'Mai'!U20,'Juin'!U20,'Juillet'!U20,'Août'!U20,'Septembre'!U20,'Octobre'!U20,'Novembre'!U20,'Décembre'!U20),"") | AH18: =IF(ISNUMBER(CHOOSE($Z$3,'Janvier'!V20,'Février'!V20,'Mars'!V20,'Avril'!V20,'Mai'!V20,'Juin'!V20,'Juillet'!V20,'Août'!V20,'Septembre'!V20,'Octobre'!V20,'Novembre'!V20,'Décembre'!V20)),CHOOSE($Z$3,'Janvier'!V20,'Février'!V20,'Mars'!V20,'Avril'!V20,'Mai'!V20,'Juin'!V20,'Juillet'!V20,'Août'!V20,'Septembre'!V20,'Octobre'!V20,'Novembre'!V20,'Décembre'!V20),"") | AI18: =IF(ISNUMBER(CHOOSE($Z$3,'Janvier'!W20,'Février'!W20,'Mars'!W20,'Avril'!W20,'Mai'!W20,'Juin'!W20,'Juillet'!W20,'Août'!W20,'Septembre'!W20,'Octobre'!W20,'Novembre'!W20,'Décembre'!W20)),CHOOSE($Z$3,'Janvier'!W20,'Février'!W20,'Mars'!W20,'Avril'!W20,'Mai'!W20,'Juin'!W20,'Juillet'!W20,'Août'!W20,'Septembre'!W20,'Octobre'!W20,'Novembre'!W20,'Décembre'!W20),"") | AJ18: =IF(Produits!$A$19="","",Produits!$D$19) | AK18: =IF(ISNUMBER(CHOOSE($Z$3,'Janvier'!X20,'Février'!X20,'Mars'!X20,'Avril'!X20,'Mai'!X20,'Juin'!X20,'Juillet'!X20,'Août'!X20,'Septembre'!X20,'Octobre'!X20,'Novembre'!X20,'Décembre'!X20)),CHOOSE($Z$3,'Janvier'!X20,'Février'!X20,'Mars'!X20,'Avril'!X20,'Mai'!X20,'Juin'!X20,'Juillet'!X20,'Août'!X20,'Septembre'!X20,'Octobre'!X20,'Novembre'!X20,'Décembre'!X20),"") | AL18: =IF(AND(ISNUMBER(AI18),ISNUMBER(AJ18)),IF(AI18<=AJ18,1,0),0) | AM18: =IF(OR(AA18="",AK18=""),-1,AK18+ROW()/1000000)
A19: 8 | B19: =IF(LARGE($AM$5:$AM$64,8)<=0,"",INDEX($AA$5:$AA$64,MATCH(LARGE($AM$5:$AM$64,8),$AM$5:$AM$64,0))) | D19: =IF(B19="","",INDEX($AG$5:$AG$64,MATCH(LARGE($AM$5:$AM$64,8),$AM$5:$AM$64,0))) | E19: =IF(B19="","",INDEX($AK$5:$AK$64,MATCH(LARGE($AM$5:$AM$64,8),$AM$5:$AM$64,0))) | AA19: =IF(Produits!$A$20="","",Produits!$A$20) | AB19: =IF(ISNUMBER(CHOOSE($Z$3,'Janvier'!E21,'Février'!E21,'Mars'!E21,'Avril'!E21,'Mai'!E21,'Juin'!E21,'Juillet'!E21,'Août'!E21,'Septembre'!E21,'Octobre'!E21,'Novembre'!E21,'Décembre'!E21)),CHOOSE($Z$3,'Janvier'!E21,'Février'!E21,'Mars'!E21,'Avril'!E21,'Mai'!E21,'Juin'!E21,'Juillet'!E21,'Août'!E21,'Septembre'!E21,'Octobre'!E21,'Novembre'!E21,'Décembre'!E21),"") | AC19: =IF(ISNUMBER(CHOOSE($Z$3,'Janvier'!I21,'Février'!I21,'Mars'!I21,'Avril'!I21,'Mai'!I21,'Juin'!I21,'Juillet'!I21,'Août'!I21,'Septembre'!I21,'Octobre'!I21,'Novembre'!I21,'Décembre'!I21)),CHOOSE($Z$3,'Janvier'!I21,'Février'!I21,'Mars'!I21,'Avril'!I21,'Mai'!I21,'Juin'!I21,'Juillet'!I21,'Août'!I21,'Septembre'!I21,'Octobre'!I21,'Novembre'!I21,'Décembre'!I21),"") | AD19: =IF(ISNUMBER(CHOOSE($Z$3,'Janvier'!M21,'Février'!M21,'Mars'!M21,'Avril'!M21,'Mai'!M21,'Juin'!M21,'Juillet'!M21,'Août'!M21,'Septembre'!M21,'Octobre'!M21,'Novembre'!M21,'Décembre'!M21)),CHOOSE($Z$3,'Janvier'!M21,'Février'!M21,'Mars'!M21,'Avril'!M21,'Mai'!M21,'Juin'!M21,'Juillet'!M21,'Août'!M21,'Septembre'!M21,'Octobre'!M21,'Novembre'!M21,'Décembre'!M21),"") | AE19: =IF(ISNUMBER(CHOOSE($Z$3,'Janvier'!Q21,'Février'!Q21,'Mars'!Q21,'Avril'!Q21,'Mai'!Q21,'Juin'!Q21,'Juillet'!Q21,'Août'!Q21,'Septembre'!Q21,'Octobre'!Q21,'Novembre'!Q21,'Décembre'!Q21)),CHOOSE($Z$3,'Janvier'!Q21,'Février'!Q21,'Mars'!Q21,'Avril'!Q21,'Mai'!Q21,'Juin'!Q21,'Juillet'!Q21,'Août'!Q21,'Septembre'!Q21,'Octobre'!Q21,'Novembre'!Q21,'Décembre'!Q21),"") | AF19: =IF(ISNUMBER(CHOOSE($Z$3,'Janvier'!T21,'Février'!T21,'Mars'!T21,'Avril'!T21,'Mai'!T21,'Juin'!T21,'Juillet'!T21,'Août'!T21,'Septembre'!T21,'Octobre'!T21,'Novembre'!T21,'Décembre'!T21)),CHOOSE($Z$3,'Janvier'!T21,'Février'!T21,'Mars'!T21,'Avril'!T21,'Mai'!T21,'Juin'!T21,'Juillet'!T21,'Août'!T21,'Septembre'!T21,'Octobre'!T21,'Novembre'!T21,'Décembre'!T21),"") | AG19: =IF(ISNUMBER(CHOOSE($Z$3,'Janvier'!U21,'Février'!U21,'Mars'!U21,'Avril'!U21,'Mai'!U21,'Juin'!U21,'Juillet'!U21,'Août'!U21,'Septembre'!U21,'Octobre'!U21,'Novembre'!U21,'Décembre'!U21)),CHOOSE($Z$3,'Janvier'!U21,'Février'!U21,'Mars'!U21,'Avril'!U21,'Mai'!U21,'Juin'!U21,'Juillet'!U21,'Août'!U21,'Septembre'!U21,'Octobre'!U21,'Novembre'!U21,'Décembre'!U21),"") | AH19: =IF(ISNUMBER(CHOOSE($Z$3,'Janvier'!V21,'Février'!V21,'Mars'!V21,'Avril'!V21,'Mai'!V21,'Juin'!V21,'Juillet'!V21,'Août'!V21,'Septembre'!V21,'Octobre'!V21,'Novembre'!V21,'Décembre'!V21)),CHOOSE($Z$3,'Janvier'!V21,'Février'!V21,'Mars'!V21,'Avril'!V21,'Mai'!V21,'Juin'!V21,'Juillet'!V21,'Août'!V21,'Septembre'!V21,'Octobre'!V21,'Novembre'!V21,'Décembre'!V21),"") | AI19: =IF(ISNUMBER(CHOOSE($Z$3,'Janvier'!W21,'Février'!W21,'Mars'!W21,'Avril'!W21,'Mai'!W21,'Juin'!W21,'Juillet'!W21,'Août'!W21,'Septembre'!W21,'Octobre'!W21,'Novembre'!W21,'Décembre'!W21)),CHOOSE($Z$3,'Janvier'!W21,'Février'!W21,'Mars'!W21,'Avril'!W21,'Mai'!W21,'Juin'!W21,'Juillet'!W21,'Août'!W21,'Septembre'!W21,'Octobre'!W21,'Novembre'!W21,'Décembre'!W21),"") | AJ19: =IF(Produits!$A$20="","",Produits!$D$20) | AK19: =IF(ISNUMBER(CHOOSE($Z$3,'Janvier'!X21,'Février'!X21,'Mars'!X21,'Avril'!X21,'Mai'!X21,'Juin'!X21,'Juillet'!X21,'Août'!X21,'Septembre'!X21,'Octobre'!X21,'Novembre'!X21,'Décembre'!X21)),CHOOSE($Z$3,'Janvier'!X21,'Février'!X21,'Mars'!X21,'Avril'!X21,'Mai'!X21,'Juin'!X21,'Juillet'!X21,'Août'!X21,'Septembre'!X21,'Octobre'!X21,'Novembre'!X21,'Décembre'!X21),"") | AL19: =IF(AND(ISNUMBER(AI19),ISNUMBER(AJ19)),IF(AI19<=AJ19,1,0),0) | AM19: =IF(OR(AA19="",AK19=""),-1,AK19+ROW()/1000000)
A20: 9 | B20: =IF(LARGE($AM$5:$AM$64,9)<=0,"",INDEX($AA$5:$AA$64,MATCH(LARGE($AM$5:$AM$64,9),$AM$5:$AM$64,0))) | D20: =IF(B20="","",INDEX($AG$5:$AG$64,MATCH(LARGE($AM$5:$AM$64,9),$AM$5:$AM$64,0))) | E20: =IF(B20="","",INDEX($AK$5:$AK$64,MATCH(LARGE($AM$5:$AM$64,9),$AM$5:$AM$64,0))) | AA20: =IF(Produits!$A$22="","",Produits!$A$22) | AB20: =IF(ISNUMBER(CHOOSE($Z$3,'Janvier'!E23,'Février'!E23,'Mars'!E23,'Avril'!E23,'Mai'!E23,'Juin'!E23,'Juillet'!E23,'Août'!E23,'Septembre'!E23,'Octobre'!E23,'Novembre'!E23,'Décembre'!E23)),CHOOSE($Z$3,'Janvier'!E23,'Février'!E23,'Mars'!E23,'Avril'!E23,'Mai'!E23,'Juin'!E23,'Juillet'!E23,'Août'!E23,'Septembre'!E23,'Octobre'!E23,'Novembre'!E23,'Décembre'!E23),"") | AC20: =IF(ISNUMBER(CHOOSE($Z$3,'Janvier'!I23,'Février'!I23,'Mars'!I23,'Avril'!I23,'Mai'!I23,'Juin'!I23,'Juillet'!I23,'Août'!I23,'Septembre'!I23,'Octobre'!I23,'Novembre'!I23,'Décembre'!I23)),CHOOSE($Z$3,'Janvier'!I23,'Février'!I23,'Mars'!I23,'Avril'!I23,'Mai'!I23,'Juin'!I23,'Juillet'!I23,'Août'!I23,'Septembre'!I23,'Octobre'!I23,'Novembre'!I23,'Décembre'!I23),"") | AD20: =IF(ISNUMBER(CHOOSE($Z$3,'Janvier'!M23,'Février'!M23,'Mars'!M23,'Avril'!M23,'Mai'!M23,'Juin'!M23,'Juillet'!M23,'Août'!M23,'Septembre'!M23,'Octobre'!M23,'Novembre'!M23,'Décembre'!M23)),CHOOSE($Z$3,'Janvier'!M23,'Février'!M23,'Mars'!M23,'Avril'!M23,'Mai'!M23,'Juin'!M23,'Juillet'!M23,'Août'!M23,'Septembre'!M23,'Octobre'!M23,'Novembre'!M23,'Décembre'!M23),"") | AE20: =IF(ISNUMBER(CHOOSE($Z$3,'Janvier'!Q23,'Février'!Q23,'Mars'!Q23,'Avril'!Q23,'Mai'!Q23,'Juin'!Q23,'Juillet'!Q23,'Août'!Q23,'Septembre'!Q23,'Octobre'!Q23,'Novembre'!Q23,'Décembre'!Q23)),CHOOSE($Z$3,'Janvier'!Q23,'Février'!Q23,'Mars'!Q23,'Avril'!Q23,'Mai'!Q23,'Juin'!Q23,'Juillet'!Q23,'Août'!Q23,'Septembre'!Q23,'Octobre'!Q23,'Novembre'!Q23,'Décembre'!Q23),"") | AF20: =IF(ISNUMBER(CHOOSE($Z$3,'Janvier'!T23,'Février'!T23,'Mars'!T23,'Avril'!T23,'Mai'!T23,'Juin'!T23,'Juillet'!T23,'Août'!T23,'Septembre'!T23,'Octobre'!T23,'Novembre'!T23,'Décembre'!T23)),CHOOSE($Z$3,'Janvier'!T23,'Février'!T23,'Mars'!T23,'Avril'!T23,'Mai'!T23,'Juin'!T23,'Juillet'!T23,'Août'!T23,'Septembre'!T23,'Octobre'!T23,'Novembre'!T23,'Décembre'!T23),"") | AG20: =IF(ISNUMBER(CHOOSE($Z$3,'Janvier'!U23,'Février'!U23,'Mars'!U23,'Avril'!U23,'Mai'!U23,'Juin'!U23,'Juillet'!U23,'Août'!U23,'Septembre'!U23,'Octobre'!U23,'Novembre'!U23,'Décembre'!U23)),CHOOSE($Z$3,'Janvier'!U23,'Février'!U23,'Mars'!U23,'Avril'!U23,'Mai'!U23,'Juin'!U23,'Juillet'!U23,'Août'!U23,'Septembre'!U23,'Octobre'!U23,'Novembre'!U23,'Décembre'!U23),"") | AH20: =IF(ISNUMBER(CHOOSE($Z$3,'Janvier'!V23,'Février'!V23,'Mars'!V23,'Avril'!V23,'Mai'!V23,'Juin'!V23,'Juillet'!V23,'Août'!V23,'Septembre'!V23,'Octobre'!V23,'Novembre'!V23,'Décembre'!V23)),CHOOSE($Z$3,'Janvier'!V23,'Février'!V23,'Mars'!V23,'Avril'!V23,'Mai'!V23,'Juin'!V23,'Juillet'!V23,'Août'!V23,'Septembre'!V23,'Octobre'!V23,'Novembre'!V23,'Décembre'!V23),"") | AI20: =IF(ISNUMBER(CHOOSE($Z$3,'Janvier'!W23,'Février'!W23,'Mars'!W23,'Avril'!W23,'Mai'!W23,'Juin'!W23,'Juillet'!W23,'Août'!W23,'Septembre'!W23,'Octobre'!W23,'Novembre'!W23,'Décembre'!W23)),CHOOSE($Z$3,'Janvier'!W23,'Février'!W23,'Mars'!W23,'Avril'!W23,'Mai'!W23,'Juin'!W23,'Juillet'!W23,'Août'!W23,'Septembre'!W23,'Octobre'!W23,'Novembre'!W23,'Décembre'!W23),"") | AJ20: =IF(Produits!$A$22="","",Produits!$D$22) | AK20: =IF(ISNUMBER(CHOOSE($Z$3,'Janvier'!X23,'Février'!X23,'Mars'!X23,'Avril'!X23,'Mai'!X23,'Juin'!X23,'Juillet'!X23,'Août'!X23,'Septembre'!X23,'Octobre'!X23,'Novembre'!X23,'Décembre'!X23)),CHOOSE($Z$3,'Janvier'!X23,'Février'!X23,'Mars'!X23,'Avril'!X23,'Mai'!X23,'Juin'!X23,'Juillet'!X23,'Août'!X23,'Septembre'!X23,'Octobre'!X23,'Novembre'!X23,'Décembre'!X23),"") | AL20: =IF(AND(ISNUMBER(AI20),ISNUMBER(AJ20)),IF(AI20<=AJ20,1,0),0) | AM20: =IF(OR(AA20="",AK20=""),-1,AK20+ROW()/1000000)
A21: 10 | B21: =IF(LARGE($AM$5:$AM$64,10)<=0,"",INDEX($AA$5:$AA$64,MATCH(LARGE($AM$5:$AM$64,10),$AM$5:$AM$64,0))) | D21: =IF(B21="","",INDEX($AG$5:$AG$64,MATCH(LARGE($AM$5:$AM$64,10),$AM$5:$AM$64,0))) | E21: =IF(B21="","",INDEX($AK$5:$AK$64,MATCH(LARGE($AM$5:$AM$64,10),$AM$5:$AM$64,0))) | AA21: =IF(Produits!$A$23="","",Produits!$A$23) | AB21: =IF(ISNUMBER(CHOOSE($Z$3,'Janvier'!E24,'Février'!E24,'Mars'!E24,'Avril'!E24,'Mai'!E24,'Juin'!E24,'Juillet'!E24,'Août'!E24,'Septembre'!E24,'Octobre'!E24,'Novembre'!E24,'Décembre'!E24)),CHOOSE($Z$3,'Janvier'!E24,'Février'!E24,'Mars'!E24,'Avril'!E24,'Mai'!E24,'Juin'!E24,'Juillet'!E24,'Août'!E24,'Septembre'!E24,'Octobre'!E24,'Novembre'!E24,'Décembre'!E24),"") | AC21: =IF(ISNUMBER(CHOOSE($Z$3,'Janvier'!I24,'Février'!I24,'Mars'!I24,'Avril'!I24,'Mai'!I24,'Juin'!I24,'Juillet'!I24,'Août'!I24,'Septembre'!I24,'Octobre'!I24,'Novembre'!I24,'Décembre'!I24)),CHOOSE($Z$3,'Janvier'!I24,'Février'!I24,'Mars'!I24,'Avril'!I24,'Mai'!I24,'Juin'!I24,'Juillet'!I24,'Août'!I24,'Septembre'!I24,'Octobre'!I24,'Novembre'!I24,'Décembre'!I24),"") | AD21: =IF(ISNUMBER(CHOOSE($Z$3,'Janvier'!M24,'Février'!M24,'Mars'!M24,'Avril'!M24,'Mai'!M24,'Juin'!M24,'Juillet'!M24,'Août'!M24,'Septembre'!M24,'Octobre'!M24,'Novembre'!M24,'Décembre'!M24)),CHOOSE($Z$3,'Janvier'!M24,'Février'!M24,'Mars'!M24,'Avril'!M24,'Mai'!M24,'Juin'!M24,'Juillet'!M24,'Août'!M24,'Septembre'!M24,'Octobre'!M24,'Novembre'!M24,'Décembre'!M24),"") | AE21: =IF(ISNUMBER(CHOOSE($Z$3,'Janvier'!Q24,'Février'!Q24,'Mars'!Q24,'Avril'!Q24,'Mai'!Q24,'Juin'!Q24,'Juillet'!Q24,'Août'!Q24,'Septembre'!Q24,'Octobre'!Q24,'Novembre'!Q24,'Décembre'!Q24)),CHOOSE($Z$3,'Janvier'!Q24,'Février'!Q24,'Mars'!Q24,'Avril'!Q24,'Mai'!Q24,'Juin'!Q24,'Juillet'!Q24,'Août'!Q24,'Septembre'!Q24,'Octobre'!Q24,'Novembre'!Q24,'Décembre'!Q24),"") | AF21: =IF(ISNUMBER(CHOOSE($Z$3,'Janvier'!T24,'Février'!T24,'Mars'!T24,'Avril'!T24,'Mai'!T24,'Juin'!T24,'Juillet'!T24,'Août'!T24,'Septembre'!T24,'Octobre'!T24,'Novembre'!T24,'Décembre'!T24)),CHOOSE($Z$3,'Janvier'!T24,'Février'!T24,'Mars'!T24,'Avril'!T24,'Mai'!T24,'Juin'!T24,'Juillet'!T24,'Août'!T24,'Septembre'!T24,'Octobre'!T24,'Novembre'!T24,'Décembre'!T24),"") | AG21: =IF(ISNUMBER(CHOOSE($Z$3,'Janvier'!U24,'Février'!U24,'Mars'!U24,'Avril'!U24,'Mai'!U24,'Juin'!U24,'Juillet'!U24,'Août'!U24,'Septembre'!U24,'Octobre'!U24,'Novembre'!U24,'Décembre'!U24)),CHOOSE($Z$3,'Janvier'!U24,'Février'!U24,'Mars'!U24,'Avril'!U24,'Mai'!U24,'Juin'!U24,'Juillet'!U24,'Août'!U24,'Septembre'!U24,'Octobre'!U24,'Novembre'!U24,'Décembre'!U24),"") | AH21: =IF(ISNUMBER(CHOOSE($Z$3,'Janvier'!V24,'Février'!V24,'Mars'!V24,'Avril'!V24,'Mai'!V24,'Juin'!V24,'Juillet'!V24,'Août'!V24,'Septembre'!V24,'Octobre'!V24,'Novembre'!V24,'Décembre'!V24)),CHOOSE($Z$3,'Janvier'!V24,'Février'!V24,'Mars'!V24,'Avril'!V24,'Mai'!V24,'Juin'!V24,'Juillet'!V24,'Août'!V24,'Septembre'!V24,'Octobre'!V24,'Novembre'!V24,'Décembre'!V24),"") | AI21: =IF(ISNUMBER(CHOOSE($Z$3,'Janvier'!W24,'Février'!W24,'Mars'!W24,'Avril'!W24,'Mai'!W24,'Juin'!W24,'Juillet'!W24,'Août'!W24,'Septembre'!W24,'Octobre'!W24,'Novembre'!W24,'Décembre'!W24)),CHOOSE($Z$3,'Janvier'!W24,'Février'!W24,'Mars'!W24,'Avril'!W24,'Mai'!W24,'Juin'!W24,'Juillet'!W24,'Août'!W24,'Septembre'!W24,'Octobre'!W24,'Novembre'!W24,'Décembre'!W24),"") | AJ21: =IF(Produits!$A$23="","",Produits!$D$23) | AK21: =IF(ISNUMBER(CHOOSE($Z$3,'Janvier'!X24,'Février'!X24,'Mars'!X24,'Avril'!X24,'Mai'!X24,'Juin'!X24,'Juillet'!X24,'Août'!X24,'Septembre'!X24,'Octobre'!X24,'Novembre'!X24,'Décembre'!X24)),CHOOSE($Z$3,'Janvier'!X24,'Février'!X24,'Mars'!X24,'Avril'!X24,'Mai'!X24,'Juin'!X24,'Juillet'!X24,'Août'!X24,'Septembre'!X24,'Octobre'!X24,'Novembre'!X24,'Décembre'!X24),"") | AL21: =IF(AND(ISNUMBER(AI21),ISNUMBER(AJ21)),IF(AI21<=AJ21,1,0),0) | AM21: =IF(OR(AA21="",AK21=""),-1,AK21+ROW()/1000000)
AA22: =IF(Produits!$A$24="","",Produits!$A$24) | AB22: =IF(ISNUMBER(CHOOSE($Z$3,'Janvier'!E25,'Février'!E25,'Mars'!E25,'Avril'!E25,'Mai'!E25,'Juin'!E25,'Juillet'!E25,'Août'!E25,'Septembre'!E25,'Octobre'!E25,'Novembre'!E25,'Décembre'!E25)),CHOOSE($Z$3,'Janvier'!E25,'Février'!E25,'Mars'!E25,'Avril'!E25,'Mai'!E25,'Juin'!E25,'Juillet'!E25,'Août'!E25,'Septembre'!E25,'Octobre'!E25,'Novembre'!E25,'Décembre'!E25),"") | AC22: =IF(ISNUMBER(CHOOSE($Z$3,'Janvier'!I25,'Février'!I25,'Mars'!I25,'Avril'!I25,'Mai'!I25,'Juin'!I25,'Juillet'!I25,'Août'!I25,'Septembre'!I25,'Octobre'!I25,'Novembre'!I25,'Décembre'!I25)),CHOOSE($Z$3,'Janvier'!I25,'Février'!I25,'Mars'!I25,'Avril'!I25,'Mai'!I25,'Juin'!I25,'Juillet'!I25,'Août'!I25,'Septembre'!I25,'Octobre'!I25,'Novembre'!I25,'Décembre'!I25),"") | AD22: =IF(ISNUMBER(CHOOSE($Z$3,'Janvier'!M25,'Février'!M25,'Mars'!M25,'Avril'!M25,'Mai'!M25,'Juin'!M25,'Juillet'!M25,'Août'!M25,'Septembre'!M25,'Octobre'!M25,'Novembre'!M25,'Décembre'!M25)),CHOOSE($Z$3,'Janvier'!M25,'Février'!M25,'Mars'!M25,'Avril'!M25,'Mai'!M25,'Juin'!M25,'Juillet'!M25,'Août'!M25,'Septembre'!M25,'Octobre'!M25,'Novembre'!M25,'Décembre'!M25),"") | AE22: =IF(ISNUMBER(CHOOSE($Z$3,'Janvier'!Q25,'Février'!Q25,'Mars'!Q25,'Avril'!Q25,'Mai'!Q25,'Juin'!Q25,'Juillet'!Q25,'Août'!Q25,'Septembre'!Q25,'Octobre'!Q25,'Novembre'!Q25,'Décembre'!Q25)),CHOOSE($Z$3,'Janvier'!Q25,'Février'!Q25,'Mars'!Q25,'Avril'!Q25,'Mai'!Q25,'Juin'!Q25,'Juillet'!Q25,'Août'!Q25,'Septembre'!Q25,'Octobre'!Q25,'Novembre'!Q25,'Décembre'!Q25),"") | AF22: =IF(ISNUMBER(CHOOSE($Z$3,'Janvier'!T25,'Février'!T25,'Mars'!T25,'Avril'!T25,'Mai'!T25,'Juin'!T25,'Juillet'!T25,'Août'!T25,'Septembre'!T25,'Octobre'!T25,'Novembre'!T25,'Décembre'!T25)),CHOOSE($Z$3,'Janvier'!T25,'Février'!T25,'Mars'!T25,'Avril'!T25,'Mai'!T25,'Juin'!T25,'Juillet'!T25,'Août'!T25,'Septembre'!T25,'Octobre'!T25,'Novembre'!T25,'Décembre'!T25),"") | AG22: =IF(ISNUMBER(CHOOSE($Z$3,'Janvier'!U25,'Février'!U25,'Mars'!U25,'Avril'!U25,'Mai'!U25,'Juin'!U25,'Juillet'!U25,'Août'!U25,'Septembre'!U25,'Octobre'!U25,'Novembre'!U25,'Décembre'!U25)),CHOOSE($Z$3,'Janvier'!U25,'Février'!U25,'Mars'!U25,'Avril'!U25,'Mai'!U25,'Juin'!U25,'Juillet'!U25,'Août'!U25,'Septembre'!U25,'Octobre'!U25,'Novembre'!U25,'Décembre'!U25),"") | AH22: =IF(ISNUMBER(CHOOSE($Z$3,'Janvier'!V25,'Février'!V25,'Mars'!V25,'Avril'!V25,'Mai'!V25,'Juin'!V25,'Juillet'!V25,'Août'!V25,'Septembre'!V25,'Octobre'!V25,'Novembre'!V25,'Décembre'!V25)),CHOOSE($Z$3,'Janvier'!V25,'Février'!V25,'Mars'!V25,'Avril'!V25,'Mai'!V25,'Juin'!V25,'Juillet'!V25,'Août'!V25,'Septembre'!V25,'Octobre'!V25,'Novembre'!V25,'Décembre'!V25),"") | AI22: =IF(ISNUMBER(CHOOSE($Z$3,'Janvier'!W25,'Février'!W25,'Mars'!W25,'Avril'!W25,'Mai'!W25,'Juin'!W25,'Juillet'!W25,'Août'!W25,'Septembre'!W25,'Octobre'!W25,'Novembre'!W25,'Décembre'!W25)),CHOOSE($Z$3,'Janvier'!W25,'Février'!W25,'Mars'!W25,'Avril'!W25,'Mai'!W25,'Juin'!W25,'Juillet'!W25,'Août'!W25,'Septembre'!W25,'Octobre'!W25,'Novembre'!W25,'Décembre'!W25),"") | AJ22: =IF(Produits!$A$24="","",Produits!$D$24) | AK22: =IF(ISNUMBER(CHOOSE($Z$3,'Janvier'!X25,'Février'!X25,'Mars'!X25,'Avril'!X25,'Mai'!X25,'Juin'!X25,'Juillet'!X25,'Août'!X25,'Septembre'!X25,'Octobre'!X25,'Novembre'!X25,'Décembre'!X25)),CHOOSE($Z$3,'Janvier'!X25,'Février'!X25,'Mars'!X25,'Avril'!X25,'Mai'!X25,'Juin'!X25,'Juillet'!X25,'Août'!X25,'Septembre'!X25,'Octobre'!X25,'Novembre'!X25,'Décembre'!X25),"") | AL22: =IF(AND(ISNUMBER(AI22),ISNUMBER(AJ22)),IF(AI22<=AJ22,1,0),0) | AM22: =IF(OR(AA22="",AK22=""),-1,AK22+ROW()/1000000)
AA23: =IF(Produits!$A$25="","",Produits!$A$25) | AB23: =IF(ISNUMBER(CHOOSE($Z$3,'Janvier'!E26,'Février'!E26,'Mars'!E26,'Avril'!E26,'Mai'!E26,'Juin'!E26,'Juillet'!E26,'Août'!E26,'Septembre'!E26,'Octobre'!E26,'Novembre'!E26,'Décembre'!E26)),CHOOSE($Z$3,'Janvier'!E26,'Février'!E26,'Mars'!E26,'Avril'!E26,'Mai'!E26,'Juin'!E26,'Juillet'!E26,'Août'!E26,'Septembre'!E26,'Octobre'!E26,'Novembre'!E26,'Décembre'!E26),"") | AC23: =IF(ISNUMBER(CHOOSE($Z$3,'Janvier'!I26,'Février'!I26,'Mars'!I26,'Avril'!I26,'Mai'!I26,'Juin'!I26,'Juillet'!I26,'Août'!I26,'Septembre'!I26,'Octobre'!I26,'Novembre'!I26,'Décembre'!I26)),CHOOSE($Z$3,'Janvier'!I26,'Février'!I26,'Mars'!I26,'Avril'!I26,'Mai'!I26,'Juin'!I26,'Juillet'!I26,'Août'!I26,'Septembre'!I26,'Octobre'!I26,'Novembre'!I26,'Décembre'!I26),"") | AD23: =IF(ISNUMBER(CHOOSE($Z$3,'Janvier'!M26,'Février'!M26,'Mars'!M26,'Avril'!M26,'Mai'!M26,'Juin'!M26,'Juillet'!M26,'Août'!M26,'Septembre'!M26,'Octobre'!M26,'Novembre'!M26,'Décembre'!M26)),CHOOSE($Z$3,'Janvier'!M26,'Février'!M26,'Mars'!M26,'Avril'!M26,'Mai'!M26,'Juin'!M26,'Juillet'!M26,'Août'!M26,'Septembre'!M26,'Octobre'!M26,'Novembre'!M26,'Décembre'!M26),"") | AE23: =IF(ISNUMBER(CHOOSE($Z$3,'Janvier'!Q26,'Février'!Q26,'Mars'!Q26,'Avril'!Q26,'Mai'!Q26,'Juin'!Q26,'Juillet'!Q26,'Août'!Q26,'Septembre'!Q26,'Octobre'!Q26,'Novembre'!Q26,'Décembre'!Q26)),CHOOSE($Z$3,'Janvier'!Q26,'Février'!Q26,'Mars'!Q26,'Avril'!Q26,'Mai'!Q26,'Juin'!Q26,'Juillet'!Q26,'Août'!Q26,'Septembre'!Q26,'Octobre'!Q26,'Novembre'!Q26,'Décembre'!Q26),"") | AF23: =IF(ISNUMBER(CHOOSE($Z$3,'Janvier'!T26,'Février'!T26,'Mars'!T26,'Avril'!T26,'Mai'!T26,'Juin'!T26,'Juillet'!T26,'Août'!T26,'Septembre'!T26,'Octobre'!T26,'Novembre'!T26,'Décembre'!T26)),CHOOSE($Z$3,'Janvier'!T26,'Février'!T26,'Mars'!T26,'Avril'!T26,'Mai'!T26,'Juin'!T26,'Juillet'!T26,'Août'!T26,'Septembre'!T26,'Octobre'!T26,'Novembre'!T26,'Décembre'!T26),"") | AG23: =IF(ISNUMBER(CHOOSE($Z$3,'Janvier'!U26,'Février'!U26,'Mars'!U26,'Avril'!U26,'Mai'!U26,'Juin'!U26,'Juillet'!U26,'Août'!U26,'Septembre'!U26,'Octobre'!U26,'Novembre'!U26,'Décembre'!U26)),CHOOSE($Z$3,'Janvier'!U26,'Février'!U26,'Mars'!U26,'Avril'!U26,'Mai'!U26,'Juin'!U26,'Juillet'!U26,'Août'!U26,'Septembre'!U26,'Octobre'!U26,'Novembre'!U26,'Décembre'!U26),"") | AH23: =IF(ISNUMBER(CHOOSE($Z$3,'Janvier'!V26,'Février'!V26,'Mars'!V26,'Avril'!V26,'Mai'!V26,'Juin'!V26,'Juillet'!V26,'Août'!V26,'Septembre'!V26,'Octobre'!V26,'Novembre'!V26,'Décembre'!V26)),CHOOSE($Z$3,'Janvier'!V26,'Février'!V26,'Mars'!V26,'Avril'!V26,'Mai'!V26,'Juin'!V26,'Juillet'!V26,'Août'!V26,'Septembre'!V26,'Octobre'!V26,'Novembre'!V26,'Décembre'!V26),"") | AI23: =IF(ISNUMBER(CHOOSE($Z$3,'Janvier'!W26,'Février'!W26,'Mars'!W26,'Avril'!W26,'Mai'!W26,'Juin'!W26,'Juillet'!W26,'Août'!W26,'Septembre'!W26,'Octobre'!W26,'Novembre'!W26,'Décembre'!W26)),CHOOSE($Z$3,'Janvier'!W26,'Février'!W26,'Mars'!W26,'Avril'!W26,'Mai'!W26,'Juin'!W26,'Juillet'!W26,'Août'!W26,'Septembre'!W26,'Octobre'!W26,'Novembre'!W26,'Décembre'!W26),"") | AJ23: =IF(Produits!$A$25="","",Produits!$D$25) | AK23: =IF(ISNUMBER(CHOOSE($Z$3,'Janvier'!X26,'Février'!X26,'Mars'!X26,'Avril'!X26,'Mai'!X26,'Juin'!X26,'Juillet'!X26,'Août'!X26,'Septembre'!X26,'Octobre'!X26,'Novembre'!X26,'Décembre'!X26)),CHOOSE($Z$3,'Janvier'!X26,'Février'!X26,'Mars'!X26,'Avril'!X26,'Mai'!X26,'Juin'!X26,'Juillet'!X26,'Août'!X26,'Septembre'!X26,'Octobre'!X26,'Novembre'!X26,'Décembre'!X26),"") | AL23: =IF(AND(ISNUMBER(AI23),ISNUMBER(AJ23)),IF(AI23<=AJ23,1,0),0) | AM23: =IF(OR(AA23="",AK23=""),-1,AK23+ROW()/1000000)
A24: Tendance du stock et alertes | AA24: =IF(Produits!$A$26="","",Produits!$A$26) | AB24: =IF(ISNUMBER(CHOOSE($Z$3,'Janvier'!E27,'Février'!E27,'Mars'!E27,'Avril'!E27,'Mai'!E27,'Juin'!E27,'Juillet'!E27,'Août'!E27,'Septembre'!E27,'Octobre'!E27,'Novembre'!E27,'Décembre'!E27)),CHOOSE($Z$3,'Janvier'!E27,'Février'!E27,'Mars'!E27,'Avril'!E27,'Mai'!E27,'Juin'!E27,'Juillet'!E27,'Août'!E27,'Septembre'!E27,'Octobre'!E27,'Novembre'!E27,'Décembre'!E27),"") | AC24: =IF(ISNUMBER(CHOOSE($Z$3,'Janvier'!I27,'Février'!I27,'Mars'!I27,'Avril'!I27,'Mai'!I27,'Juin'!I27,'Juillet'!I27,'Août'!I27,'Septembre'!I27,'Octobre'!I27,'Novembre'!I27,'Décembre'!I27)),CHOOSE($Z$3,'Janvier'!I27,'Février'!I27,'Mars'!I27,'Avril'!I27,'Mai'!I27,'Juin'!I27,'Juillet'!I27,'Août'!I27,'Septembre'!I27,'Octobre'!I27,'Novembre'!I27,'Décembre'!I27),"") | AD24: =IF(ISNUMBER(CHOOSE($Z$3,'Janvier'!M27,'Février'!M27,'Mars'!M27,'Avril'!M27,'Mai'!M27,'Juin'!M27,'Juillet'!M27,'Août'!M27,'Septembre'!M27,'Octobre'!M27,'Novembre'!M27,'Décembre'!M27)),CHOOSE($Z$3,'Janvier'!M27,'Février'!M27,'Mars'!M27,'Avril'!M27,'Mai'!M27,'Juin'!M27,'Juillet'!M27,'Août'!M27,'Septembre'!M27,'Octobre'!M27,'Novembre'!M27,'Décembre'!M27),"") | AE24: =IF(ISNUMBER(CHOOSE($Z$3,'Janvier'!Q27,'Février'!Q27,'Mars'!Q27,'Avril'!Q27,'Mai'!Q27,'Juin'!Q27,'Juillet'!Q27,'Août'!Q27,'Septembre'!Q27,'Octobre'!Q27,'Novembre'!Q27,'Décembre'!Q27)),CHOOSE($Z$3,'Janvier'!Q27,'Février'!Q27,'Mars'!Q27,'Avril'!Q27,'Mai'!Q27,'Juin'!Q27,'Juillet'!Q27,'Août'!Q27,'Septembre'!Q27,'Octobre'!Q27,'Novembre'!Q27,'Décembre'!Q27),"") | AF24: =IF(ISNUMBER(CHOOSE($Z$3,'Janvier'!T27,'Février'!T27,'Mars'!T27,'Avril'!T27,'Mai'!T27,'Juin'!T27,'Juillet'!T27,'Août'!T27,'Septembre'!T27,'Octobre'!T27,'Novembre'!T27,'Décembre'!T27)),CHOOSE($Z$3,'Janvier'!T27,'Février'!T27,'Mars'!T27,'Avril'!T27,'Mai'!T27,'Juin'!T27,'Juillet'!T27,'Août'!T27,'Septembre'!T27,'Octobre'!T27,'Novembre'!T27,'Décembre'!T27),"") | AG24: =IF(ISNUMBER(CHOOSE($Z$3,'Janvier'!U27,'Février'!U27,'Mars'!U27,'Avril'!U27,'Mai'!U27,'Juin'!U27,'Juillet'!U27,'Août'!U27,'Septembre'!U27,'Octobre'!U27,'Novembre'!U27,'Décembre'!U27)),CHOOSE($Z$3,'Janvier'!U27,'Février'!U27,'Mars'!U27,'Avril'!U27,'Mai'!U27,'Juin'!U27,'Juillet'!U27,'Août'!U27,'Septembre'!U27,'Octobre'!U27,'Novembre'!U27,'Décembre'!U27),"") | AH24: =IF(ISNUMBER(CHOOSE($Z$3,'Janvier'!V27,'Février'!V27,'Mars'!V27,'Avril'!V27,'Mai'!V27,'Juin'!V27,'Juillet'!V27,'Août'!V27,'Septembre'!V27,'Octobre'!V27,'Novembre'!V27,'Décembre'!V27)),CHOOSE($Z$3,'Janvier'!V27,'Février'!V27,'Mars'!V27,'Avril'!V27,'Mai'!V27,'Juin'!V27,'Juillet'!V27,'Août'!V27,'Septembre'!V27,'Octobre'!V27,'Novembre'!V27,'Décembre'!V27),"") | AI24: =IF(ISNUMBER(CHOOSE($Z$3,'Janvier'!W27,'Février'!W27,'Mars'!W27,'Avril'!W27,'Mai'!W27,'Juin'!W27,'Juillet'!W27,'Août'!W27,'Septembre'!W27,'Octobre'!W27,'Novembre'!W27,'Décembre'!W27)),CHOOSE($Z$3,'Janvier'!W27,'Février'!W27,'Mars'!W27,'Avril'!W27,'Mai'!W27,'Juin'!W27,'Juillet'!W27,'Août'!W27,'Septembre'!W27,'Octobre'!W27,'Novembre'!W27,'Décembre'!W27),"") | AJ24: =IF(Produits!$A$26="","",Produits!$D$26) | AK24: =IF(ISNUMBER(CHOOSE($Z$3,'Janvier'!X27,'Février'!X27,'Mars'!X27,'Avril'!X27,'Mai'!X27,'Juin'!X27,'Juillet'!X27,'Août'!X27,'Septembre'!X27,'Octobre'!X27,'Novembre'!X27,'Décembre'!X27)),CHOOSE($Z$3,'Janvier'!X27,'Février'!X27,'Mars'!X27,'Avril'!X27,'Mai'!X27,'Juin'!X27,'Juillet'!X27,'Août'!X27,'Septembre'!X27,'Octobre'!X27,'Novembre'!X27,'Décembre'!X27),"") | AL24: =IF(AND(ISNUMBER(AI24),ISNUMBER(AJ24)),IF(AI24<=AJ24,1,0),0) | AM24: =IF(OR(AA24="",AK24=""),-1,AK24+ROW()/1000000)
A25: Produit | C25: S1 | D25: S2 | E25: S3 | F25: S4 | G25: Évol. | H25: Dernier stock | I25: Mini | J25: Alerte | AA25: =IF(Produits!$A$27="","",Produits!$A$27) | AB25: =IF(ISNUMBER(CHOOSE($Z$3,'Janvier'!E28,'Février'!E28,'Mars'!E28,'Avril'!E28,'Mai'!E28,'Juin'!E28,'Juillet'!E28,'Août'!E28,'Septembre'!E28,'Octobre'!E28,'Novembre'!E28,'Décembre'!E28)),CHOOSE($Z$3,'Janvier'!E28,'Février'!E28,'Mars'!E28,'Avril'!E28,'Mai'!E28,'Juin'!E28,'Juillet'!E28,'Août'!E28,'Septembre'!E28,'Octobre'!E28,'Novembre'!E28,'Décembre'!E28),"") | AC25: =IF(ISNUMBER(CHOOSE($Z$3,'Janvier'!I28,'Février'!I28,'Mars'!I28,'Avril'!I28,'Mai'!I28,'Juin'!I28,'Juillet'!I28,'Août'!I28,'Septembre'!I28,'Octobre'!I28,'Novembre'!I28,'Décembre'!I28)),CHOOSE($Z$3,'Janvier'!I28,'Février'!I28,'Mars'!I28,'Avril'!I28,'Mai'!I28,'Juin'!I28,'Juillet'!I28,'Août'!I28,'Septembre'!I28,'Octobre'!I28,'Novembre'!I28,'Décembre'!I28),"") | AD25: =IF(ISNUMBER(CHOOSE($Z$3,'Janvier'!M28,'Février'!M28,'Mars'!M28,'Avril'!M28,'Mai'!M28,'Juin'!M28,'Juillet'!M28,'Août'!M28,'Septembre'!M28,'Octobre'!M28,'Novembre'!M28,'Décembre'!M28)),CHOOSE($Z$3,'Janvier'!M28,'Février'!M28,'Mars'!M28,'Avril'!M28,'Mai'!M28,'Juin'!M28,'Juillet'!M28,'Août'!M28,'Septembre'!M28,'Octobre'!M28,'Novembre'!M28,'Décembre'!M28),"") | AE25: =IF(ISNUMBER(CHOOSE($Z$3,'Janvier'!Q28,'Février'!Q28,'Mars'!Q28,'Avril'!Q28,'Mai'!Q28,'Juin'!Q28,'Juillet'!Q28,'Août'!Q28,'Septembre'!Q28,'Octobre'!Q28,'Novembre'!Q28,'Décembre'!Q28)),CHOOSE($Z$3,'Janvier'!Q28,'Février'!Q28,'Mars'!Q28,'Avril'!Q28,'Mai'!Q28,'Juin'!Q28,'Juillet'!Q28,'Août'!Q28,'Septembre'!Q28,'Octobre'!Q28,'Novembre'!Q28,'Décembre'!Q28),"") | AF25: =IF(ISNUMBER(CHOOSE($Z$3,'Janvier'!T28,'Février'!T28,'Mars'!T28,'Avril'!T28,'Mai'!T28,'Juin'!T28,'Juillet'!T28,'Août'!T28,'Septembre'!T28,'Octobre'!T28,'Novembre'!T28,'Décembre'!T28)),CHOOSE($Z$3,'Janvier'!T28,'Février'!T28,'Mars'!T28,'Avril'!T28,'Mai'!T28,'Juin'!T28,'Juillet'!T28,'Août'!T28,'Septembre'!T28,'Octobre'!T28,'Novembre'!T28,'Décembre'!T28),"") | AG25: =IF(ISNUMBER(CHOOSE($Z$3,'Janvier'!U28,'Février'!U28,'Mars'!U28,'Avril'!U28,'Mai'!U28,'Juin'!U28,'Juillet'!U28,'Août'!U28,'Septembre'!U28,'Octobre'!U28,'Novembre'!U28,'Décembre'!U28)),CHOOSE($Z$3,'Janvier'!U28,'Février'!U28,'Mars'!U28,'Avril'!U28,'Mai'!U28,'Juin'!U28,'Juillet'!U28,'Août'!U28,'Septembre'!U28,'Octobre'!U28,'Novembre'!U28,'Décembre'!U28),"") | AH25: =IF(ISNUMBER(CHOOSE($Z$3,'Janvier'!V28,'Février'!V28,'Mars'!V28,'Avril'!V28,'Mai'!V28,'Juin'!V28,'Juillet'!V28,'Août'!V28,'Septembre'!V28,'Octobre'!V28,'Novembre'!V28,'Décembre'!V28)),CHOOSE($Z$3,'Janvier'!V28,'Février'!V28,'Mars'!V28,'Avril'!V28,'Mai'!V28,'Juin'!V28,'Juillet'!V28,'Août'!V28,'Septembre'!V28,'Octobre'!V28,'Novembre'!V28,'Décembre'!V28),"") | AI25: =IF(ISNUMBER(CHOOSE($Z$3,'Janvier'!W28,'Février'!W28,'Mars'!W28,'Avril'!W28,'Mai'!W28,'Juin'!W28,'Juillet'!W28,'Août'!W28,'Septembre'!W28,'Octobre'!W28,'Novembre'!W28,'Décembre'!W28)),CHOOSE($Z$3,'Janvier'!W28,'Février'!W28,'Mars'!W28,'Avril'!W28,'Mai'!W28,'Juin'!W28,'Juillet'!W28,'Août'!W28,'Septembre'!W28,'Octobre'!W28,'Novembre'!W28,'Décembre'!W28),"") | AJ25: =IF(Produits!$A$27="","",Produits!$D$27) | AK25: =IF(ISNUMBER(CHOOSE($Z$3,'Janvier'!X28,'Février'!X28,'Mars'!X28,'Avril'!X28,'Mai'!X28,'Juin'!X28,'Juillet'!X28,'Août'!X28,'Septembre'!X28,'Octobre'!X28,'Novembre'!X28,'Décembre'!X28)),CHOOSE($Z$3,'Janvier'!X28,'Février'!X28,'Mars'!X28,'Avril'!X28,'Mai'!X28,'Juin'!X28,'Juillet'!X28,'Août'!X28,'Septembre'!X28,'Octobre'!X28,'Novembre'!X28,'Décembre'!X28),"") | AL25: =IF(AND(ISNUMBER(AI25),ISNUMBER(AJ25)),IF(AI25<=AJ25,1,0),0) | AM25: =IF(OR(AA25="",AK25=""),-1,AK25+ROW()/1000000)
A26: =AA5 | C26: =IF(OR(AB5="",MAX(AB5,AC5,AD5,AE5)=0),"",REPT("█",MAX(1,ROUND(AB5/MAX(AB5,AC5,AD5,AE5)*6,0)))) | D26: =IF(OR(AC5="",MAX(AB5,AC5,AD5,AE5)=0),"",REPT("█",MAX(1,ROUND(AC5/MAX(AB5,AC5,AD5,AE5)*6,0)))) | E26: =IF(OR(AD5="",MAX(AB5,AC5,AD5,AE5)=0),"",REPT("█",MAX(1,ROUND(AD5/MAX(AB5,AC5,AD5,AE5)*6,0)))) | F26: =IF(OR(AE5="",MAX(AB5,AC5,AD5,AE5)=0),"",REPT("█",MAX(1,ROUND(AE5/MAX(AB5,AC5,AD5,AE5)*6,0)))) | G26: =IF(COUNT(AB5,AC5,AD5,AE5)<2,"",IF(IF(AE5<>"",AE5,IF(AD5<>"",AD5,IF(AC5<>"",AC5,IF(AB5<>"",AB5,""))))>IF(AB5<>"",AB5,IF(AC5<>"",AC5,IF(AD5<>"",AD5,AE5))),"▲",IF(IF(AE5<>"",AE5,IF(AD5<>"",AD5,IF(AC5<>"",AC5,IF(AB5<>"",AB5,""))))<IF(AB5<>"",AB5,IF(AC5<>"",AC5,IF(AD5<>"",AD5,AE5))),"▼","="))) | H26: =AI5 | I26: =AJ5 | J26: =IF(AL5=1,"À COMMANDER",IF(AA5="","","")) | AA26: =IF(Produits!$A$28="","",Produits!$A$28) | AB26: =IF(ISNUMBER(CHOOSE($Z$3,'Janvier'!E29,'Février'!E29,'Mars'!E29,'Avril'!E29,'Mai'!E29,'Juin'!E29,'Juillet'!E29,'Août'!E29,'Septembre'!E29,'Octobre'!E29,'Novembre'!E29,'Décembre'!E29)),CHOOSE($Z$3,'Janvier'!E29,'Février'!E29,'Mars'!E29,'Avril'!E29,'Mai'!E29,'Juin'!E29,'Juillet'!E29,'Août'!E29,'Septembre'!E29,'Octobre'!E29,'Novembre'!E29,'Décembre'!E29),"") | AC26: =IF(ISNUMBER(CHOOSE($Z$3,'Janvier'!I29,'Février'!I29,'Mars'!I29,'Avril'!I29,'Mai'!I29,'Juin'!I29,'Juillet'!I29,'Août'!I29,'Septembre'!I29,'Octobre'!I29,'Novembre'!I29,'Décembre'!I29)),CHOOSE($Z$3,'Janvier'!I29,'Février'!I29,'Mars'!I29,'Avril'!I29,'Mai'!I29,'Juin'!I29,'Juillet'!I29,'Août'!I29,'Septembre'!I29,'Octobre'!I29,'Novembre'!I29,'Décembre'!I29),"") | AD26: =IF(ISNUMBER(CHOOSE($Z$3,'Janvier'!M29,'Février'!M29,'Mars'!M29,'Avril'!M29,'Mai'!M29,'Juin'!M29,'Juillet'!M29,'Août'!M29,'Septembre'!M29,'Octobre'!M29,'Novembre'!M29,'Décembre'!M29)),CHOOSE($Z$3,'Janvier'!M29,'Février'!M29,'Mars'!M29,'Avril'!M29,'Mai'!M29,'Juin'!M29,'Juillet'!M29,'Août'!M29,'Septembre'!M29,'Octobre'!M29,'Novembre'!M29,'Décembre'!M29),"") | AE26: =IF(ISNUMBER(CHOOSE($Z$3,'Janvier'!Q29,'Février'!Q29,'Mars'!Q29,'Avril'!Q29,'Mai'!Q29,'Juin'!Q29,'Juillet'!Q29,'Août'!Q29,'Septembre'!Q29,'Octobre'!Q29,'Novembre'!Q29,'Décembre'!Q29)),CHOOSE($Z$3,'Janvier'!Q29,'Février'!Q29,'Mars'!Q29,'Avril'!Q29,'Mai'!Q29,'Juin'!Q29,'Juillet'!Q29,'Août'!Q29,'Septembre'!Q29,'Octobre'!Q29,'Novembre'!Q29,'Décembre'!Q29),"") | AF26: =IF(ISNUMBER(CHOOSE($Z$3,'Janvier'!T29,'Février'!T29,'Mars'!T29,'Avril'!T29,'Mai'!T29,'Juin'!T29,'Juillet'!T29,'Août'!T29,'Septembre'!T29,'Octobre'!T29,'Novembre'!T29,'Décembre'!T29)),CHOOSE($Z$3,'Janvier'!T29,'Février'!T29,'Mars'!T29,'Avril'!T29,'Mai'!T29,'Juin'!T29,'Juillet'!T29,'Août'!T29,'Septembre'!T29,'Octobre'!T29,'Novembre'!T29,'Décembre'!T29),"") | AG26: =IF(ISNUMBER(CHOOSE($Z$3,'Janvier'!U29,'Février'!U29,'Mars'!U29,'Avril'!U29,'Mai'!U29,'Juin'!U29,'Juillet'!U29,'Août'!U29,'Septembre'!U29,'Octobre'!U29,'Novembre'!U29,'Décembre'!U29)),CHOOSE($Z$3,'Janvier'!U29,'Février'!U29,'Mars'!U29,'Avril'!U29,'Mai'!U29,'Juin'!U29,'Juillet'!U29,'Août'!U29,'Septembre'!U29,'Octobre'!U29,'Novembre'!U29,'Décembre'!U29),"") | AH26: =IF(ISNUMBER(CHOOSE($Z$3,'Janvier'!V29,'Février'!V29,'Mars'!V29,'Avril'!V29,'Mai'!V29,'Juin'!V29,'Juillet'!V29,'Août'!V29,'Septembre'!V29,'Octobre'!V29,'Novembre'!V29,'Décembre'!V29)),CHOOSE($Z$3,'Janvier'!V29,'Février'!V29,'Mars'!V29,'Avril'!V29,'Mai'!V29,'Juin'!V29,'Juillet'!V29,'Août'!V29,'Septembre'!V29,'Octobre'!V29,'Novembre'!V29,'Décembre'!V29),"") | AI26: =IF(ISNUMBER(CHOOSE($Z$3,'Janvier'!W29,'Février'!W29,'Mars'!W29,'Avril'!W29,'Mai'!W29,'Juin'!W29,'Juillet'!W29,'Août'!W29,'Septembre'!W29,'Octobre'!W29,'Novembre'!W29,'Décembre'!W29)),CHOOSE($Z$3,'Janvier'!W29,'Février'!W29,'Mars'!W29,'Avril'!W29,'Mai'!W29,'Juin'!W29,'Juillet'!W29,'Août'!W29,'Septembre'!W29,'Octobre'!W29,'Novembre'!W29,'Décembre'!W29),"") | AJ26: =IF(Produits!$A$28="","",Produits!$D$28) | AK26: =IF(ISNUMBER(CHOOSE($Z$3,'Janvier'!X29,'Février'!X29,'Mars'!X29,'Avril'!X29,'Mai'!X29,'Juin'!X29,'Juillet'!X29,'Août'!X29,'Septembre'!X29,'Octobre'!X29,'Novembre'!X29,'Décembre'!X29)),CHOOSE($Z$3,'Janvier'!X29,'Février'!X29,'Mars'!X29,'Avril'!X29,'Mai'!X29,'Juin'!X29,'Juillet'!X29,'Août'!X29,'Septembre'!X29,'Octobre'!X29,'Novembre'!X29,'Décembre'!X29),"") | AL26: =IF(AND(ISNUMBER(AI26),ISNUMBER(AJ26)),IF(AI26<=AJ26,1,0),0) | AM26: =IF(OR(AA26="",AK26=""),-1,AK26+ROW()/1000000)
A27: =AA6 | C27: =IF(OR(AB6="",MAX(AB6,AC6,AD6,AE6)=0),"",REPT("█",MAX(1,ROUND(AB6/MAX(AB6,AC6,AD6,AE6)*6,0)))) | D27: =IF(OR(AC6="",MAX(AB6,AC6,AD6,AE6)=0),"",REPT("█",MAX(1,ROUND(AC6/MAX(AB6,AC6,AD6,AE6)*6,0)))) | E27: =IF(OR(AD6="",MAX(AB6,AC6,AD6,AE6)=0),"",REPT("█",MAX(1,ROUND(AD6/MAX(AB6,AC6,AD6,AE6)*6,0)))) | F27: =IF(OR(AE6="",MAX(AB6,AC6,AD6,AE6)=0),"",REPT("█",MAX(1,ROUND(AE6/MAX(AB6,AC6,AD6,AE6)*6,0)))) | G27: =IF(COUNT(AB6,AC6,AD6,AE6)<2,"",IF(IF(AE6<>"",AE6,IF(AD6<>"",AD6,IF(AC6<>"",AC6,IF(AB6<>"",AB6,""))))>IF(AB6<>"",AB6,IF(AC6<>"",AC6,IF(AD6<>"",AD6,AE6))),"▲",IF(IF(AE6<>"",AE6,IF(AD6<>"",AD6,IF(AC6<>"",AC6,IF(AB6<>"",AB6,""))))<IF(AB6<>"",AB6,IF(AC6<>"",AC6,IF(AD6<>"",AD6,AE6))),"▼","="))) | H27: =AI6 | I27: =AJ6 | J27: =IF(AL6=1,"À COMMANDER",IF(AA6="","","")) | AA27: =IF(Produits!$A$29="","",Produits!$A$29) | AB27: =IF(ISNUMBER(CHOOSE($Z$3,'Janvier'!E30,'Février'!E30,'Mars'!E30,'Avril'!E30,'Mai'!E30,'Juin'!E30,'Juillet'!E30,'Août'!E30,'Septembre'!E30,'Octobre'!E30,'Novembre'!E30,'Décembre'!E30)),CHOOSE($Z$3,'Janvier'!E30,'Février'!E30,'Mars'!E30,'Avril'!E30,'Mai'!E30,'Juin'!E30,'Juillet'!E30,'Août'!E30,'Septembre'!E30,'Octobre'!E30,'Novembre'!E30,'Décembre'!E30),"") | AC27: =IF(ISNUMBER(CHOOSE($Z$3,'Janvier'!I30,'Février'!I30,'Mars'!I30,'Avril'!I30,'Mai'!I30,'Juin'!I30,'Juillet'!I30,'Août'!I30,'Septembre'!I30,'Octobre'!I30,'Novembre'!I30,'Décembre'!I30)),CHOOSE($Z$3,'Janvier'!I30,'Février'!I30,'Mars'!I30,'Avril'!I30,'Mai'!I30,'Juin'!I30,'Juillet'!I30,'Août'!I30,'Septembre'!I30,'Octobre'!I30,'Novembre'!I30,'Décembre'!I30),"") | AD27: =IF(ISNUMBER(CHOOSE($Z$3,'Janvier'!M30,'Février'!M30,'Mars'!M30,'Avril'!M30,'Mai'!M30,'Juin'!M30,'Juillet'!M30,'Août'!M30,'Septembre'!M30,'Octobre'!M30,'Novembre'!M30,'Décembre'!M30)),CHOOSE($Z$3,'Janvier'!M30,'Février'!M30,'Mars'!M30,'Avril'!M30,'Mai'!M30,'Juin'!M30,'Juillet'!M30,'Août'!M30,'Septembre'!M30,'Octobre'!M30,'Novembre'!M30,'Décembre'!M30),"") | AE27: =IF(ISNUMBER(CHOOSE($Z$3,'Janvier'!Q30,'Février'!Q30,'Mars'!Q30,'Avril'!Q30,'Mai'!Q30,'Juin'!Q30,'Juillet'!Q30,'Août'!Q30,'Septembre'!Q30,'Octobre'!Q30,'Novembre'!Q30,'Décembre'!Q30)),CHOOSE($Z$3,'Janvier'!Q30,'Février'!Q30,'Mars'!Q30,'Avril'!Q30,'Mai'!Q30,'Juin'!Q30,'Juillet'!Q30,'Août'!Q30,'Septembre'!Q30,'Octobre'!Q30,'Novembre'!Q30,'Décembre'!Q30),"") | AF27: =IF(ISNUMBER(CHOOSE($Z$3,'Janvier'!T30,'Février'!T30,'Mars'!T30,'Avril'!T30,'Mai'!T30,'Juin'!T30,'Juillet'!T30,'Août'!T30,'Septembre'!T30,'Octobre'!T30,'Novembre'!T30,'Décembre'!T30)),CHOOSE($Z$3,'Janvier'!T30,'Février'!T30,'Mars'!T30,'Avril'!T30,'Mai'!T30,'Juin'!T30,'Juillet'!T30,'Août'!T30,'Septembre'!T30,'Octobre'!T30,'Novembre'!T30,'Décembre'!T30),"") | AG27: =IF(ISNUMBER(CHOOSE($Z$3,'Janvier'!U30,'Février'!U30,'Mars'!U30,'Avril'!U30,'Mai'!U30,'Juin'!U30,'Juillet'!U30,'Août'!U30,'Septembre'!U30,'Octobre'!U30,'Novembre'!U30,'Décembre'!U30)),CHOOSE($Z$3,'Janvier'!U30,'Février'!U30,'Mars'!U30,'Avril'!U30,'Mai'!U30,'Juin'!U30,'Juillet'!U30,'Août'!U30,'Septembre'!U30,'Octobre'!U30,'Novembre'!U30,'Décembre'!U30),"") | AH27: =IF(ISNUMBER(CHOOSE($Z$3,'Janvier'!V30,'Février'!V30,'Mars'!V30,'Avril'!V30,'Mai'!V30,'Juin'!V30,'Juillet'!V30,'Août'!V30,'Septembre'!V30,'Octobre'!V30,'Novembre'!V30,'Décembre'!V30)),CHOOSE($Z$3,'Janvier'!V30,'Février'!V30,'Mars'!V30,'Avril'!V30,'Mai'!V30,'Juin'!V30,'Juillet'!V30,'Août'!V30,'Septembre'!V30,'Octobre'!V30,'Novembre'!V30,'Décembre'!V30),"") | AI27: =IF(ISNUMBER(CHOOSE($Z$3,'Janvier'!W30,'Février'!W30,'Mars'!W30,'Avril'!W30,'Mai'!W30,'Juin'!W30,'Juillet'!W30,'Août'!W30,'Septembre'!W30,'Octobre'!W30,'Novembre'!W30,'Décembre'!W30)),CHOOSE($Z$3,'Janvier'!W30,'Février'!W30,'Mars'!W30,'Avril'!W30,'Mai'!W30,'Juin'!W30,'Juillet'!W30,'Août'!W30,'Septembre'!W30,'Octobre'!W30,'Novembre'!W30,'Décembre'!W30),"") | AJ27: =IF(Produits!$A$29="","",Produits!$D$29) | AK27: =IF(ISNUMBER(CHOOSE($Z$3,'Janvier'!X30,'Février'!X30,'Mars'!X30,'Avril'!X30,'Mai'!X30,'Juin'!X30,'Juillet'!X30,'Août'!X30,'Septembre'!X30,'Octobre'!X30,'Novembre'!X30,'Décembre'!X30)),CHOOSE($Z$3,'Janvier'!X30,'Février'!X30,'Mars'!X30,'Avril'!X30,'Mai'!X30,'Juin'!X30,'Juillet'!X30,'Août'!X30,'Septembre'!X30,'Octobre'!X30,'Novembre'!X30,'Décembre'!X30),"") | AL27: =IF(AND(ISNUMBER(AI27),ISNUMBER(AJ27)),IF(AI27<=AJ27,1,0),0) | AM27: =IF(OR(AA27="",AK27=""),-1,AK27+ROW()/1000000)
A28: =AA7 | C28: =IF(OR(AB7="",MAX(AB7,AC7,AD7,AE7)=0),"",REPT("█",MAX(1,ROUND(AB7/MAX(AB7,AC7,AD7,AE7)*6,0)))) | D28: =IF(OR(AC7="",MAX(AB7,AC7,AD7,AE7)=0),"",REPT("█",MAX(1,ROUND(AC7/MAX(AB7,AC7,AD7,AE7)*6,0)))) | E28: =IF(OR(AD7="",MAX(AB7,AC7,AD7,AE7)=0),"",REPT("█",MAX(1,ROUND(AD7/MAX(AB7,AC7,AD7,AE7)*6,0)))) | F28: =IF(OR(AE7="",MAX(AB7,AC7,AD7,AE7)=0),"",REPT("█",MAX(1,ROUND(AE7/MAX(AB7,AC7,AD7,AE7)*6,0)))) | G28: =IF(COUNT(AB7,AC7,AD7,AE7)<2,"",IF(IF(AE7<>"",AE7,IF(AD7<>"",AD7,IF(AC7<>"",AC7,IF(AB7<>"",AB7,""))))>IF(AB7<>"",AB7,IF(AC7<>"",AC7,IF(AD7<>"",AD7,AE7))),"▲",IF(IF(AE7<>"",AE7,IF(AD7<>"",AD7,IF(AC7<>"",AC7,IF(AB7<>"",AB7,""))))<IF(AB7<>"",AB7,IF(AC7<>"",AC7,IF(AD7<>"",AD7,AE7))),"▼","="))) | H28: =AI7 | I28: =AJ7 | J28: =IF(AL7=1,"À COMMANDER",IF(AA7="","","")) | AA28: =IF(Produits!$A$30="","",Produits!$A$30) | AB28: =IF(ISNUMBER(CHOOSE($Z$3,'Janvier'!E31,'Février'!E31,'Mars'!E31,'Avril'!E31,'Mai'!E31,'Juin'!E31,'Juillet'!E31,'Août'!E31,'Septembre'!E31,'Octobre'!E31,'Novembre'!E31,'Décembre'!E31)),CHOOSE($Z$3,'Janvier'!E31,'Février'!E31,'Mars'!E31,'Avril'!E31,'Mai'!E31,'Juin'!E31,'Juillet'!E31,'Août'!E31,'Septembre'!E31,'Octobre'!E31,'Novembre'!E31,'Décembre'!E31),"") | AC28: =IF(ISNUMBER(CHOOSE($Z$3,'Janvier'!I31,'Février'!I31,'Mars'!I31,'Avril'!I31,'Mai'!I31,'Juin'!I31,'Juillet'!I31,'Août'!I31,'Septembre'!I31,'Octobre'!I31,'Novembre'!I31,'Décembre'!I31)),CHOOSE($Z$3,'Janvier'!I31,'Février'!I31,'Mars'!I31,'Avril'!I31,'Mai'!I31,'Juin'!I31,'Juillet'!I31,'Août'!I31,'Septembre'!I31,'Octobre'!I31,'Novembre'!I31,'Décembre'!I31),"") | AD28: =IF(ISNUMBER(CHOOSE($Z$3,'Janvier'!M31,'Février'!M31,'Mars'!M31,'Avril'!M31,'Mai'!M31,'Juin'!M31,'Juillet'!M31,'Août'!M31,'Septembre'!M31,'Octobre'!M31,'Novembre'!M31,'Décembre'!M31)),CHOOSE($Z$3,'Janvier'!M31,'Février'!M31,'Mars'!M31,'Avril'!M31,'Mai'!M31,'Juin'!M31,'Juillet'!M31,'Août'!M31,'Septembre'!M31,'Octobre'!M31,'Novembre'!M31,'Décembre'!M31),"") | AE28: =IF(ISNUMBER(CHOOSE($Z$3,'Janvier'!Q31,'Février'!Q31,'Mars'!Q31,'Avril'!Q31,'Mai'!Q31,'Juin'!Q31,'Juillet'!Q31,'Août'!Q31,'Septembre'!Q31,'Octobre'!Q31,'Novembre'!Q31,'Décembre'!Q31)),CHOOSE($Z$3,'Janvier'!Q31,'Février'!Q31,'Mars'!Q31,'Avril'!Q31,'Mai'!Q31,'Juin'!Q31,'Juillet'!Q31,'Août'!Q31,'Septembre'!Q31,'Octobre'!Q31,'Novembre'!Q31,'Décembre'!Q31),"") | AF28: =IF(ISNUMBER(CHOOSE($Z$3,'Janvier'!T31,'Février'!T31,'Mars'!T31,'Avril'!T31,'Mai'!T31,'Juin'!T31,'Juillet'!T31,'Août'!T31,'Septembre'!T31,'Octobre'!T31,'Novembre'!T31,'Décembre'!T31)),CHOOSE($Z$3,'Janvier'!T31,'Février'!T31,'Mars'!T31,'Avril'!T31,'Mai'!T31,'Juin'!T31,'Juillet'!T31,'Août'!T31,'Septembre'!T31,'Octobre'!T31,'Novembre'!T31,'Décembre'!T31),"") | AG28: =IF(ISNUMBER(CHOOSE($Z$3,'Janvier'!U31,'Février'!U31,'Mars'!U31,'Avril'!U31,'Mai'!U31,'Juin'!U31,'Juillet'!U31,'Août'!U31,'Septembre'!U31,'Octobre'!U31,'Novembre'!U31,'Décembre'!U31)),CHOOSE($Z$3,'Janvier'!U31,'Février'!U31,'Mars'!U31,'Avril'!U31,'Mai'!U31,'Juin'!U31,'Juillet'!U31,'Août'!U31,'Septembre'!U31,'Octobre'!U31,'Novembre'!U31,'Décembre'!U31),"") | AH28: =IF(ISNUMBER(CHOOSE($Z$3,'Janvier'!V31,'Février'!V31,'Mars'!V31,'Avril'!V31,'Mai'!V31,'Juin'!V31,'Juillet'!V31,'Août'!V31,'Septembre'!V31,'Octobre'!V31,'Novembre'!V31,'Décembre'!V31)),CHOOSE($Z$3,'Janvier'!V31,'Février'!V31,'Mars'!V31,'Avril'!V31,'Mai'!V31,'Juin'!V31,'Juillet'!V31,'Août'!V31,'Septembre'!V31,'Octobre'!V31,'Novembre'!V31,'Décembre'!V31),"") | AI28: =IF(ISNUMBER(CHOOSE($Z$3,'Janvier'!W31,'Février'!W31,'Mars'!W31,'Avril'!W31,'Mai'!W31,'Juin'!W31,'Juillet'!W31,'Août'!W31,'Septembre'!W31,'Octobre'!W31,'Novembre'!W31,'Décembre'!W31)),CHOOSE($Z$3,'Janvier'!W31,'Février'!W31,'Mars'!W31,'Avril'!W31,'Mai'!W31,'Juin'!W31,'Juillet'!W31,'Août'!W31,'Septembre'!W31,'Octobre'!W31,'Novembre'!W31,'Décembre'!W31),"") | AJ28: =IF(Produits!$A$30="","",Produits!$D$30) | AK28: =IF(ISNUMBER(CHOOSE($Z$3,'Janvier'!X31,'Février'!X31,'Mars'!X31,'Avril'!X31,'Mai'!X31,'Juin'!X31,'Juillet'!X31,'Août'!X31,'Septembre'!X31,'Octobre'!X31,'Novembre'!X31,'Décembre'!X31)),CHOOSE($Z$3,'Janvier'!X31,'Février'!X31,'Mars'!X31,'Avril'!X31,'Mai'!X31,'Juin'!X31,'Juillet'!X31,'Août'!X31,'Septembre'!X31,'Octobre'!X31,'Novembre'!X31,'Décembre'!X31),"") | AL28: =IF(AND(ISNUMBER(AI28),ISNUMBER(AJ28)),IF(AI28<=AJ28,1,0),0) | AM28: =IF(OR(AA28="",AK28=""),-1,AK28+ROW()/1000000)
A29: =AA8 | C29: =IF(OR(AB8="",MAX(AB8,AC8,AD8,AE8)=0),"",REPT("█",MAX(1,ROUND(AB8/MAX(AB8,AC8,AD8,AE8)*6,0)))) | D29: =IF(OR(AC8="",MAX(AB8,AC8,AD8,AE8)=0),"",REPT("█",MAX(1,ROUND(AC8/MAX(AB8,AC8,AD8,AE8)*6,0)))) | E29: =IF(OR(AD8="",MAX(AB8,AC8,AD8,AE8)=0),"",REPT("█",MAX(1,ROUND(AD8/MAX(AB8,AC8,AD8,AE8)*6,0)))) | F29: =IF(OR(AE8="",MAX(AB8,AC8,AD8,AE8)=0),"",REPT("█",MAX(1,ROUND(AE8/MAX(AB8,AC8,AD8,AE8)*6,0)))) | G29: =IF(COUNT(AB8,AC8,AD8,AE8)<2,"",IF(IF(AE8<>"",AE8,IF(AD8<>"",AD8,IF(AC8<>"",AC8,IF(AB8<>"",AB8,""))))>IF(AB8<>"",AB8,IF(AC8<>"",AC8,IF(AD8<>"",AD8,AE8))),"▲",IF(IF(AE8<>"",AE8,IF(AD8<>"",AD8,IF(AC8<>"",AC8,IF(AB8<>"",AB8,""))))<IF(AB8<>"",AB8,IF(AC8<>"",AC8,IF(AD8<>"",AD8,AE8))),"▼","="))) | H29: =AI8 | I29: =AJ8 | J29: =IF(AL8=1,"À COMMANDER",IF(AA8="","","")) | AA29: =IF(Produits!$A$31="","",Produits!$A$31) | AB29: =IF(ISNUMBER(CHOOSE($Z$3,'Janvier'!E32,'Février'!E32,'Mars'!E32,'Avril'!E32,'Mai'!E32,'Juin'!E32,'Juillet'!E32,'Août'!E32,'Septembre'!E32,'Octobre'!E32,'Novembre'!E32,'Décembre'!E32)),CHOOSE($Z$3,'Janvier'!E32,'Février'!E32,'Mars'!E32,'Avril'!E32,'Mai'!E32,'Juin'!E32,'Juillet'!E32,'Août'!E32,'Septembre'!E32,'Octobre'!E32,'Novembre'!E32,'Décembre'!E32),"") | AC29: =IF(ISNUMBER(CHOOSE($Z$3,'Janvier'!I32,'Février'!I32,'Mars'!I32,'Avril'!I32,'Mai'!I32,'Juin'!I32,'Juillet'!I32,'Août'!I32,'Septembre'!I32,'Octobre'!I32,'Novembre'!I32,'Décembre'!I32)),CHOOSE($Z$3,'Janvier'!I32,'Février'!I32,'Mars'!I32,'Avril'!I32,'Mai'!I32,'Juin'!I32,'Juillet'!I32,'Août'!I32,'Septembre'!I32,'Octobre'!I32,'Novembre'!I32,'Décembre'!I32),"") | AD29: =IF(ISNUMBER(CHOOSE($Z$3,'Janvier'!M32,'Février'!M32,'Mars'!M32,'Avril'!M32,'Mai'!M32,'Juin'!M32,'Juillet'!M32,'Août'!M32,'Septembre'!M32,'Octobre'!M32,'Novembre'!M32,'Décembre'!M32)),CHOOSE($Z$3,'Janvier'!M32,'Février'!M32,'Mars'!M32,'Avril'!M32,'Mai'!M32,'Juin'!M32,'Juillet'!M32,'Août'!M32,'Septembre'!M32,'Octobre'!M32,'Novembre'!M32,'Décembre'!M32),"") | AE29: =IF(ISNUMBER(CHOOSE($Z$3,'Janvier'!Q32,'Février'!Q32,'Mars'!Q32,'Avril'!Q32,'Mai'!Q32,'Juin'!Q32,'Juillet'!Q32,'Août'!Q32,'Septembre'!Q32,'Octobre'!Q32,'Novembre'!Q32,'Décembre'!Q32)),CHOOSE($Z$3,'Janvier'!Q32,'Février'!Q32,'Mars'!Q32,'Avril'!Q32,'Mai'!Q32,'Juin'!Q32,'Juillet'!Q32,'Août'!Q32,'Septembre'!Q32,'Octobre'!Q32,'Novembre'!Q32,'Décembre'!Q32),"") | AF29: =IF(ISNUMBER(CHOOSE($Z$3,'Janvier'!T32,'Février'!T32,'Mars'!T32,'Avril'!T32,'Mai'!T32,'Juin'!T32,'Juillet'!T32,'Août'!T32,'Septembre'!T32,'Octobre'!T32,'Novembre'!T32,'Décembre'!T32)),CHOOSE($Z$3,'Janvier'!T32,'Février'!T32,'Mars'!T32,'Avril'!T32,'Mai'!T32,'Juin'!T32,'Juillet'!T32,'Août'!T32,'Septembre'!T32,'Octobre'!T32,'Novembre'!T32,'Décembre'!T32),"") | AG29: =IF(ISNUMBER(CHOOSE($Z$3,'Janvier'!U32,'Février'!U32,'Mars'!U32,'Avril'!U32,'Mai'!U32,'Juin'!U32,'Juillet'!U32,'Août'!U32,'Septembre'!U32,'Octobre'!U32,'Novembre'!U32,'Décembre'!U32)),CHOOSE($Z$3,'Janvier'!U32,'Février'!U32,'Mars'!U32,'Avril'!U32,'Mai'!U32,'Juin'!U32,'Juillet'!U32,'Août'!U32,'Septembre'!U32,'Octobre'!U32,'Novembre'!U32,'Décembre'!U32),"") | AH29: =IF(ISNUMBER(CHOOSE($Z$3,'Janvier'!V32,'Février'!V32,'Mars'!V32,'Avril'!V32,'Mai'!V32,'Juin'!V32,'Juillet'!V32,'Août'!V32,'Septembre'!V32,'Octobre'!V32,'Novembre'!V32,'Décembre'!V32)),CHOOSE($Z$3,'Janvier'!V32,'Février'!V32,'Mars'!V32,'Avril'!V32,'Mai'!V32,'Juin'!V32,'Juillet'!V32,'Août'!V32,'Septembre'!V32,'Octobre'!V32,'Novembre'!V32,'Décembre'!V32),"") | AI29: =IF(ISNUMBER(CHOOSE($Z$3,'Janvier'!W32,'Février'!W32,'Mars'!W32,'Avril'!W32,'Mai'!W32,'Juin'!W32,'Juillet'!W32,'Août'!W32,'Septembre'!W32,'Octobre'!W32,'Novembre'!W32,'Décembre'!W32)),CHOOSE($Z$3,'Janvier'!W32,'Février'!W32,'Mars'!W32,'Avril'!W32,'Mai'!W32,'Juin'!W32,'Juillet'!W32,'Août'!W32,'Septembre'!W32,'Octobre'!W32,'Novembre'!W32,'Décembre'!W32),"") | AJ29: =IF(Produits!$A$31="","",Produits!$D$31) | AK29: =IF(ISNUMBER(CHOOSE($Z$3,'Janvier'!X32,'Février'!X32,'Mars'!X32,'Avril'!X32,'Mai'!X32,'Juin'!X32,'Juillet'!X32,'Août'!X32,'Septembre'!X32,'Octobre'!X32,'Novembre'!X32,'Décembre'!X32)),CHOOSE($Z$3,'Janvier'!X32,'Février'!X32,'Mars'!X32,'Avril'!X32,'Mai'!X32,'Juin'!X32,'Juillet'!X32,'Août'!X32,'Septembre'!X32,'Octobre'!X32,'Novembre'!X32,'Décembre'!X32),"") | AL29: =IF(AND(ISNUMBER(AI29),ISNUMBER(AJ29)),IF(AI29<=AJ29,1,0),0) | AM29: =IF(OR(AA29="",AK29=""),-1,AK29+ROW()/1000000)
A30: =AA9 | C30: =IF(OR(AB9="",MAX(AB9,AC9,AD9,AE9)=0),"",REPT("█",MAX(1,ROUND(AB9/MAX(AB9,AC9,AD9,AE9)*6,0)))) | D30: =IF(OR(AC9="",MAX(AB9,AC9,AD9,AE9)=0),"",REPT("█",MAX(1,ROUND(AC9/MAX(AB9,AC9,AD9,AE9)*6,0)))) | E30: =IF(OR(AD9="",MAX(AB9,AC9,AD9,AE9)=0),"",REPT("█",MAX(1,ROUND(AD9/MAX(AB9,AC9,AD9,AE9)*6,0)))) | F30: =IF(OR(AE9="",MAX(AB9,AC9,AD9,AE9)=0),"",REPT("█",MAX(1,ROUND(AE9/MAX(AB9,AC9,AD9,AE9)*6,0)))) | G30: =IF(COUNT(AB9,AC9,AD9,AE9)<2,"",IF(IF(AE9<>"",AE9,IF(AD9<>"",AD9,IF(AC9<>"",AC9,IF(AB9<>"",AB9,""))))>IF(AB9<>"",AB9,IF(AC9<>"",AC9,IF(AD9<>"",AD9,AE9))),"▲",IF(IF(AE9<>"",AE9,IF(AD9<>"",AD9,IF(AC9<>"",AC9,IF(AB9<>"",AB9,""))))<IF(AB9<>"",AB9,IF(AC9<>"",AC9,IF(AD9<>"",AD9,AE9))),"▼","="))) | H30: =AI9 | I30: =AJ9 | J30: =IF(AL9=1,"À COMMANDER",IF(AA9="","","")) | AA30: =IF(Produits!$A$32="","",Produits!$A$32) | AB30: =IF(ISNUMBER(CHOOSE($Z$3,'Janvier'!E33,'Février'!E33,'Mars'!E33,'Avril'!E33,'Mai'!E33,'Juin'!E33,'Juillet'!E33,'Août'!E33,'Septembre'!E33,'Octobre'!E33,'Novembre'!E33,'Décembre'!E33)),CHOOSE($Z$3,'Janvier'!E33,'Février'!E33,'Mars'!E33,'Avril'!E33,'Mai'!E33,'Juin'!E33,'Juillet'!E33,'Août'!E33,'Septembre'!E33,'Octobre'!E33,'Novembre'!E33,'Décembre'!E33),"") | AC30: =IF(ISNUMBER(CHOOSE($Z$3,'Janvier'!I33,'Février'!I33,'Mars'!I33,'Avril'!I33,'Mai'!I33,'Juin'!I33,'Juillet'!I33,'Août'!I33,'Septembre'!I33,'Octobre'!I33,'Novembre'!I33,'Décembre'!I33)),CHOOSE($Z$3,'Janvier'!I33,'Février'!I33,'Mars'!I33,'Avril'!I33,'Mai'!I33,'Juin'!I33,'Juillet'!I33,'Août'!I33,'Septembre'!I33,'Octobre'!I33,'Novembre'!I33,'Décembre'!I33),"") | AD30: =IF(ISNUMBER(CHOOSE($Z$3,'Janvier'!M33,'Février'!M33,'Mars'!M33,'Avril'!M33,'Mai'!M33,'Juin'!M33,'Juillet'!M33,'Août'!M33,'Septembre'!M33,'Octobre'!M33,'Novembre'!M33,'Décembre'!M33)),CHOOSE($Z$3,'Janvier'!M33,'Février'!M33,'Mars'!M33,'Avril'!M33,'Mai'!M33,'Juin'!M33,'Juillet'!M33,'Août'!M33,'Septembre'!M33,'Octobre'!M33,'Novembre'!M33,'Décembre'!M33),"") | AE30: =IF(ISNUMBER(CHOOSE($Z$3,'Janvier'!Q33,'Février'!Q33,'Mars'!Q33,'Avril'!Q33,'Mai'!Q33,'Juin'!Q33,'Juillet'!Q33,'Août'!Q33,'Septembre'!Q33,'Octobre'!Q33,'Novembre'!Q33,'Décembre'!Q33)),CHOOSE($Z$3,'Janvier'!Q33,'Février'!Q33,'Mars'!Q33,'Avril'!Q33,'Mai'!Q33,'Juin'!Q33,'Juillet'!Q33,'Août'!Q33,'Septembre'!Q33,'Octobre'!Q33,'Novembre'!Q33,'Décembre'!Q33),"") | AF30: =IF(ISNUMBER(CHOOSE($Z$3,'Janvier'!T33,'Février'!T33,'Mars'!T33,'Avril'!T33,'Mai'!T33,'Juin'!T33,'Juillet'!T33,'Août'!T33,'Septembre'!T33,'Octobre'!T33,'Novembre'!T33,'Décembre'!T33)),CHOOSE($Z$3,'Janvier'!T33,'Février'!T33,'Mars'!T33,'Avril'!T33,'Mai'!T33,'Juin'!T33,'Juillet'!T33,'Août'!T33,'Septembre'!T33,'Octobre'!T33,'Novembre'!T33,'Décembre'!T33),"") | AG30: =IF(ISNUMBER(CHOOSE($Z$3,'Janvier'!U33,'Février'!U33,'Mars'!U33,'Avril'!U33,'Mai'!U33,'Juin'!U33,'Juillet'!U33,'Août'!U33,'Septembre'!U33,'Octobre'!U33,'Novembre'!U33,'Décembre'!U33)),CHOOSE($Z$3,'Janvier'!U33,'Février'!U33,'Mars'!U33,'Avril'!U33,'Mai'!U33,'Juin'!U33,'Juillet'!U33,'Août'!U33,'Septembre'!U33,'Octobre'!U33,'Novembre'!U33,'Décembre'!U33),"") | AH30: =IF(ISNUMBER(CHOOSE($Z$3,'Janvier'!V33,'Février'!V33,'Mars'!V33,'Avril'!V33,'Mai'!V33,'Juin'!V33,'Juillet'!V33,'Août'!V33,'Septembre'!V33,'Octobre'!V33,'Novembre'!V33,'Décembre'!V33)),CHOOSE($Z$3,'Janvier'!V33,'Février'!V33,'Mars'!V33,'Avril'!V33,'Mai'!V33,'Juin'!V33,'Juillet'!V33,'Août'!V33,'Septembre'!V33,'Octobre'!V33,'Novembre'!V33,'Décembre'!V33),"") | AI30: =IF(ISNUMBER(CHOOSE($Z$3,'Janvier'!W33,'Février'!W33,'Mars'!W33,'Avril'!W33,'Mai'!W33,'Juin'!W33,'Juillet'!W33,'Août'!W33,'Septembre'!W33,'Octobre'!W33,'Novembre'!W33,'Décembre'!W33)),CHOOSE($Z$3,'Janvier'!W33,'Février'!W33,'Mars'!W33,'Avril'!W33,'Mai'!W33,'Juin'!W33,'Juillet'!W33,'Août'!W33,'Septembre'!W33,'Octobre'!W33,'Novembre'!W33,'Décembre'!W33),"") | AJ30: =IF(Produits!$A$32="","",Produits!$D$32) | AK30: =IF(ISNUMBER(CHOOSE($Z$3,'Janvier'!X33,'Février'!X33,'Mars'!X33,'Avril'!X33,'Mai'!X33,'Juin'!X33,'Juillet'!X33,'Août'!X33,'Septembre'!X33,'Octobre'!X33,'Novembre'!X33,'Décembre'!X33)),CHOOSE($Z$3,'Janvier'!X33,'Février'!X33,'Mars'!X33,'Avril'!X33,'Mai'!X33,'Juin'!X33,'Juillet'!X33,'Août'!X33,'Septembre'!X33,'Octobre'!X33,'Novembre'!X33,'Décembre'!X33),"") | AL30: =IF(AND(ISNUMBER(AI30),ISNUMBER(AJ30)),IF(AI30<=AJ30,1,0),0) | AM30: =IF(OR(AA30="",AK30=""),-1,AK30+ROW()/1000000)
A31: =AA10 | C31: =IF(OR(AB10="",MAX(AB10,AC10,AD10,AE10)=0),"",REPT("█",MAX(1,ROUND(AB10/MAX(AB10,AC10,AD10,AE10)*6,0)))) | D31: =IF(OR(AC10="",MAX(AB10,AC10,AD10,AE10)=0),"",REPT("█",MAX(1,ROUND(AC10/MAX(AB10,AC10,AD10,AE10)*6,0)))) | E31: =IF(OR(AD10="",MAX(AB10,AC10,AD10,AE10)=0),"",REPT("█",MAX(1,ROUND(AD10/MAX(AB10,AC10,AD10,AE10)*6,0)))) | F31: =IF(OR(AE10="",MAX(AB10,AC10,AD10,AE10)=0),"",REPT("█",MAX(1,ROUND(AE10/MAX(AB10,AC10,AD10,AE10)*6,0)))) | G31: =IF(COUNT(AB10,AC10,AD10,AE10)<2,"",IF(IF(AE10<>"",AE10,IF(AD10<>"",AD10,IF(AC10<>"",AC10,IF(AB10<>"",AB10,""))))>IF(AB10<>"",AB10,IF(AC10<>"",AC10,IF(AD10<>"",AD10,AE10))),"▲",IF(IF(AE10<>"",AE10,IF(AD10<>"",AD10,IF(AC10<>"",AC10,IF(AB10<>"",AB10,""))))<IF(AB10<>"",AB10,IF(AC10<>"",AC10,IF(AD10<>"",AD10,AE10))),"▼","="))) | H31: =AI10 | I31: =AJ10 | J31: =IF(AL10=1,"À COMMANDER",IF(AA10="","","")) | AA31: =IF(Produits!$A$33="","",Produits!$A$33) | AB31: =IF(ISNUMBER(CHOOSE($Z$3,'Janvier'!E34,'Février'!E34,'Mars'!E34,'Avril'!E34,'Mai'!E34,'Juin'!E34,'Juillet'!E34,'Août'!E34,'Septembre'!E34,'Octobre'!E34,'Novembre'!E34,'Décembre'!E34)),CHOOSE($Z$3,'Janvier'!E34,'Février'!E34,'Mars'!E34,'Avril'!E34,'Mai'!E34,'Juin'!E34,'Juillet'!E34,'Août'!E34,'Septembre'!E34,'Octobre'!E34,'Novembre'!E34,'Décembre'!E34),"") | AC31: =IF(ISNUMBER(CHOOSE($Z$3,'Janvier'!I34,'Février'!I34,'Mars'!I34,'Avril'!I34,'Mai'!I34,'Juin'!I34,'Juillet'!I34,'Août'!I34,'Septembre'!I34,'Octobre'!I34,'Novembre'!I34,'Décembre'!I34)),CHOOSE($Z$3,'Janvier'!I34,'Février'!I34,'Mars'!I34,'Avril'!I34,'Mai'!I34,'Juin'!I34,'Juillet'!I34,'Août'!I34,'Septembre'!I34,'Octobre'!I34,'Novembre'!I34,'Décembre'!I34),"") | AD31: =IF(ISNUMBER(CHOOSE($Z$3,'Janvier'!M34,'Février'!M34,'Mars'!M34,'Avril'!M34,'Mai'!M34,'Juin'!M34,'Juillet'!M34,'Août'!M34,'Septembre'!M34,'Octobre'!M34,'Novembre'!M34,'Décembre'!M34)),CHOOSE($Z$3,'Janvier'!M34,'Février'!M34,'Mars'!M34,'Avril'!M34,'Mai'!M34,'Juin'!M34,'Juillet'!M34,'Août'!M34,'Septembre'!M34,'Octobre'!M34,'Novembre'!M34,'Décembre'!M34),"") | AE31: =IF(ISNUMBER(CHOOSE($Z$3,'Janvier'!Q34,'Février'!Q34,'Mars'!Q34,'Avril'!Q34,'Mai'!Q34,'Juin'!Q34,'Juillet'!Q34,'Août'!Q34,'Septembre'!Q34,'Octobre'!Q34,'Novembre'!Q34,'Décembre'!Q34)),CHOOSE($Z$3,'Janvier'!Q34,'Février'!Q34,'Mars'!Q34,'Avril'!Q34,'Mai'!Q34,'Juin'!Q34,'Juillet'!Q34,'Août'!Q34,'Septembre'!Q34,'Octobre'!Q34,'Novembre'!Q34,'Décembre'!Q34),"") | AF31: =IF(ISNUMBER(CHOOSE($Z$3,'Janvier'!T34,'Février'!T34,'Mars'!T34,'Avril'!T34,'Mai'!T34,'Juin'!T34,'Juillet'!T34,'Août'!T34,'Septembre'!T34,'Octobre'!T34,'Novembre'!T34,'Décembre'!T34)),CHOOSE($Z$3,'Janvier'!T34,'Février'!T34,'Mars'!T34,'Avril'!T34,'Mai'!T34,'Juin'!T34,'Juillet'!T34,'Août'!T34,'Septembre'!T34,'Octobre'!T34,'Novembre'!T34,'Décembre'!T34),"") | AG31: =IF(ISNUMBER(CHOOSE($Z$3,'Janvier'!U34,'Février'!U34,'Mars'!U34,'Avril'!U34,'Mai'!U34,'Juin'!U34,'Juillet'!U34,'Août'!U34,'Septembre'!U34,'Octobre'!U34,'Novembre'!U34,'Décembre'!U34)),CHOOSE($Z$3,'Janvier'!U34,'Février'!U34,'Mars'!U34,'Avril'!U34,'Mai'!U34,'Juin'!U34,'Juillet'!U34,'Août'!U34,'Septembre'!U34,'Octobre'!U34,'Novembre'!U34,'Décembre'!U34),"") | AH31: =IF(ISNUMBER(CHOOSE($Z$3,'Janvier'!V34,'Février'!V34,'Mars'!V34,'Avril'!V34,'Mai'!V34,'Juin'!V34,'Juillet'!V34,'Août'!V34,'Septembre'!V34,'Octobre'!V34,'Novembre'!V34,'Décembre'!V34)),CHOOSE($Z$3,'Janvier'!V34,'Février'!V34,'Mars'!V34,'Avril'!V34,'Mai'!V34,'Juin'!V34,'Juillet'!V34,'Août'!V34,'Septembre'!V34,'Octobre'!V34,'Novembre'!V34,'Décembre'!V34),"") | AI31: =IF(ISNUMBER(CHOOSE($Z$3,'Janvier'!W34,'Février'!W34,'Mars'!W34,'Avril'!W34,'Mai'!W34,'Juin'!W34,'Juillet'!W34,'Août'!W34,'Septembre'!W34,'Octobre'!W34,'Novembre'!W34,'Décembre'!W34)),CHOOSE($Z$3,'Janvier'!W34,'Février'!W34,'Mars'!W34,'Avril'!W34,'Mai'!W34,'Juin'!W34,'Juillet'!W34,'Août'!W34,'Septembre'!W34,'Octobre'!W34,'Novembre'!W34,'Décembre'!W34),"") | AJ31: =IF(Produits!$A$33="","",Produits!$D$33) | AK31: =IF(ISNUMBER(CHOOSE($Z$3,'Janvier'!X34,'Février'!X34,'Mars'!X34,'Avril'!X34,'Mai'!X34,'Juin'!X34,'Juillet'!X34,'Août'!X34,'Septembre'!X34,'Octobre'!X34,'Novembre'!X34,'Décembre'!X34)),CHOOSE($Z$3,'Janvier'!X34,'Février'!X34,'Mars'!X34,'Avril'!X34,'Mai'!X34,'Juin'!X34,'Juillet'!X34,'Août'!X34,'Septembre'!X34,'Octobre'!X34,'Novembre'!X34,'Décembre'!X34),"") | AL31: =IF(AND(ISNUMBER(AI31),ISNUMBER(AJ31)),IF(AI31<=AJ31,1,0),0) | AM31: =IF(OR(AA31="",AK31=""),-1,AK31+ROW()/1000000)
A32: =AA11 | C32: =IF(OR(AB11="",MAX(AB11,AC11,AD11,AE11)=0),"",REPT("█",MAX(1,ROUND(AB11/MAX(AB11,AC11,AD11,AE11)*6,0)))) | D32: =IF(OR(AC11="",MAX(AB11,AC11,AD11,AE11)=0),"",REPT("█",MAX(1,ROUND(AC11/MAX(AB11,AC11,AD11,AE11)*6,0)))) | E32: =IF(OR(AD11="",MAX(AB11,AC11,AD11,AE11)=0),"",REPT("█",MAX(1,ROUND(AD11/MAX(AB11,AC11,AD11,AE11)*6,0)))) | F32: =IF(OR(AE11="",MAX(AB11,AC11,AD11,AE11)=0),"",REPT("█",MAX(1,ROUND(AE11/MAX(AB11,AC11,AD11,AE11)*6,0)))) | G32: =IF(COUNT(AB11,AC11,AD11,AE11)<2,"",IF(IF(AE11<>"",AE11,IF(AD11<>"",AD11,IF(AC11<>"",AC11,IF(AB11<>"",AB11,""))))>IF(AB11<>"",AB11,IF(AC11<>"",AC11,IF(AD11<>"",AD11,AE11))),"▲",IF(IF(AE11<>"",AE11,IF(AD11<>"",AD11,IF(AC11<>"",AC11,IF(AB11<>"",AB11,""))))<IF(AB11<>"",AB11,IF(AC11<>"",AC11,IF(AD11<>"",AD11,AE11))),"▼","="))) | H32: =AI11 | I32: =AJ11 | J32: =IF(AL11=1,"À COMMANDER",IF(AA11="","","")) | AA32: =IF(Produits!$A$34="","",Produits!$A$34) | AB32: =IF(ISNUMBER(CHOOSE($Z$3,'Janvier'!E35,'Février'!E35,'Mars'!E35,'Avril'!E35,'Mai'!E35,'Juin'!E35,'Juillet'!E35,'Août'!E35,'Septembre'!E35,'Octobre'!E35,'Novembre'!E35,'Décembre'!E35)),CHOOSE($Z$3,'Janvier'!E35,'Février'!E35,'Mars'!E35,'Avril'!E35,'Mai'!E35,'Juin'!E35,'Juillet'!E35,'Août'!E35,'Septembre'!E35,'Octobre'!E35,'Novembre'!E35,'Décembre'!E35),"") | AC32: =IF(ISNUMBER(CHOOSE($Z$3,'Janvier'!I35,'Février'!I35,'Mars'!I35,'Avril'!I35,'Mai'!I35,'Juin'!I35,'Juillet'!I35,'Août'!I35,'Septembre'!I35,'Octobre'!I35,'Novembre'!I35,'Décembre'!I35)),CHOOSE($Z$3,'Janvier'!I35,'Février'!I35,'Mars'!I35,'Avril'!I35,'Mai'!I35,'Juin'!I35,'Juillet'!I35,'Août'!I35,'Septembre'!I35,'Octobre'!I35,'Novembre'!I35,'Décembre'!I35),"") | AD32: =IF(ISNUMBER(CHOOSE($Z$3,'Janvier'!M35,'Février'!M35,'Mars'!M35,'Avril'!M35,'Mai'!M35,'Juin'!M35,'Juillet'!M35,'Août'!M35,'Septembre'!M35,'Octobre'!M35,'Novembre'!M35,'Décembre'!M35)),CHOOSE($Z$3,'Janvier'!M35,'Février'!M35,'Mars'!M35,'Avril'!M35,'Mai'!M35,'Juin'!M35,'Juillet'!M35,'Août'!M35,'Septembre'!M35,'Octobre'!M35,'Novembre'!M35,'Décembre'!M35),"") | AE32: =IF(ISNUMBER(CHOOSE($Z$3,'Janvier'!Q35,'Février'!Q35,'Mars'!Q35,'Avril'!Q35,'Mai'!Q35,'Juin'!Q35,'Juillet'!Q35,'Août'!Q35,'Septembre'!Q35,'Octobre'!Q35,'Novembre'!Q35,'Décembre'!Q35)),CHOOSE($Z$3,'Janvier'!Q35,'Février'!Q35,'Mars'!Q35,'Avril'!Q35,'Mai'!Q35,'Juin'!Q35,'Juillet'!Q35,'Août'!Q35,'Septembre'!Q35,'Octobre'!Q35,'Novembre'!Q35,'Décembre'!Q35),"") | AF32: =IF(ISNUMBER(CHOOSE($Z$3,'Janvier'!T35,'Février'!T35,'Mars'!T35,'Avril'!T35,'Mai'!T35,'Juin'!T35,'Juillet'!T35,'Août'!T35,'Septembre'!T35,'Octobre'!T35,'Novembre'!T35,'Décembre'!T35)),CHOOSE($Z$3,'Janvier'!T35,'Février'!T35,'Mars'!T35,'Avril'!T35,'Mai'!T35,'Juin'!T35,'Juillet'!T35,'Août'!T35,'Septembre'!T35,'Octobre'!T35,'Novembre'!T35,'Décembre'!T35),"") | AG32: =IF(ISNUMBER(CHOOSE($Z$3,'Janvier'!U35,'Février'!U35,'Mars'!U35,'Avril'!U35,'Mai'!U35,'Juin'!U35,'Juillet'!U35,'Août'!U35,'Septembre'!U35,'Octobre'!U35,'Novembre'!U35,'Décembre'!U35)),CHOOSE($Z$3,'Janvier'!U35,'Février'!U35,'Mars'!U35,'Avril'!U35,'Mai'!U35,'Juin'!U35,'Juillet'!U35,'Août'!U35,'Septembre'!U35,'Octobre'!U35,'Novembre'!U35,'Décembre'!U35),"") | AH32: =IF(ISNUMBER(CHOOSE($Z$3,'Janvier'!V35,'Février'!V35,'Mars'!V35,'Avril'!V35,'Mai'!V35,'Juin'!V35,'Juillet'!V35,'Août'!V35,'Septembre'!V35,'Octobre'!V35,'Novembre'!V35,'Décembre'!V35)),CHOOSE($Z$3,'Janvier'!V35,'Février'!V35,'Mars'!V35,'Avril'!V35,'Mai'!V35,'Juin'!V35,'Juillet'!V35,'Août'!V35,'Septembre'!V35,'Octobre'!V35,'Novembre'!V35,'Décembre'!V35),"") | AI32: =IF(ISNUMBER(CHOOSE($Z$3,'Janvier'!W35,'Février'!W35,'Mars'!W35,'Avril'!W35,'Mai'!W35,'Juin'!W35,'Juillet'!W35,'Août'!W35,'Septembre'!W35,'Octobre'!W35,'Novembre'!W35,'Décembre'!W35)),CHOOSE($Z$3,'Janvier'!W35,'Février'!W35,'Mars'!W35,'Avril'!W35,'Mai'!W35,'Juin'!W35,'Juillet'!W35,'Août'!W35,'Septembre'!W35,'Octobre'!W35,'Novembre'!W35,'Décembre'!W35),"") | AJ32: =IF(Produits!$A$34="","",Produits!$D$34) | AK32: =IF(ISNUMBER(CHOOSE($Z$3,'Janvier'!X35,'Février'!X35,'Mars'!X35,'Avril'!X35,'Mai'!X35,'Juin'!X35,'Juillet'!X35,'Août'!X35,'Septembre'!X35,'Octobre'!X35,'Novembre'!X35,'Décembre'!X35)),CHOOSE($Z$3,'Janvier'!X35,'Février'!X35,'Mars'!X35,'Avril'!X35,'Mai'!X35,'Juin'!X35,'Juillet'!X35,'Août'!X35,'Septembre'!X35,'Octobre'!X35,'Novembre'!X35,'Décembre'!X35),"") | AL32: =IF(AND(ISNUMBER(AI32),ISNUMBER(AJ32)),IF(AI32<=AJ32,1,0),0) | AM32: =IF(OR(AA32="",AK32=""),-1,AK32+ROW()/1000000)
A33: =AA12 | C33: =IF(OR(AB12="",MAX(AB12,AC12,AD12,AE12)=0),"",REPT("█",MAX(1,ROUND(AB12/MAX(AB12,AC12,AD12,AE12)*6,0)))) | D33: =IF(OR(AC12="",MAX(AB12,AC12,AD12,AE12)=0),"",REPT("█",MAX(1,ROUND(AC12/MAX(AB12,AC12,AD12,AE12)*6,0)))) | E33: =IF(OR(AD12="",MAX(AB12,AC12,AD12,AE12)=0),"",REPT("█",MAX(1,ROUND(AD12/MAX(AB12,AC12,AD12,AE12)*6,0)))) | F33: =IF(OR(AE12="",MAX(AB12,AC12,AD12,AE12)=0),"",REPT("█",MAX(1,ROUND(AE12/MAX(AB12,AC12,AD12,AE12)*6,0)))) | G33: =IF(COUNT(AB12,AC12,AD12,AE12)<2,"",IF(IF(AE12<>"",AE12,IF(AD12<>"",AD12,IF(AC12<>"",AC12,IF(AB12<>"",AB12,""))))>IF(AB12<>"",AB12,IF(AC12<>"",AC12,IF(AD12<>"",AD12,AE12))),"▲",IF(IF(AE12<>"",AE12,IF(AD12<>"",AD12,IF(AC12<>"",AC12,IF(AB12<>"",AB12,""))))<IF(AB12<>"",AB12,IF(AC12<>"",AC12,IF(AD12<>"",AD12,AE12))),"▼","="))) | H33: =AI12 | I33: =AJ12 | J33: =IF(AL12=1,"À COMMANDER",IF(AA12="","","")) | AA33: =IF(Produits!$A$35="","",Produits!$A$35) | AB33: =IF(ISNUMBER(CHOOSE($Z$3,'Janvier'!E36,'Février'!E36,'Mars'!E36,'Avril'!E36,'Mai'!E36,'Juin'!E36,'Juillet'!E36,'Août'!E36,'Septembre'!E36,'Octobre'!E36,'Novembre'!E36,'Décembre'!E36)),CHOOSE($Z$3,'Janvier'!E36,'Février'!E36,'Mars'!E36,'Avril'!E36,'Mai'!E36,'Juin'!E36,'Juillet'!E36,'Août'!E36,'Septembre'!E36,'Octobre'!E36,'Novembre'!E36,'Décembre'!E36),"") | AC33: =IF(ISNUMBER(CHOOSE($Z$3,'Janvier'!I36,'Février'!I36,'Mars'!I36,'Avril'!I36,'Mai'!I36,'Juin'!I36,'Juillet'!I36,'Août'!I36,'Septembre'!I36,'Octobre'!I36,'Novembre'!I36,'Décembre'!I36)),CHOOSE($Z$3,'Janvier'!I36,'Février'!I36,'Mars'!I36,'Avril'!I36,'Mai'!I36,'Juin'!I36,'Juillet'!I36,'Août'!I36,'Septembre'!I36,'Octobre'!I36,'Novembre'!I36,'Décembre'!I36),"") | AD33: =IF(ISNUMBER(CHOOSE($Z$3,'Janvier'!M36,'Février'!M36,'Mars'!M36,'Avril'!M36,'Mai'!M36,'Juin'!M36,'Juillet'!M36,'Août'!M36,'Septembre'!M36,'Octobre'!M36,'Novembre'!M36,'Décembre'!M36)),CHOOSE($Z$3,'Janvier'!M36,'Février'!M36,'Mars'!M36,'Avril'!M36,'Mai'!M36,'Juin'!M36,'Juillet'!M36,'Août'!M36,'Septembre'!M36,'Octobre'!M36,'Novembre'!M36,'Décembre'!M36),"") | AE33: =IF(ISNUMBER(CHOOSE($Z$3,'Janvier'!Q36,'Février'!Q36,'Mars'!Q36,'Avril'!Q36,'Mai'!Q36,'Juin'!Q36,'Juillet'!Q36,'Août'!Q36,'Septembre'!Q36,'Octobre'!Q36,'Novembre'!Q36,'Décembre'!Q36)),CHOOSE($Z$3,'Janvier'!Q36,'Février'!Q36,'Mars'!Q36,'Avril'!Q36,'Mai'!Q36,'Juin'!Q36,'Juillet'!Q36,'Août'!Q36,'Septembre'!Q36,'Octobre'!Q36,'Novembre'!Q36,'Décembre'!Q36),"") | AF33: =IF(ISNUMBER(CHOOSE($Z$3,'Janvier'!T36,'Février'!T36,'Mars'!T36,'Avril'!T36,'Mai'!T36,'Juin'!T36,'Juillet'!T36,'Août'!T36,'Septembre'!T36,'Octobre'!T36,'Novembre'!T36,'Décembre'!T36)),CHOOSE($Z$3,'Janvier'!T36,'Février'!T36,'Mars'!T36,'Avril'!T36,'Mai'!T36,'Juin'!T36,'Juillet'!T36,'Août'!T36,'Septembre'!T36,'Octobre'!T36,'Novembre'!T36,'Décembre'!T36),"") | AG33: =IF(ISNUMBER(CHOOSE($Z$3,'Janvier'!U36,'Février'!U36,'Mars'!U36,'Avril'!U36,'Mai'!U36,'Juin'!U36,'Juillet'!U36,'Août'!U36,'Septembre'!U36,'Octobre'!U36,'Novembre'!U36,'Décembre'!U36)),CHOOSE($Z$3,'Janvier'!U36,'Février'!U36,'Mars'!U36,'Avril'!U36,'Mai'!U36,'Juin'!U36,'Juillet'!U36,'Août'!U36,'Septembre'!U36,'Octobre'!U36,'Novembre'!U36,'Décembre'!U36),"") | AH33: =IF(ISNUMBER(CHOOSE($Z$3,'Janvier'!V36,'Février'!V36,'Mars'!V36,'Avril'!V36,'Mai'!V36,'Juin'!V36,'Juillet'!V36,'Août'!V36,'Septembre'!V36,'Octobre'!V36,'Novembre'!V36,'Décembre'!V36)),CHOOSE($Z$3,'Janvier'!V36,'Février'!V36,'Mars'!V36,'Avril'!V36,'Mai'!V36,'Juin'!V36,'Juillet'!V36,'Août'!V36,'Septembre'!V36,'Octobre'!V36,'Novembre'!V36,'Décembre'!V36),"") | AI33: =IF(ISNUMBER(CHOOSE($Z$3,'Janvier'!W36,'Février'!W36,'Mars'!W36,'Avril'!W36,'Mai'!W36,'Juin'!W36,'Juillet'!W36,'Août'!W36,'Septembre'!W36,'Octobre'!W36,'Novembre'!W36,'Décembre'!W36)),CHOOSE($Z$3,'Janvier'!W36,'Février'!W36,'Mars'!W36,'Avril'!W36,'Mai'!W36,'Juin'!W36,'Juillet'!W36,'Août'!W36,'Septembre'!W36,'Octobre'!W36,'Novembre'!W36,'Décembre'!W36),"") | AJ33: =IF(Produits!$A$35="","",Produits!$D$35) | AK33: =IF(ISNUMBER(CHOOSE($Z$3,'Janvier'!X36,'Février'!X36,'Mars'!X36,'Avril'!X36,'Mai'!X36,'Juin'!X36,'Juillet'!X36,'Août'!X36,'Septembre'!X36,'Octobre'!X36,'Novembre'!X36,'Décembre'!X36)),CHOOSE($Z$3,'Janvier'!X36,'Février'!X36,'Mars'!X36,'Avril'!X36,'Mai'!X36,'Juin'!X36,'Juillet'!X36,'Août'!X36,'Septembre'!X36,'Octobre'!X36,'Novembre'!X36,'Décembre'!X36),"") | AL33: =IF(AND(ISNUMBER(AI33),ISNUMBER(AJ33)),IF(AI33<=AJ33,1,0),0) | AM33: =IF(OR(AA33="",AK33=""),-1,AK33+ROW()/1000000)
A34: =AA13 | C34: =IF(OR(AB13="",MAX(AB13,AC13,AD13,AE13)=0),"",REPT("█",MAX(1,ROUND(AB13/MAX(AB13,AC13,AD13,AE13)*6,0)))) | D34: =IF(OR(AC13="",MAX(AB13,AC13,AD13,AE13)=0),"",REPT("█",MAX(1,ROUND(AC13/MAX(AB13,AC13,AD13,AE13)*6,0)))) | E34: =IF(OR(AD13="",MAX(AB13,AC13,AD13,AE13)=0),"",REPT("█",MAX(1,ROUND(AD13/MAX(AB13,AC13,AD13,AE13)*6,0)))) | F34: =IF(OR(AE13="",MAX(AB13,AC13,AD13,AE13)=0),"",REPT("█",MAX(1,ROUND(AE13/MAX(AB13,AC13,AD13,AE13)*6,0)))) | G34: =IF(COUNT(AB13,AC13,AD13,AE13)<2,"",IF(IF(AE13<>"",AE13,IF(AD13<>"",AD13,IF(AC13<>"",AC13,IF(AB13<>"",AB13,""))))>IF(AB13<>"",AB13,IF(AC13<>"",AC13,IF(AD13<>"",AD13,AE13))),"▲",IF(IF(AE13<>"",AE13,IF(AD13<>"",AD13,IF(AC13<>"",AC13,IF(AB13<>"",AB13,""))))<IF(AB13<>"",AB13,IF(AC13<>"",AC13,IF(AD13<>"",AD13,AE13))),"▼","="))) | H34: =AI13 | I34: =AJ13 | J34: =IF(AL13=1,"À COMMANDER",IF(AA13="","","")) | AA34: =IF(Produits!$A$36="","",Produits!$A$36) | AB34: =IF(ISNUMBER(CHOOSE($Z$3,'Janvier'!E37,'Février'!E37,'Mars'!E37,'Avril'!E37,'Mai'!E37,'Juin'!E37,'Juillet'!E37,'Août'!E37,'Septembre'!E37,'Octobre'!E37,'Novembre'!E37,'Décembre'!E37)),CHOOSE($Z$3,'Janvier'!E37,'Février'!E37,'Mars'!E37,'Avril'!E37,'Mai'!E37,'Juin'!E37,'Juillet'!E37,'Août'!E37,'Septembre'!E37,'Octobre'!E37,'Novembre'!E37,'Décembre'!E37),"") | AC34: =IF(ISNUMBER(CHOOSE($Z$3,'Janvier'!I37,'Février'!I37,'Mars'!I37,'Avril'!I37,'Mai'!I37,'Juin'!I37,'Juillet'!I37,'Août'!I37,'Septembre'!I37,'Octobre'!I37,'Novembre'!I37,'Décembre'!I37)),CHOOSE($Z$3,'Janvier'!I37,'Février'!I37,'Mars'!I37,'Avril'!I37,'Mai'!I37,'Juin'!I37,'Juillet'!I37,'Août'!I37,'Septembre'!I37,'Octobre'!I37,'Novembre'!I37,'Décembre'!I37),"") | AD34: =IF(ISNUMBER(CHOOSE($Z$3,'Janvier'!M37,'Février'!M37,'Mars'!M37,'Avril'!M37,'Mai'!M37,'Juin'!M37,'Juillet'!M37,'Août'!M37,'Septembre'!M37,'Octobre'!M37,'Novembre'!M37,'Décembre'!M37)),CHOOSE($Z$3,'Janvier'!M37,'Février'!M37,'Mars'!M37,'Avril'!M37,'Mai'!M37,'Juin'!M37,'Juillet'!M37,'Août'!M37,'Septembre'!M37,'Octobre'!M37,'Novembre'!M37,'Décembre'!M37),"") | AE34: =IF(ISNUMBER(CHOOSE($Z$3,'Janvier'!Q37,'Février'!Q37,'Mars'!Q37,'Avril'!Q37,'Mai'!Q37,'Juin'!Q37,'Juillet'!Q37,'Août'!Q37,'Septembre'!Q37,'Octobre'!Q37,'Novembre'!Q37,'Décembre'!Q37)),CHOOSE($Z$3,'Janvier'!Q37,'Février'!Q37,'Mars'!Q37,'Avril'!Q37,'Mai'!Q37,'Juin'!Q37,'Juillet'!Q37,'Août'!Q37,'Septembre'!Q37,'Octobre'!Q37,'Novembre'!Q37,'Décembre'!Q37),"") | AF34: =IF(ISNUMBER(CHOOSE($Z$3,'Janvier'!T37,'Février'!T37,'Mars'!T37,'Avril'!T37,'Mai'!T37,'Juin'!T37,'Juillet'!T37,'Août'!T37,'Septembre'!T37,'Octobre'!T37,'Novembre'!T37,'Décembre'!T37)),CHOOSE($Z$3,'Janvier'!T37,'Février'!T37,'Mars'!T37,'Avril'!T37,'Mai'!T37,'Juin'!T37,'Juillet'!T37,'Août'!T37,'Septembre'!T37,'Octobre'!T37,'Novembre'!T37,'Décembre'!T37),"") | AG34: =IF(ISNUMBER(CHOOSE($Z$3,'Janvier'!U37,'Février'!U37,'Mars'!U37,'Avril'!U37,'Mai'!U37,'Juin'!U37,'Juillet'!U37,'Août'!U37,'Septembre'!U37,'Octobre'!U37,'Novembre'!U37,'Décembre'!U37)),CHOOSE($Z$3,'Janvier'!U37,'Février'!U37,'Mars'!U37,'Avril'!U37,'Mai'!U37,'Juin'!U37,'Juillet'!U37,'Août'!U37,'Septembre'!U37,'Octobre'!U37,'Novembre'!U37,'Décembre'!U37),"") | AH34: =IF(ISNUMBER(CHOOSE($Z$3,'Janvier'!V37,'Février'!V37,'Mars'!V37,'Avril'!V37,'Mai'!V37,'Juin'!V37,'Juillet'!V37,'Août'!V37,'Septembre'!V37,'Octobre'!V37,'Novembre'!V37,'Décembre'!V37)),CHOOSE($Z$3,'Janvier'!V37,'Février'!V37,'Mars'!V37,'Avril'!V37,'Mai'!V37,'Juin'!V37,'Juillet'!V37,'Août'!V37,'Septembre'!V37,'Octobre'!V37,'Novembre'!V37,'Décembre'!V37),"") | AI34: =IF(ISNUMBER(CHOOSE($Z$3,'Janvier'!W37,'Février'!W37,'Mars'!W37,'Avril'!W37,'Mai'!W37,'Juin'!W37,'Juillet'!W37,'Août'!W37,'Septembre'!W37,'Octobre'!W37,'Novembre'!W37,'Décembre'!W37)),CHOOSE($Z$3,'Janvier'!W37,'Février'!W37,'Mars'!W37,'Avril'!W37,'Mai'!W37,'Juin'!W37,'Juillet'!W37,'Août'!W37,'Septembre'!W37,'Octobre'!W37,'Novembre'!W37,'Décembre'!W37),"") | AJ34: =IF(Produits!$A$36="","",Produits!$D$36) | AK34: =IF(ISNUMBER(CHOOSE($Z$3,'Janvier'!X37,'Février'!X37,'Mars'!X37,'Avril'!X37,'Mai'!X37,'Juin'!X37,'Juillet'!X37,'Août'!X37,'Septembre'!X37,'Octobre'!X37,'Novembre'!X37,'Décembre'!X37)),CHOOSE($Z$3,'Janvier'!X37,'Février'!X37,'Mars'!X37,'Avril'!X37,'Mai'!X37,'Juin'!X37,'Juillet'!X37,'Août'!X37,'Septembre'!X37,'Octobre'!X37,'Novembre'!X37,'Décembre'!X37),"") | AL34: =IF(AND(ISNUMBER(AI34),ISNUMBER(AJ34)),IF(AI34<=AJ34,1,0),0) | AM34: =IF(OR(AA34="",AK34=""),-1,AK34+ROW()/1000000)
A35: =AA14 | C35: =IF(OR(AB14="",MAX(AB14,AC14,AD14,AE14)=0),"",REPT("█",MAX(1,ROUND(AB14/MAX(AB14,AC14,AD14,AE14)*6,0)))) | D35: =IF(OR(AC14="",MAX(AB14,AC14,AD14,AE14)=0),"",REPT("█",MAX(1,ROUND(AC14/MAX(AB14,AC14,AD14,AE14)*6,0)))) | E35: =IF(OR(AD14="",MAX(AB14,AC14,AD14,AE14)=0),"",REPT("█",MAX(1,ROUND(AD14/MAX(AB14,AC14,AD14,AE14)*6,0)))) | F35: =IF(OR(AE14="",MAX(AB14,AC14,AD14,AE14)=0),"",REPT("█",MAX(1,ROUND(AE14/MAX(AB14,AC14,AD14,AE14)*6,0)))) | G35: =IF(COUNT(AB14,AC14,AD14,AE14)<2,"",IF(IF(AE14<>"",AE14,IF(AD14<>"",AD14,IF(AC14<>"",AC14,IF(AB14<>"",AB14,""))))>IF(AB14<>"",AB14,IF(AC14<>"",AC14,IF(AD14<>"",AD14,AE14))),"▲",IF(IF(AE14<>"",AE14,IF(AD14<>"",AD14,IF(AC14<>"",AC14,IF(AB14<>"",AB14,""))))<IF(AB14<>"",AB14,IF(AC14<>"",AC14,IF(AD14<>"",AD14,AE14))),"▼","="))) | H35: =AI14 | I35: =AJ14 | J35: =IF(AL14=1,"À COMMANDER",IF(AA14="","","")) | AA35: =IF(Produits!$A$38="","",Produits!$A$38) | AB35: =IF(ISNUMBER(CHOOSE($Z$3,'Janvier'!E39,'Février'!E39,'Mars'!E39,'Avril'!E39,'Mai'!E39,'Juin'!E39,'Juillet'!E39,'Août'!E39,'Septembre'!E39,'Octobre'!E39,'Novembre'!E39,'Décembre'!E39)),CHOOSE($Z$3,'Janvier'!E39,'Février'!E39,'Mars'!E39,'Avril'!E39,'Mai'!E39,'Juin'!E39,'Juillet'!E39,'Août'!E39,'Septembre'!E39,'Octobre'!E39,'Novembre'!E39,'Décembre'!E39),"") | AC35: =IF(ISNUMBER(CHOOSE($Z$3,'Janvier'!I39,'Février'!I39,'Mars'!I39,'Avril'!I39,'Mai'!I39,'Juin'!I39,'Juillet'!I39,'Août'!I39,'Septembre'!I39,'Octobre'!I39,'Novembre'!I39,'Décembre'!I39)),CHOOSE($Z$3,'Janvier'!I39,'Février'!I39,'Mars'!I39,'Avril'!I39,'Mai'!I39,'Juin'!I39,'Juillet'!I39,'Août'!I39,'Septembre'!I39,'Octobre'!I39,'Novembre'!I39,'Décembre'!I39),"") | AD35: =IF(ISNUMBER(CHOOSE($Z$3,'Janvier'!M39,'Février'!M39,'Mars'!M39,'Avril'!M39,'Mai'!M39,'Juin'!M39,'Juillet'!M39,'Août'!M39,'Septembre'!M39,'Octobre'!M39,'Novembre'!M39,'Décembre'!M39)),CHOOSE($Z$3,'Janvier'!M39,'Février'!M39,'Mars'!M39,'Avril'!M39,'Mai'!M39,'Juin'!M39,'Juillet'!M39,'Août'!M39,'Septembre'!M39,'Octobre'!M39,'Novembre'!M39,'Décembre'!M39),"") | AE35: =IF(ISNUMBER(CHOOSE($Z$3,'Janvier'!Q39,'Février'!Q39,'Mars'!Q39,'Avril'!Q39,'Mai'!Q39,'Juin'!Q39,'Juillet'!Q39,'Août'!Q39,'Septembre'!Q39,'Octobre'!Q39,'Novembre'!Q39,'Décembre'!Q39)),CHOOSE($Z$3,'Janvier'!Q39,'Février'!Q39,'Mars'!Q39,'Avril'!Q39,'Mai'!Q39,'Juin'!Q39,'Juillet'!Q39,'Août'!Q39,'Septembre'!Q39,'Octobre'!Q39,'Novembre'!Q39,'Décembre'!Q39),"") | AF35: =IF(ISNUMBER(CHOOSE($Z$3,'Janvier'!T39,'Février'!T39,'Mars'!T39,'Avril'!T39,'Mai'!T39,'Juin'!T39,'Juillet'!T39,'Août'!T39,'Septembre'!T39,'Octobre'!T39,'Novembre'!T39,'Décembre'!T39)),CHOOSE($Z$3,'Janvier'!T39,'Février'!T39,'Mars'!T39,'Avril'!T39,'Mai'!T39,'Juin'!T39,'Juillet'!T39,'Août'!T39,'Septembre'!T39,'Octobre'!T39,'Novembre'!T39,'Décembre'!T39),"") | AG35: =IF(ISNUMBER(CHOOSE($Z$3,'Janvier'!U39,'Février'!U39,'Mars'!U39,'Avril'!U39,'Mai'!U39,'Juin'!U39,'Juillet'!U39,'Août'!U39,'Septembre'!U39,'Octobre'!U39,'Novembre'!U39,'Décembre'!U39)),CHOOSE($Z$3,'Janvier'!U39,'Février'!U39,'Mars'!U39,'Avril'!U39,'Mai'!U39,'Juin'!U39,'Juillet'!U39,'Août'!U39,'Septembre'!U39,'Octobre'!U39,'Novembre'!U39,'Décembre'!U39),"") | AH35: =IF(ISNUMBER(CHOOSE($Z$3,'Janvier'!V39,'Février'!V39,'Mars'!V39,'Avril'!V39,'Mai'!V39,'Juin'!V39,'Juillet'!V39,'Août'!V39,'Septembre'!V39,'Octobre'!V39,'Novembre'!V39,'Décembre'!V39)),CHOOSE($Z$3,'Janvier'!V39,'Février'!V39,'Mars'!V39,'Avril'!V39,'Mai'!V39,'Juin'!V39,'Juillet'!V39,'Août'!V39,'Septembre'!V39,'Octobre'!V39,'Novembre'!V39,'Décembre'!V39),"") | AI35: =IF(ISNUMBER(CHOOSE($Z$3,'Janvier'!W39,'Février'!W39,'Mars'!W39,'Avril'!W39,'Mai'!W39,'Juin'!W39,'Juillet'!W39,'Août'!W39,'Septembre'!W39,'Octobre'!W39,'Novembre'!W39,'Décembre'!W39)),CHOOSE($Z$3,'Janvier'!W39,'Février'!W39,'Mars'!W39,'Avril'!W39,'Mai'!W39,'Juin'!W39,'Juillet'!W39,'Août'!W39,'Septembre'!W39,'Octobre'!W39,'Novembre'!W39,'Décembre'!W39),"") | AJ35: =IF(Produits!$A$38="","",Produits!$D$38) | AK35: =IF(ISNUMBER(CHOOSE($Z$3,'Janvier'!X39,'Février'!X39,'Mars'!X39,'Avril'!X39,'Mai'!X39,'Juin'!X39,'Juillet'!X39,'Août'!X39,'Septembre'!X39,'Octobre'!X39,'Novembre'!X39,'Décembre'!X39)),CHOOSE($Z$3,'Janvier'!X39,'Février'!X39,'Mars'!X39,'Avril'!X39,'Mai'!X39,'Juin'!X39,'Juillet'!X39,'Août'!X39,'Septembre'!X39,'Octobre'!X39,'Novembre'!X39,'Décembre'!X39),"") | AL35: =IF(AND(ISNUMBER(AI35),ISNUMBER(AJ35)),IF(AI35<=AJ35,1,0),0) | AM35: =IF(OR(AA35="",AK35=""),-1,AK35+ROW()/1000000)
A36: =AA15 | C36: =IF(OR(AB15="",MAX(AB15,AC15,AD15,AE15)=0),"",REPT("█",MAX(1,ROUND(AB15/MAX(AB15,AC15,AD15,AE15)*6,0)))) | D36: =IF(OR(AC15="",MAX(AB15,AC15,AD15,AE15)=0),"",REPT("█",MAX(1,ROUND(AC15/MAX(AB15,AC15,AD15,AE15)*6,0)))) | E36: =IF(OR(AD15="",MAX(AB15,AC15,AD15,AE15)=0),"",REPT("█",MAX(1,ROUND(AD15/MAX(AB15,AC15,AD15,AE15)*6,0)))) | F36: =IF(OR(AE15="",MAX(AB15,AC15,AD15,AE15)=0),"",REPT("█",MAX(1,ROUND(AE15/MAX(AB15,AC15,AD15,AE15)*6,0)))) | G36: =IF(COUNT(AB15,AC15,AD15,AE15)<2,"",IF(IF(AE15<>"",AE15,IF(AD15<>"",AD15,IF(AC15<>"",AC15,IF(AB15<>"",AB15,""))))>IF(AB15<>"",AB15,IF(AC15<>"",AC15,IF(AD15<>"",AD15,AE15))),"▲",IF(IF(AE15<>"",AE15,IF(AD15<>"",AD15,IF(AC15<>"",AC15,IF(AB15<>"",AB15,""))))<IF(AB15<>"",AB15,IF(AC15<>"",AC15,IF(AD15<>"",AD15,AE15))),"▼","="))) | H36: =AI15 | I36: =AJ15 | J36: =IF(AL15=1,"À COMMANDER",IF(AA15="","","")) | AA36: =IF(Produits!$A$39="","",Produits!$A$39) | AB36: =IF(ISNUMBER(CHOOSE($Z$3,'Janvier'!E40,'Février'!E40,'Mars'!E40,'Avril'!E40,'Mai'!E40,'Juin'!E40,'Juillet'!E40,'Août'!E40,'Septembre'!E40,'Octobre'!E40,'Novembre'!E40,'Décembre'!E40)),CHOOSE($Z$3,'Janvier'!E40,'Février'!E40,'Mars'!E40,'Avril'!E40,'Mai'!E40,'Juin'!E40,'Juillet'!E40,'Août'!E40,'Septembre'!E40,'Octobre'!E40,'Novembre'!E40,'Décembre'!E40),"") | AC36: =IF(ISNUMBER(CHOOSE($Z$3,'Janvier'!I40,'Février'!I40,'Mars'!I40,'Avril'!I40,'Mai'!I40,'Juin'!I40,'Juillet'!I40,'Août'!I40,'Septembre'!I40,'Octobre'!I40,'Novembre'!I40,'Décembre'!I40)),CHOOSE($Z$3,'Janvier'!I40,'Février'!I40,'Mars'!I40,'Avril'!I40,'Mai'!I40,'Juin'!I40,'Juillet'!I40,'Août'!I40,'Septembre'!I40,'Octobre'!I40,'Novembre'!I40,'Décembre'!I40),"") | AD36: =IF(ISNUMBER(CHOOSE($Z$3,'Janvier'!M40,'Février'!M40,'Mars'!M40,'Avril'!M40,'Mai'!M40,'Juin'!M40,'Juillet'!M40,'Août'!M40,'Septembre'!M40,'Octobre'!M40,'Novembre'!M40,'Décembre'!M40)),CHOOSE($Z$3,'Janvier'!M40,'Février'!M40,'Mars'!M40,'Avril'!M40,'Mai'!M40,'Juin'!M40,'Juillet'!M40,'Août'!M40,'Septembre'!M40,'Octobre'!M40,'Novembre'!M40,'Décembre'!M40),"") | AE36: =IF(ISNUMBER(CHOOSE($Z$3,'Janvier'!Q40,'Février'!Q40,'Mars'!Q40,'Avril'!Q40,'Mai'!Q40,'Juin'!Q40,'Juillet'!Q40,'Août'!Q40,'Septembre'!Q40,'Octobre'!Q40,'Novembre'!Q40,'Décembre'!Q40)),CHOOSE($Z$3,'Janvier'!Q40,'Février'!Q40,'Mars'!Q40,'Avril'!Q40,'Mai'!Q40,'Juin'!Q40,'Juillet'!Q40,'Août'!Q40,'Septembre'!Q40,'Octobre'!Q40,'Novembre'!Q40,'Décembre'!Q40),"") | AF36: =IF(ISNUMBER(CHOOSE($Z$3,'Janvier'!T40,'Février'!T40,'Mars'!T40,'Avril'!T40,'Mai'!T40,'Juin'!T40,'Juillet'!T40,'Août'!T40,'Septembre'!T40,'Octobre'!T40,'Novembre'!T40,'Décembre'!T40)),CHOOSE($Z$3,'Janvier'!T40,'Février'!T40,'Mars'!T40,'Avril'!T40,'Mai'!T40,'Juin'!T40,'Juillet'!T40,'Août'!T40,'Septembre'!T40,'Octobre'!T40,'Novembre'!T40,'Décembre'!T40),"") | AG36: =IF(ISNUMBER(CHOOSE($Z$3,'Janvier'!U40,'Février'!U40,'Mars'!U40,'Avril'!U40,'Mai'!U40,'Juin'!U40,'Juillet'!U40,'Août'!U40,'Septembre'!U40,'Octobre'!U40,'Novembre'!U40,'Décembre'!U40)),CHOOSE($Z$3,'Janvier'!U40,'Février'!U40,'Mars'!U40,'Avril'!U40,'Mai'!U40,'Juin'!U40,'Juillet'!U40,'Août'!U40,'Septembre'!U40,'Octobre'!U40,'Novembre'!U40,'Décembre'!U40),"") | AH36: =IF(ISNUMBER(CHOOSE($Z$3,'Janvier'!V40,'Février'!V40,'Mars'!V40,'Avril'!V40,'Mai'!V40,'Juin'!V40,'Juillet'!V40,'Août'!V40,'Septembre'!V40,'Octobre'!V40,'Novembre'!V40,'Décembre'!V40)),CHOOSE($Z$3,'Janvier'!V40,'Février'!V40,'Mars'!V40,'Avril'!V40,'Mai'!V40,'Juin'!V40,'Juillet'!V40,'Août'!V40,'Septembre'!V40,'Octobre'!V40,'Novembre'!V40,'Décembre'!V40),"") | AI36: =IF(ISNUMBER(CHOOSE($Z$3,'Janvier'!W40,'Février'!W40,'Mars'!W40,'Avril'!W40,'Mai'!W40,'Juin'!W40,'Juillet'!W40,'Août'!W40,'Septembre'!W40,'Octobre'!W40,'Novembre'!W40,'Décembre'!W40)),CHOOSE($Z$3,'Janvier'!W40,'Février'!W40,'Mars'!W40,'Avril'!W40,'Mai'!W40,'Juin'!W40,'Juillet'!W40,'Août'!W40,'Septembre'!W40,'Octobre'!W40,'Novembre'!W40,'Décembre'!W40),"") | AJ36: =IF(Produits!$A$39="","",Produits!$D$39) | AK36: =IF(ISNUMBER(CHOOSE($Z$3,'Janvier'!X40,'Février'!X40,'Mars'!X40,'Avril'!X40,'Mai'!X40,'Juin'!X40,'Juillet'!X40,'Août'!X40,'Septembre'!X40,'Octobre'!X40,'Novembre'!X40,'Décembre'!X40)),CHOOSE($Z$3,'Janvier'!X40,'Février'!X40,'Mars'!X40,'Avril'!X40,'Mai'!X40,'Juin'!X40,'Juillet'!X40,'Août'!X40,'Septembre'!X40,'Octobre'!X40,'Novembre'!X40,'Décembre'!X40),"") | AL36: =IF(AND(ISNUMBER(AI36),ISNUMBER(AJ36)),IF(AI36<=AJ36,1,0),0) | AM36: =IF(OR(AA36="",AK36=""),-1,AK36+ROW()/1000000)
A37: =AA16 | C37: =IF(OR(AB16="",MAX(AB16,AC16,AD16,AE16)=0),"",REPT("█",MAX(1,ROUND(AB16/MAX(AB16,AC16,AD16,AE16)*6,0)))) | D37: =IF(OR(AC16="",MAX(AB16,AC16,AD16,AE16)=0),"",REPT("█",MAX(1,ROUND(AC16/MAX(AB16,AC16,AD16,AE16)*6,0)))) | E37: =IF(OR(AD16="",MAX(AB16,AC16,AD16,AE16)=0),"",REPT("█",MAX(1,ROUND(AD16/MAX(AB16,AC16,AD16,AE16)*6,0)))) | F37: =IF(OR(AE16="",MAX(AB16,AC16,AD16,AE16)=0),"",REPT("█",MAX(1,ROUND(AE16/MAX(AB16,AC16,AD16,AE16)*6,0)))) | G37: =IF(COUNT(AB16,AC16,AD16,AE16)<2,"",IF(IF(AE16<>"",AE16,IF(AD16<>"",AD16,IF(AC16<>"",AC16,IF(AB16<>"",AB16,""))))>IF(AB16<>"",AB16,IF(AC16<>"",AC16,IF(AD16<>"",AD16,AE16))),"▲",IF(IF(AE16<>"",AE16,IF(AD16<>"",AD16,IF(AC16<>"",AC16,IF(AB16<>"",AB16,""))))<IF(AB16<>"",AB16,IF(AC16<>"",AC16,IF(AD16<>"",AD16,AE16))),"▼","="))) | H37: =AI16 | I37: =AJ16 | J37: =IF(AL16=1,"À COMMANDER",IF(AA16="","","")) | AA37: =IF(Produits!$A$40="","",Produits!$A$40) | AB37: =IF(ISNUMBER(CHOOSE($Z$3,'Janvier'!E41,'Février'!E41,'Mars'!E41,'Avril'!E41,'Mai'!E41,'Juin'!E41,'Juillet'!E41,'Août'!E41,'Septembre'!E41,'Octobre'!E41,'Novembre'!E41,'Décembre'!E41)),CHOOSE($Z$3,'Janvier'!E41,'Février'!E41,'Mars'!E41,'Avril'!E41,'Mai'!E41,'Juin'!E41,'Juillet'!E41,'Août'!E41,'Septembre'!E41,'Octobre'!E41,'Novembre'!E41,'Décembre'!E41),"") | AC37: =IF(ISNUMBER(CHOOSE($Z$3,'Janvier'!I41,'Février'!I41,'Mars'!I41,'Avril'!I41,'Mai'!I41,'Juin'!I41,'Juillet'!I41,'Août'!I41,'Septembre'!I41,'Octobre'!I41,'Novembre'!I41,'Décembre'!I41)),CHOOSE($Z$3,'Janvier'!I41,'Février'!I41,'Mars'!I41,'Avril'!I41,'Mai'!I41,'Juin'!I41,'Juillet'!I41,'Août'!I41,'Septembre'!I41,'Octobre'!I41,'Novembre'!I41,'Décembre'!I41),"") | AD37: =IF(ISNUMBER(CHOOSE($Z$3,'Janvier'!M41,'Février'!M41,'Mars'!M41,'Avril'!M41,'Mai'!M41,'Juin'!M41,'Juillet'!M41,'Août'!M41,'Septembre'!M41,'Octobre'!M41,'Novembre'!M41,'Décembre'!M41)),CHOOSE($Z$3,'Janvier'!M41,'Février'!M41,'Mars'!M41,'Avril'!M41,'Mai'!M41,'Juin'!M41,'Juillet'!M41,'Août'!M41,'Septembre'!M41,'Octobre'!M41,'Novembre'!M41,'Décembre'!M41),"") | AE37: =IF(ISNUMBER(CHOOSE($Z$3,'Janvier'!Q41,'Février'!Q41,'Mars'!Q41,'Avril'!Q41,'Mai'!Q41,'Juin'!Q41,'Juillet'!Q41,'Août'!Q41,'Septembre'!Q41,'Octobre'!Q41,'Novembre'!Q41,'Décembre'!Q41)),CHOOSE($Z$3,'Janvier'!Q41,'Février'!Q41,'Mars'!Q41,'Avril'!Q41,'Mai'!Q41,'Juin'!Q41,'Juillet'!Q41,'Août'!Q41,'Septembre'!Q41,'Octobre'!Q41,'Novembre'!Q41,'Décembre'!Q41),"") | AF37: =IF(ISNUMBER(CHOOSE($Z$3,'Janvier'!T41,'Février'!T41,'Mars'!T41,'Avril'!T41,'Mai'!T41,'Juin'!T41,'Juillet'!T41,'Août'!T41,'Septembre'!T41,'Octobre'!T41,'Novembre'!T41,'Décembre'!T41)),CHOOSE($Z$3,'Janvier'!T41,'Février'!T41,'Mars'!T41,'Avril'!T41,'Mai'!T41,'Juin'!T41,'Juillet'!T41,'Août'!T41,'Septembre'!T41,'Octobre'!T41,'Novembre'!T41,'Décembre'!T41),"") | AG37: =IF(ISNUMBER(CHOOSE($Z$3,'Janvier'!U41,'Février'!U41,'Mars'!U41,'Avril'!U41,'Mai'!U41,'Juin'!U41,'Juillet'!U41,'Août'!U41,'Septembre'!U41,'Octobre'!U41,'Novembre'!U41,'Décembre'!U41)),CHOOSE($Z$3,'Janvier'!U41,'Février'!U41,'Mars'!U41,'Avril'!U41,'Mai'!U41,'Juin'!U41,'Juillet'!U41,'Août'!U41,'Septembre'!U41,'Octobre'!U41,'Novembre'!U41,'Décembre'!U41),"") | AH37: =IF(ISNUMBER(CHOOSE($Z$3,'Janvier'!V41,'Février'!V41,'Mars'!V41,'Avril'!V41,'Mai'!V41,'Juin'!V41,'Juillet'!V41,'Août'!V41,'Septembre'!V41,'Octobre'!V41,'Novembre'!V41,'Décembre'!V41)),CHOOSE($Z$3,'Janvier'!V41,'Février'!V41,'Mars'!V41,'Avril'!V41,'Mai'!V41,'Juin'!V41,'Juillet'!V41,'Août'!V41,'Septembre'!V41,'Octobre'!V41,'Novembre'!V41,'Décembre'!V41),"") | AI37: =IF(ISNUMBER(CHOOSE($Z$3,'Janvier'!W41,'Février'!W41,'Mars'!W41,'Avril'!W41,'Mai'!W41,'Juin'!W41,'Juillet'!W41,'Août'!W41,'Septembre'!W41,'Octobre'!W41,'Novembre'!W41,'Décembre'!W41)),CHOOSE($Z$3,'Janvier'!W41,'Février'!W41,'Mars'!W41,'Avril'!W41,'Mai'!W41,'Juin'!W41,'Juillet'!W41,'Août'!W41,'Septembre'!W41,'Octobre'!W41,'Novembre'!W41,'Décembre'!W41),"") | AJ37: =IF(Produits!$A$40="","",Produits!$D$40) | AK37: =IF(ISNUMBER(CHOOSE($Z$3,'Janvier'!X41,'Février'!X41,'Mars'!X41,'Avril'!X41,'Mai'!X41,'Juin'!X41,'Juillet'!X41,'Août'!X41,'Septembre'!X41,'Octobre'!X41,'Novembre'!X41,'Décembre'!X41)),CHOOSE($Z$3,'Janvier'!X41,'Février'!X41,'Mars'!X41,'Avril'!X41,'Mai'!X41,'Juin'!X41,'Juillet'!X41,'Août'!X41,'Septembre'!X41,'Octobre'!X41,'Novembre'!X41,'Décembre'!X41),"") | AL37: =IF(AND(ISNUMBER(AI37),ISNUMBER(AJ37)),IF(AI37<=AJ37,1,0),0) | AM37: =IF(OR(AA37="",AK37=""),-1,AK37+ROW()/1000000)
A38: =AA17 | C38: =IF(OR(AB17="",MAX(AB17,AC17,AD17,AE17)=0),"",REPT("█",MAX(1,ROUND(AB17/MAX(AB17,AC17,AD17,AE17)*6,0)))) | D38: =IF(OR(AC17="",MAX(AB17,AC17,AD17,AE17)=0),"",REPT("█",MAX(1,ROUND(AC17/MAX(AB17,AC17,AD17,AE17)*6,0)))) | E38: =IF(OR(AD17="",MAX(AB17,AC17,AD17,AE17)=0),"",REPT("█",MAX(1,ROUND(AD17/MAX(AB17,AC17,AD17,AE17)*6,0)))) | F38: =IF(OR(AE17="",MAX(AB17,AC17,AD17,AE17)=0),"",REPT("█",MAX(1,ROUND(AE17/MAX(AB17,AC17,AD17,AE17)*6,0)))) | G38: =IF(COUNT(AB17,AC17,AD17,AE17)<2,"",IF(IF(AE17<>"",AE17,IF(AD17<>"",AD17,IF(AC17<>"",AC17,IF(AB17<>"",AB17,""))))>IF(AB17<>"",AB17,IF(AC17<>"",AC17,IF(AD17<>"",AD17,AE17))),"▲",IF(IF(AE17<>"",AE17,IF(AD17<>"",AD17,IF(AC17<>"",AC17,IF(AB17<>"",AB17,""))))<IF(AB17<>"",AB17,IF(AC17<>"",AC17,IF(AD17<>"",AD17,AE17))),"▼","="))) | H38: =AI17 | I38: =AJ17 | J38: =IF(AL17=1,"À COMMANDER",IF(AA17="","","")) | AA38: =IF(Produits!$A$41="","",Produits!$A$41) | AB38: =IF(ISNUMBER(CHOOSE($Z$3,'Janvier'!E42,'Février'!E42,'Mars'!E42,'Avril'!E42,'Mai'!E42,'Juin'!E42,'Juillet'!E42,'Août'!E42,'Septembre'!E42,'Octobre'!E42,'Novembre'!E42,'Décembre'!E42)),CHOOSE($Z$3,'Janvier'!E42,'Février'!E42,'Mars'!E42,'Avril'!E42,'Mai'!E42,'Juin'!E42,'Juillet'!E42,'Août'!E42,'Septembre'!E42,'Octobre'!E42,'Novembre'!E42,'Décembre'!E42),"") | AC38: =IF(ISNUMBER(CHOOSE($Z$3,'Janvier'!I42,'Février'!I42,'Mars'!I42,'Avril'!I42,'Mai'!I42,'Juin'!I42,'Juillet'!I42,'Août'!I42,'Septembre'!I42,'Octobre'!I42,'Novembre'!I42,'Décembre'!I42)),CHOOSE($Z$3,'Janvier'!I42,'Février'!I42,'Mars'!I42,'Avril'!I42,'Mai'!I42,'Juin'!I42,'Juillet'!I42,'Août'!I42,'Septembre'!I42,'Octobre'!I42,'Novembre'!I42,'Décembre'!I42),"") | AD38: =IF(ISNUMBER(CHOOSE($Z$3,'Janvier'!M42,'Février'!M42,'Mars'!M42,'Avril'!M42,'Mai'!M42,'Juin'!M42,'Juillet'!M42,'Août'!M42,'Septembre'!M42,'Octobre'!M42,'Novembre'!M42,'Décembre'!M42)),CHOOSE($Z$3,'Janvier'!M42,'Février'!M42,'Mars'!M42,'Avril'!M42,'Mai'!M42,'Juin'!M42,'Juillet'!M42,'Août'!M42,'Septembre'!M42,'Octobre'!M42,'Novembre'!M42,'Décembre'!M42),"") | AE38: =IF(ISNUMBER(CHOOSE($Z$3,'Janvier'!Q42,'Février'!Q42,'Mars'!Q42,'Avril'!Q42,'Mai'!Q42,'Juin'!Q42,'Juillet'!Q42,'Août'!Q42,'Septembre'!Q42,'Octobre'!Q42,'Novembre'!Q42,'Décembre'!Q42)),CHOOSE($Z$3,'Janvier'!Q42,'Février'!Q42,'Mars'!Q42,'Avril'!Q42,'Mai'!Q42,'Juin'!Q42,'Juillet'!Q42,'Août'!Q42,'Septembre'!Q42,'Octobre'!Q42,'Novembre'!Q42,'Décembre'!Q42),"") | AF38: =IF(ISNUMBER(CHOOSE($Z$3,'Janvier'!T42,'Février'!T42,'Mars'!T42,'Avril'!T42,'Mai'!T42,'Juin'!T42,'Juillet'!T42,'Août'!T42,'Septembre'!T42,'Octobre'!T42,'Novembre'!T42,'Décembre'!T42)),CHOOSE($Z$3,'Janvier'!T42,'Février'!T42,'Mars'!T42,'Avril'!T42,'Mai'!T42,'Juin'!T42,'Juillet'!T42,'Août'!T42,'Septembre'!T42,'Octobre'!T42,'Novembre'!T42,'Décembre'!T42),"") | AG38: =IF(ISNUMBER(CHOOSE($Z$3,'Janvier'!U42,'Février'!U42,'Mars'!U42,'Avril'!U42,'Mai'!U42,'Juin'!U42,'Juillet'!U42,'Août'!U42,'Septembre'!U42,'Octobre'!U42,'Novembre'!U42,'Décembre'!U42)),CHOOSE($Z$3,'Janvier'!U42,'Février'!U42,'Mars'!U42,'Avril'!U42,'Mai'!U42,'Juin'!U42,'Juillet'!U42,'Août'!U42,'Septembre'!U42,'Octobre'!U42,'Novembre'!U42,'Décembre'!U42),"") | AH38: =IF(ISNUMBER(CHOOSE($Z$3,'Janvier'!V42,'Février'!V42,'Mars'!V42,'Avril'!V42,'Mai'!V42,'Juin'!V42,'Juillet'!V42,'Août'!V42,'Septembre'!V42,'Octobre'!V42,'Novembre'!V42,'Décembre'!V42)),CHOOSE($Z$3,'Janvier'!V42,'Février'!V42,'Mars'!V42,'Avril'!V42,'Mai'!V42,'Juin'!V42,'Juillet'!V42,'Août'!V42,'Septembre'!V42,'Octobre'!V42,'Novembre'!V42,'Décembre'!V42),"") | AI38: =IF(ISNUMBER(CHOOSE($Z$3,'Janvier'!W42,'Février'!W42,'Mars'!W42,'Avril'!W42,'Mai'!W42,'Juin'!W42,'Juillet'!W42,'Août'!W42,'Septembre'!W42,'Octobre'!W42,'Novembre'!W42,'Décembre'!W42)),CHOOSE($Z$3,'Janvier'!W42,'Février'!W42,'Mars'!W42,'Avril'!W42,'Mai'!W42,'Juin'!W42,'Juillet'!W42,'Août'!W42,'Septembre'!W42,'Octobre'!W42,'Novembre'!W42,'Décembre'!W42),"") | AJ38: =IF(Produits!$A$41="","",Produits!$D$41) | AK38: =IF(ISNUMBER(CHOOSE($Z$3,'Janvier'!X42,'Février'!X42,'Mars'!X42,'Avril'!X42,'Mai'!X42,'Juin'!X42,'Juillet'!X42,'Août'!X42,'Septembre'!X42,'Octobre'!X42,'Novembre'!X42,'Décembre'!X42)),CHOOSE($Z$3,'Janvier'!X42,'Février'!X42,'Mars'!X42,'Avril'!X42,'Mai'!X42,'Juin'!X42,'Juillet'!X42,'Août'!X42,'Septembre'!X42,'Octobre'!X42,'Novembre'!X42,'Décembre'!X42),"") | AL38: =IF(AND(ISNUMBER(AI38),ISNUMBER(AJ38)),IF(AI38<=AJ38,1,0),0) | AM38: =IF(OR(AA38="",AK38=""),-1,AK38+ROW()/1000000)
A39: =AA18 | C39: =IF(OR(AB18="",MAX(AB18,AC18,AD18,AE18)=0),"",REPT("█",MAX(1,ROUND(AB18/MAX(AB18,AC18,AD18,AE18)*6,0)))) | D39: =IF(OR(AC18="",MAX(AB18,AC18,AD18,AE18)=0),"",REPT("█",MAX(1,ROUND(AC18/MAX(AB18,AC18,AD18,AE18)*6,0)))) | E39: =IF(OR(AD18="",MAX(AB18,AC18,AD18,AE18)=0),"",REPT("█",MAX(1,ROUND(AD18/MAX(AB18,AC18,AD18,AE18)*6,0)))) | F39: =IF(OR(AE18="",MAX(AB18,AC18,AD18,AE18)=0),"",REPT("█",MAX(1,ROUND(AE18/MAX(AB18,AC18,AD18,AE18)*6,0)))) | G39: =IF(COUNT(AB18,AC18,AD18,AE18)<2,"",IF(IF(AE18<>"",AE18,IF(AD18<>"",AD18,IF(AC18<>"",AC18,IF(AB18<>"",AB18,""))))>IF(AB18<>"",AB18,IF(AC18<>"",AC18,IF(AD18<>"",AD18,AE18))),"▲",IF(IF(AE18<>"",AE18,IF(AD18<>"",AD18,IF(AC18<>"",AC18,IF(AB18<>"",AB18,""))))<IF(AB18<>"",AB18,IF(AC18<>"",AC18,IF(AD18<>"",AD18,AE18))),"▼","="))) | H39: =AI18 | I39: =AJ18 | J39: =IF(AL18=1,"À COMMANDER",IF(AA18="","","")) | AA39: =IF(Produits!$A$42="","",Produits!$A$42) | AB39: =IF(ISNUMBER(CHOOSE($Z$3,'Janvier'!E43,'Février'!E43,'Mars'!E43,'Avril'!E43,'Mai'!E43,'Juin'!E43,'Juillet'!E43,'Août'!E43,'Septembre'!E43,'Octobre'!E43,'Novembre'!E43,'Décembre'!E43)),CHOOSE($Z$3,'Janvier'!E43,'Février'!E43,'Mars'!E43,'Avril'!E43,'Mai'!E43,'Juin'!E43,'Juillet'!E43,'Août'!E43,'Septembre'!E43,'Octobre'!E43,'Novembre'!E43,'Décembre'!E43),"") | AC39: =IF(ISNUMBER(CHOOSE($Z$3,'Janvier'!I43,'Février'!I43,'Mars'!I43,'Avril'!I43,'Mai'!I43,'Juin'!I43,'Juillet'!I43,'Août'!I43,'Septembre'!I43,'Octobre'!I43,'Novembre'!I43,'Décembre'!I43)),CHOOSE($Z$3,'Janvier'!I43,'Février'!I43,'Mars'!I43,'Avril'!I43,'Mai'!I43,'Juin'!I43,'Juillet'!I43,'Août'!I43,'Septembre'!I43,'Octobre'!I43,'Novembre'!I43,'Décembre'!I43),"") | AD39: =IF(ISNUMBER(CHOOSE($Z$3,'Janvier'!M43,'Février'!M43,'Mars'!M43,'Avril'!M43,'Mai'!M43,'Juin'!M43,'Juillet'!M43,'Août'!M43,'Septembre'!M43,'Octobre'!M43,'Novembre'!M43,'Décembre'!M43)),CHOOSE($Z$3,'Janvier'!M43,'Février'!M43,'Mars'!M43,'Avril'!M43,'Mai'!M43,'Juin'!M43,'Juillet'!M43,'Août'!M43,'Septembre'!M43,'Octobre'!M43,'Novembre'!M43,'Décembre'!M43),"") | AE39: =IF(ISNUMBER(CHOOSE($Z$3,'Janvier'!Q43,'Février'!Q43,'Mars'!Q43,'Avril'!Q43,'Mai'!Q43,'Juin'!Q43,'Juillet'!Q43,'Août'!Q43,'Septembre'!Q43,'Octobre'!Q43,'Novembre'!Q43,'Décembre'!Q43)),CHOOSE($Z$3,'Janvier'!Q43,'Février'!Q43,'Mars'!Q43,'Avril'!Q43,'Mai'!Q43,'Juin'!Q43,'Juillet'!Q43,'Août'!Q43,'Septembre'!Q43,'Octobre'!Q43,'Novembre'!Q43,'Décembre'!Q43),"") | AF39: =IF(ISNUMBER(CHOOSE($Z$3,'Janvier'!T43,'Février'!T43,'Mars'!T43,'Avril'!T43,'Mai'!T43,'Juin'!T43,'Juillet'!T43,'Août'!T43,'Septembre'!T43,'Octobre'!T43,'Novembre'!T43,'Décembre'!T43)),CHOOSE($Z$3,'Janvier'!T43,'Février'!T43,'Mars'!T43,'Avril'!T43,'Mai'!T43,'Juin'!T43,'Juillet'!T43,'Août'!T43,'Septembre'!T43,'Octobre'!T43,'Novembre'!T43,'Décembre'!T43),"") | AG39: =IF(ISNUMBER(CHOOSE($Z$3,'Janvier'!U43,'Février'!U43,'Mars'!U43,'Avril'!U43,'Mai'!U43,'Juin'!U43,'Juillet'!U43,'Août'!U43,'Septembre'!U43,'Octobre'!U43,'Novembre'!U43,'Décembre'!U43)),CHOOSE($Z$3,'Janvier'!U43,'Février'!U43,'Mars'!U43,'Avril'!U43,'Mai'!U43,'Juin'!U43,'Juillet'!U43,'Août'!U43,'Septembre'!U43,'Octobre'!U43,'Novembre'!U43,'Décembre'!U43),"") | AH39: =IF(ISNUMBER(CHOOSE($Z$3,'Janvier'!V43,'Février'!V43,'Mars'!V43,'Avril'!V43,'Mai'!V43,'Juin'!V43,'Juillet'!V43,'Août'!V43,'Septembre'!V43,'Octobre'!V43,'Novembre'!V43,'Décembre'!V43)),CHOOSE($Z$3,'Janvier'!V43,'Février'!V43,'Mars'!V43,'Avril'!V43,'Mai'!V43,'Juin'!V43,'Juillet'!V43,'Août'!V43,'Septembre'!V43,'Octobre'!V43,'Novembre'!V43,'Décembre'!V43),"") | AI39: =IF(ISNUMBER(CHOOSE($Z$3,'Janvier'!W43,'Février'!W43,'Mars'!W43,'Avril'!W43,'Mai'!W43,'Juin'!W43,'Juillet'!W43,'Août'!W43,'Septembre'!W43,'Octobre'!W43,'Novembre'!W43,'Décembre'!W43)),CHOOSE($Z$3,'Janvier'!W43,'Février'!W43,'Mars'!W43,'Avril'!W43,'Mai'!W43,'Juin'!W43,'Juillet'!W43,'Août'!W43,'Septembre'!W43,'Octobre'!W43,'Novembre'!W43,'Décembre'!W43),"") | AJ39: =IF(Produits!$A$42="","",Produits!$D$42) | AK39: =IF(ISNUMBER(CHOOSE($Z$3,'Janvier'!X43,'Février'!X43,'Mars'!X43,'Avril'!X43,'Mai'!X43,'Juin'!X43,'Juillet'!X43,'Août'!X43,'Septembre'!X43,'Octobre'!X43,'Novembre'!X43,'Décembre'!X43)),CHOOSE($Z$3,'Janvier'!X43,'Février'!X43,'Mars'!X43,'Avril'!X43,'Mai'!X43,'Juin'!X43,'Juillet'!X43,'Août'!X43,'Septembre'!X43,'Octobre'!X43,'Novembre'!X43,'Décembre'!X43),"") | AL39: =IF(AND(ISNUMBER(AI39),ISNUMBER(AJ39)),IF(AI39<=AJ39,1,0),0) | AM39: =IF(OR(AA39="",AK39=""),-1,AK39+ROW()/1000000)
A40: =AA19 | C40: =IF(OR(AB19="",MAX(AB19,AC19,AD19,AE19)=0),"",REPT("█",MAX(1,ROUND(AB19/MAX(AB19,AC19,AD19,AE19)*6,0)))) | D40: =IF(OR(AC19="",MAX(AB19,AC19,AD19,AE19)=0),"",REPT("█",MAX(1,ROUND(AC19/MAX(AB19,AC19,AD19,AE19)*6,0)))) | E40: =IF(OR(AD19="",MAX(AB19,AC19,AD19,AE19)=0),"",REPT("█",MAX(1,ROUND(AD19/MAX(AB19,AC19,AD19,AE19)*6,0)))) | F40: =IF(OR(AE19="",MAX(AB19,AC19,AD19,AE19)=0),"",REPT("█",MAX(1,ROUND(AE19/MAX(AB19,AC19,AD19,AE19)*6,0)))) | G40: =IF(COUNT(AB19,AC19,AD19,AE19)<2,"",IF(IF(AE19<>"",AE19,IF(AD19<>"",AD19,IF(AC19<>"",AC19,IF(AB19<>"",AB19,""))))>IF(AB19<>"",AB19,IF(AC19<>"",AC19,IF(AD19<>"",AD19,AE19))),"▲",IF(IF(AE19<>"",AE19,IF(AD19<>"",AD19,IF(AC19<>"",AC19,IF(AB19<>"",AB19,""))))<IF(AB19<>"",AB19,IF(AC19<>"",AC19,IF(AD19<>"",AD19,AE19))),"▼","="))) | H40: =AI19 | I40: =AJ19 | J40: =IF(AL19=1,"À COMMANDER",IF(AA19="","","")) | AA40: =IF(Produits!$A$43="","",Produits!$A$43) | AB40: =IF(ISNUMBER(CHOOSE($Z$3,'Janvier'!E44,'Février'!E44,'Mars'!E44,'Avril'!E44,'Mai'!E44,'Juin'!E44,'Juillet'!E44,'Août'!E44,'Septembre'!E44,'Octobre'!E44,'Novembre'!E44,'Décembre'!E44)),CHOOSE($Z$3,'Janvier'!E44,'Février'!E44,'Mars'!E44,'Avril'!E44,'Mai'!E44,'Juin'!E44,'Juillet'!E44,'Août'!E44,'Septembre'!E44,'Octobre'!E44,'Novembre'!E44,'Décembre'!E44),"") | AC40: =IF(ISNUMBER(CHOOSE($Z$3,'Janvier'!I44,'Février'!I44,'Mars'!I44,'Avril'!I44,'Mai'!I44,'Juin'!I44,'Juillet'!I44,'Août'!I44,'Septembre'!I44,'Octobre'!I44,'Novembre'!I44,'Décembre'!I44)),CHOOSE($Z$3,'Janvier'!I44,'Février'!I44,'Mars'!I44,'Avril'!I44,'Mai'!I44,'Juin'!I44,'Juillet'!I44,'Août'!I44,'Septembre'!I44,'Octobre'!I44,'Novembre'!I44,'Décembre'!I44),"") | AD40: =IF(ISNUMBER(CHOOSE($Z$3,'Janvier'!M44,'Février'!M44,'Mars'!M44,'Avril'!M44,'Mai'!M44,'Juin'!M44,'Juillet'!M44,'Août'!M44,'Septembre'!M44,'Octobre'!M44,'Novembre'!M44,'Décembre'!M44)),CHOOSE($Z$3,'Janvier'!M44,'Février'!M44,'Mars'!M44,'Avril'!M44,'Mai'!M44,'Juin'!M44,'Juillet'!M44,'Août'!M44,'Septembre'!M44,'Octobre'!M44,'Novembre'!M44,'Décembre'!M44),"") | AE40: =IF(ISNUMBER(CHOOSE($Z$3,'Janvier'!Q44,'Février'!Q44,'Mars'!Q44,'Avril'!Q44,'Mai'!Q44,'Juin'!Q44,'Juillet'!Q44,'Août'!Q44,'Septembre'!Q44,'Octobre'!Q44,'Novembre'!Q44,'Décembre'!Q44)),CHOOSE($Z$3,'Janvier'!Q44,'Février'!Q44,'Mars'!Q44,'Avril'!Q44,'Mai'!Q44,'Juin'!Q44,'Juillet'!Q44,'Août'!Q44,'Septembre'!Q44,'Octobre'!Q44,'Novembre'!Q44,'Décembre'!Q44),"") | AF40: =IF(ISNUMBER(CHOOSE($Z$3,'Janvier'!T44,'Février'!T44,'Mars'!T44,'Avril'!T44,'Mai'!T44,'Juin'!T44,'Juillet'!T44,'Août'!T44,'Septembre'!T44,'Octobre'!T44,'Novembre'!T44,'Décembre'!T44)),CHOOSE($Z$3,'Janvier'!T44,'Février'!T44,'Mars'!T44,'Avril'!T44,'Mai'!T44,'Juin'!T44,'Juillet'!T44,'Août'!T44,'Septembre'!T44,'Octobre'!T44,'Novembre'!T44,'Décembre'!T44),"") | AG40: =IF(ISNUMBER(CHOOSE($Z$3,'Janvier'!U44,'Février'!U44,'Mars'!U44,'Avril'!U44,'Mai'!U44,'Juin'!U44,'Juillet'!U44,'Août'!U44,'Septembre'!U44,'Octobre'!U44,'Novembre'!U44,'Décembre'!U44)),CHOOSE($Z$3,'Janvier'!U44,'Février'!U44,'Mars'!U44,'Avril'!U44,'Mai'!U44,'Juin'!U44,'Juillet'!U44,'Août'!U44,'Septembre'!U44,'Octobre'!U44,'Novembre'!U44,'Décembre'!U44),"") | AH40: =IF(ISNUMBER(CHOOSE($Z$3,'Janvier'!V44,'Février'!V44,'Mars'!V44,'Avril'!V44,'Mai'!V44,'Juin'!V44,'Juillet'!V44,'Août'!V44,'Septembre'!V44,'Octobre'!V44,'Novembre'!V44,'Décembre'!V44)),CHOOSE($Z$3,'Janvier'!V44,'Février'!V44,'Mars'!V44,'Avril'!V44,'Mai'!V44,'Juin'!V44,'Juillet'!V44,'Août'!V44,'Septembre'!V44,'Octobre'!V44,'Novembre'!V44,'Décembre'!V44),"") | AI40: =IF(ISNUMBER(CHOOSE($Z$3,'Janvier'!W44,'Février'!W44,'Mars'!W44,'Avril'!W44,'Mai'!W44,'Juin'!W44,'Juillet'!W44,'Août'!W44,'Septembre'!W44,'Octobre'!W44,'Novembre'!W44,'Décembre'!W44)),CHOOSE($Z$3,'Janvier'!W44,'Février'!W44,'Mars'!W44,'Avril'!W44,'Mai'!W44,'Juin'!W44,'Juillet'!W44,'Août'!W44,'Septembre'!W44,'Octobre'!W44,'Novembre'!W44,'Décembre'!W44),"") | AJ40: =IF(Produits!$A$43="","",Produits!$D$43) | AK40: =IF(ISNUMBER(CHOOSE($Z$3,'Janvier'!X44,'Février'!X44,'Mars'!X44,'Avril'!X44,'Mai'!X44,'Juin'!X44,'Juillet'!X44,'Août'!X44,'Septembre'!X44,'Octobre'!X44,'Novembre'!X44,'Décembre'!X44)),CHOOSE($Z$3,'Janvier'!X44,'Février'!X44,'Mars'!X44,'Avril'!X44,'Mai'!X44,'Juin'!X44,'Juillet'!X44,'Août'!X44,'Septembre'!X44,'Octobre'!X44,'Novembre'!X44,'Décembre'!X44),"") | AL40: =IF(AND(ISNUMBER(AI40),ISNUMBER(AJ40)),IF(AI40<=AJ40,1,0),0) | AM40: =IF(OR(AA40="",AK40=""),-1,AK40+ROW()/1000000)
A41: =AA20 | C41: =IF(OR(AB20="",MAX(AB20,AC20,AD20,AE20)=0),"",REPT("█",MAX(1,ROUND(AB20/MAX(AB20,AC20,AD20,AE20)*6,0)))) | D41: =IF(OR(AC20="",MAX(AB20,AC20,AD20,AE20)=0),"",REPT("█",MAX(1,ROUND(AC20/MAX(AB20,AC20,AD20,AE20)*6,0)))) | E41: =IF(OR(AD20="",MAX(AB20,AC20,AD20,AE20)=0),"",REPT("█",MAX(1,ROUND(AD20/MAX(AB20,AC20,AD20,AE20)*6,0)))) | F41: =IF(OR(AE20="",MAX(AB20,AC20,AD20,AE20)=0),"",REPT("█",MAX(1,ROUND(AE20/MAX(AB20,AC20,AD20,AE20)*6,0)))) | G41: =IF(COUNT(AB20,AC20,AD20,AE20)<2,"",IF(IF(AE20<>"",AE20,IF(AD20<>"",AD20,IF(AC20<>"",AC20,IF(AB20<>"",AB20,""))))>IF(AB20<>"",AB20,IF(AC20<>"",AC20,IF(AD20<>"",AD20,AE20))),"▲",IF(IF(AE20<>"",AE20,IF(AD20<>"",AD20,IF(AC20<>"",AC20,IF(AB20<>"",AB20,""))))<IF(AB20<>"",AB20,IF(AC20<>"",AC20,IF(AD20<>"",AD20,AE20))),"▼","="))) | H41: =AI20 | I41: =AJ20 | J41: =IF(AL20=1,"À COMMANDER",IF(AA20="","","")) | AA41: =IF(Produits!$A$44="","",Produits!$A$44) | AB41: =IF(ISNUMBER(CHOOSE($Z$3,'Janvier'!E45,'Février'!E45,'Mars'!E45,'Avril'!E45,'Mai'!E45,'Juin'!E45,'Juillet'!E45,'Août'!E45,'Septembre'!E45,'Octobre'!E45,'Novembre'!E45,'Décembre'!E45)),CHOOSE($Z$3,'Janvier'!E45,'Février'!E45,'Mars'!E45,'Avril'!E45,'Mai'!E45,'Juin'!E45,'Juillet'!E45,'Août'!E45,'Septembre'!E45,'Octobre'!E45,'Novembre'!E45,'Décembre'!E45),"") | AC41: =IF(ISNUMBER(CHOOSE($Z$3,'Janvier'!I45,'Février'!I45,'Mars'!I45,'Avril'!I45,'Mai'!I45,'Juin'!I45,'Juillet'!I45,'Août'!I45,'Septembre'!I45,'Octobre'!I45,'Novembre'!I45,'Décembre'!I45)),CHOOSE($Z$3,'Janvier'!I45,'Février'!I45,'Mars'!I45,'Avril'!I45,'Mai'!I45,'Juin'!I45,'Juillet'!I45,'Août'!I45,'Septembre'!I45,'Octobre'!I45,'Novembre'!I45,'Décembre'!I45),"") | AD41: =IF(ISNUMBER(CHOOSE($Z$3,'Janvier'!M45,'Février'!M45,'Mars'!M45,'Avril'!M45,'Mai'!M45,'Juin'!M45,'Juillet'!M45,'Août'!M45,'Septembre'!M45,'Octobre'!M45,'Novembre'!M45,'Décembre'!M45)),CHOOSE($Z$3,'Janvier'!M45,'Février'!M45,'Mars'!M45,'Avril'!M45,'Mai'!M45,'Juin'!M45,'Juillet'!M45,'Août'!M45,'Septembre'!M45,'Octobre'!M45,'Novembre'!M45,'Décembre'!M45),"") | AE41: =IF(ISNUMBER(CHOOSE($Z$3,'Janvier'!Q45,'Février'!Q45,'Mars'!Q45,'Avril'!Q45,'Mai'!Q45,'Juin'!Q45,'Juillet'!Q45,'Août'!Q45,'Septembre'!Q45,'Octobre'!Q45,'Novembre'!Q45,'Décembre'!Q45)),CHOOSE($Z$3,'Janvier'!Q45,'Février'!Q45,'Mars'!Q45,'Avril'!Q45,'Mai'!Q45,'Juin'!Q45,'Juillet'!Q45,'Août'!Q45,'Septembre'!Q45,'Octobre'!Q45,'Novembre'!Q45,'Décembre'!Q45),"") | AF41: =IF(ISNUMBER(CHOOSE($Z$3,'Janvier'!T45,'Février'!T45,'Mars'!T45,'Avril'!T45,'Mai'!T45,'Juin'!T45,'Juillet'!T45,'Août'!T45,'Septembre'!T45,'Octobre'!T45,'Novembre'!T45,'Décembre'!T45)),CHOOSE($Z$3,'Janvier'!T45,'Février'!T45,'Mars'!T45,'Avril'!T45,'Mai'!T45,'Juin'!T45,'Juillet'!T45,'Août'!T45,'Septembre'!T45,'Octobre'!T45,'Novembre'!T45,'Décembre'!T45),"") | AG41: =IF(ISNUMBER(CHOOSE($Z$3,'Janvier'!U45,'Février'!U45,'Mars'!U45,'Avril'!U45,'Mai'!U45,'Juin'!U45,'Juillet'!U45,'Août'!U45,'Septembre'!U45,'Octobre'!U45,'Novembre'!U45,'Décembre'!U45)),CHOOSE($Z$3,'Janvier'!U45,'Février'!U45,'Mars'!U45,'Avril'!U45,'Mai'!U45,'Juin'!U45,'Juillet'!U45,'Août'!U45,'Septembre'!U45,'Octobre'!U45,'Novembre'!U45,'Décembre'!U45),"") | AH41: =IF(ISNUMBER(CHOOSE($Z$3,'Janvier'!V45,'Février'!V45,'Mars'!V45,'Avril'!V45,'Mai'!V45,'Juin'!V45,'Juillet'!V45,'Août'!V45,'Septembre'!V45,'Octobre'!V45,'Novembre'!V45,'Décembre'!V45)),CHOOSE($Z$3,'Janvier'!V45,'Février'!V45,'Mars'!V45,'Avril'!V45,'Mai'!V45,'Juin'!V45,'Juillet'!V45,'Août'!V45,'Septembre'!V45,'Octobre'!V45,'Novembre'!V45,'Décembre'!V45),"") | AI41: =IF(ISNUMBER(CHOOSE($Z$3,'Janvier'!W45,'Février'!W45,'Mars'!W45,'Avril'!W45,'Mai'!W45,'Juin'!W45,'Juillet'!W45,'Août'!W45,'Septembre'!W45,'Octobre'!W45,'Novembre'!W45,'Décembre'!W45)),CHOOSE($Z$3,'Janvier'!W45,'Février'!W45,'Mars'!W45,'Avril'!W45,'Mai'!W45,'Juin'!W45,'Juillet'!W45,'Août'!W45,'Septembre'!W45,'Octobre'!W45,'Novembre'!W45,'Décembre'!W45),"") | AJ41: =IF(Produits!$A$44="","",Produits!$D$44) | AK41: =IF(ISNUMBER(CHOOSE($Z$3,'Janvier'!X45,'Février'!X45,'Mars'!X45,'Avril'!X45,'Mai'!X45,'Juin'!X45,'Juillet'!X45,'Août'!X45,'Septembre'!X45,'Octobre'!X45,'Novembre'!X45,'Décembre'!X45)),CHOOSE($Z$3,'Janvier'!X45,'Février'!X45,'Mars'!X45,'Avril'!X45,'Mai'!X45,'Juin'!X45,'Juillet'!X45,'Août'!X45,'Septembre'!X45,'Octobre'!X45,'Novembre'!X45,'Décembre'!X45),"") | AL41: =IF(AND(ISNUMBER(AI41),ISNUMBER(AJ41)),IF(AI41<=AJ41,1,0),0) | AM41: =IF(OR(AA41="",AK41=""),-1,AK41+ROW()/1000000)
A42: =AA21 | C42: =IF(OR(AB21="",MAX(AB21,AC21,AD21,AE21)=0),"",REPT("█",MAX(1,ROUND(AB21/MAX(AB21,AC21,AD21,AE21)*6,0)))) | D42: =IF(OR(AC21="",MAX(AB21,AC21,AD21,AE21)=0),"",REPT("█",MAX(1,ROUND(AC21/MAX(AB21,AC21,AD21,AE21)*6,0)))) | E42: =IF(OR(AD21="",MAX(AB21,AC21,AD21,AE21)=0),"",REPT("█",MAX(1,ROUND(AD21/MAX(AB21,AC21,AD21,AE21)*6,0)))) | F42: =IF(OR(AE21="",MAX(AB21,AC21,AD21,AE21)=0),"",REPT("█",MAX(1,ROUND(AE21/MAX(AB21,AC21,AD21,AE21)*6,0)))) | G42: =IF(COUNT(AB21,AC21,AD21,AE21)<2,"",IF(IF(AE21<>"",AE21,IF(AD21<>"",AD21,IF(AC21<>"",AC21,IF(AB21<>"",AB21,""))))>IF(AB21<>"",AB21,IF(AC21<>"",AC21,IF(AD21<>"",AD21,AE21))),"▲",IF(IF(AE21<>"",AE21,IF(AD21<>"",AD21,IF(AC21<>"",AC21,IF(AB21<>"",AB21,""))))<IF(AB21<>"",AB21,IF(AC21<>"",AC21,IF(AD21<>"",AD21,AE21))),"▼","="))) | H42: =AI21 | I42: =AJ21 | J42: =IF(AL21=1,"À COMMANDER",IF(AA21="","","")) | AA42: =IF(Produits!$A$45="","",Produits!$A$45) | AB42: =IF(ISNUMBER(CHOOSE($Z$3,'Janvier'!E46,'Février'!E46,'Mars'!E46,'Avril'!E46,'Mai'!E46,'Juin'!E46,'Juillet'!E46,'Août'!E46,'Septembre'!E46,'Octobre'!E46,'Novembre'!E46,'Décembre'!E46)),CHOOSE($Z$3,'Janvier'!E46,'Février'!E46,'Mars'!E46,'Avril'!E46,'Mai'!E46,'Juin'!E46,'Juillet'!E46,'Août'!E46,'Septembre'!E46,'Octobre'!E46,'Novembre'!E46,'Décembre'!E46),"") | AC42: =IF(ISNUMBER(CHOOSE($Z$3,'Janvier'!I46,'Février'!I46,'Mars'!I46,'Avril'!I46,'Mai'!I46,'Juin'!I46,'Juillet'!I46,'Août'!I46,'Septembre'!I46,'Octobre'!I46,'Novembre'!I46,'Décembre'!I46)),CHOOSE($Z$3,'Janvier'!I46,'Février'!I46,'Mars'!I46,'Avril'!I46,'Mai'!I46,'Juin'!I46,'Juillet'!I46,'Août'!I46,'Septembre'!I46,'Octobre'!I46,'Novembre'!I46,'Décembre'!I46),"") | AD42: =IF(ISNUMBER(CHOOSE($Z$3,'Janvier'!M46,'Février'!M46,'Mars'!M46,'Avril'!M46,'Mai'!M46,'Juin'!M46,'Juillet'!M46,'Août'!M46,'Septembre'!M46,'Octobre'!M46,'Novembre'!M46,'Décembre'!M46)),CHOOSE($Z$3,'Janvier'!M46,'Février'!M46,'Mars'!M46,'Avril'!M46,'Mai'!M46,'Juin'!M46,'Juillet'!M46,'Août'!M46,'Septembre'!M46,'Octobre'!M46,'Novembre'!M46,'Décembre'!M46),"") | AE42: =IF(ISNUMBER(CHOOSE($Z$3,'Janvier'!Q46,'Février'!Q46,'Mars'!Q46,'Avril'!Q46,'Mai'!Q46,'Juin'!Q46,'Juillet'!Q46,'Août'!Q46,'Septembre'!Q46,'Octobre'!Q46,'Novembre'!Q46,'Décembre'!Q46)),CHOOSE($Z$3,'Janvier'!Q46,'Février'!Q46,'Mars'!Q46,'Avril'!Q46,'Mai'!Q46,'Juin'!Q46,'Juillet'!Q46,'Août'!Q46,'Septembre'!Q46,'Octobre'!Q46,'Novembre'!Q46,'Décembre'!Q46),"") | AF42: =IF(ISNUMBER(CHOOSE($Z$3,'Janvier'!T46,'Février'!T46,'Mars'!T46,'Avril'!T46,'Mai'!T46,'Juin'!T46,'Juillet'!T46,'Août'!T46,'Septembre'!T46,'Octobre'!T46,'Novembre'!T46,'Décembre'!T46)),CHOOSE($Z$3,'Janvier'!T46,'Février'!T46,'Mars'!T46,'Avril'!T46,'Mai'!T46,'Juin'!T46,'Juillet'!T46,'Août'!T46,'Septembre'!T46,'Octobre'!T46,'Novembre'!T46,'Décembre'!T46),"") | AG42: =IF(ISNUMBER(CHOOSE($Z$3,'Janvier'!U46,'Février'!U46,'Mars'!U46,'Avril'!U46,'Mai'!U46,'Juin'!U46,'Juillet'!U46,'Août'!U46,'Septembre'!U46,'Octobre'!U46,'Novembre'!U46,'Décembre'!U46)),CHOOSE($Z$3,'Janvier'!U46,'Février'!U46,'Mars'!U46,'Avril'!U46,'Mai'!U46,'Juin'!U46,'Juillet'!U46,'Août'!U46,'Septembre'!U46,'Octobre'!U46,'Novembre'!U46,'Décembre'!U46),"") | AH42: =IF(ISNUMBER(CHOOSE($Z$3,'Janvier'!V46,'Février'!V46,'Mars'!V46,'Avril'!V46,'Mai'!V46,'Juin'!V46,'Juillet'!V46,'Août'!V46,'Septembre'!V46,'Octobre'!V46,'Novembre'!V46,'Décembre'!V46)),CHOOSE($Z$3,'Janvier'!V46,'Février'!V46,'Mars'!V46,'Avril'!V46,'Mai'!V46,'Juin'!V46,'Juillet'!V46,'Août'!V46,'Septembre'!V46,'Octobre'!V46,'Novembre'!V46,'Décembre'!V46),"") | AI42: =IF(ISNUMBER(CHOOSE($Z$3,'Janvier'!W46,'Février'!W46,'Mars'!W46,'Avril'!W46,'Mai'!W46,'Juin'!W46,'Juillet'!W46,'Août'!W46,'Septembre'!W46,'Octobre'!W46,'Novembre'!W46,'Décembre'!W46)),CHOOSE($Z$3,'Janvier'!W46,'Février'!W46,'Mars'!W46,'Avril'!W46,'Mai'!W46,'Juin'!W46,'Juillet'!W46,'Août'!W46,'Septembre'!W46,'Octobre'!W46,'Novembre'!W46,'Décembre'!W46),"") | AJ42: =IF(Produits!$A$45="","",Produits!$D$45) | AK42: =IF(ISNUMBER(CHOOSE($Z$3,'Janvier'!X46,'Février'!X46,'Mars'!X46,'Avril'!X46,'Mai'!X46,'Juin'!X46,'Juillet'!X46,'Août'!X46,'Septembre'!X46,'Octobre'!X46,'Novembre'!X46,'Décembre'!X46)),CHOOSE($Z$3,'Janvier'!X46,'Février'!X46,'Mars'!X46,'Avril'!X46,'Mai'!X46,'Juin'!X46,'Juillet'!X46,'Août'!X46,'Septembre'!X46,'Octobre'!X46,'Novembre'!X46,'Décembre'!X46),"") | AL42: =IF(AND(ISNUMBER(AI42),ISNUMBER(AJ42)),IF(AI42<=AJ42,1,0),0) | AM42: =IF(OR(AA42="",AK42=""),-1,AK42+ROW()/1000000)
A43: =AA22 | C43: =IF(OR(AB22="",MAX(AB22,AC22,AD22,AE22)=0),"",REPT("█",MAX(1,ROUND(AB22/MAX(AB22,AC22,AD22,AE22)*6,0)))) | D43: =IF(OR(AC22="",MAX(AB22,AC22,AD22,AE22)=0),"",REPT("█",MAX(1,ROUND(AC22/MAX(AB22,AC22,AD22,AE22)*6,0)))) | E43: =IF(OR(AD22="",MAX(AB22,AC22,AD22,AE22)=0),"",REPT("█",MAX(1,ROUND(AD22/MAX(AB22,AC22,AD22,AE22)*6,0)))) | F43: =IF(OR(AE22="",MAX(AB22,AC22,AD22,AE22)=0),"",REPT("█",MAX(1,ROUND(AE22/MAX(AB22,AC22,AD22,AE22)*6,0)))) | G43: =IF(COUNT(AB22,AC22,AD22,AE22)<2,"",IF(IF(AE22<>"",AE22,IF(AD22<>"",AD22,IF(AC22<>"",AC22,IF(AB22<>"",AB22,""))))>IF(AB22<>"",AB22,IF(AC22<>"",AC22,IF(AD22<>"",AD22,AE22))),"▲",IF(IF(AE22<>"",AE22,IF(AD22<>"",AD22,IF(AC22<>"",AC22,IF(AB22<>"",AB22,""))))<IF(AB22<>"",AB22,IF(AC22<>"",AC22,IF(AD22<>"",AD22,AE22))),"▼","="))) | H43: =AI22 | I43: =AJ22 | J43: =IF(AL22=1,"À COMMANDER",IF(AA22="","","")) | AA43: =IF(Produits!$A$46="","",Produits!$A$46) | AB43: =IF(ISNUMBER(CHOOSE($Z$3,'Janvier'!E47,'Février'!E47,'Mars'!E47,'Avril'!E47,'Mai'!E47,'Juin'!E47,'Juillet'!E47,'Août'!E47,'Septembre'!E47,'Octobre'!E47,'Novembre'!E47,'Décembre'!E47)),CHOOSE($Z$3,'Janvier'!E47,'Février'!E47,'Mars'!E47,'Avril'!E47,'Mai'!E47,'Juin'!E47,'Juillet'!E47,'Août'!E47,'Septembre'!E47,'Octobre'!E47,'Novembre'!E47,'Décembre'!E47),"") | AC43: =IF(ISNUMBER(CHOOSE($Z$3,'Janvier'!I47,'Février'!I47,'Mars'!I47,'Avril'!I47,'Mai'!I47,'Juin'!I47,'Juillet'!I47,'Août'!I47,'Septembre'!I47,'Octobre'!I47,'Novembre'!I47,'Décembre'!I47)),CHOOSE($Z$3,'Janvier'!I47,'Février'!I47,'Mars'!I47,'Avril'!I47,'Mai'!I47,'Juin'!I47,'Juillet'!I47,'Août'!I47,'Septembre'!I47,'Octobre'!I47,'Novembre'!I47,'Décembre'!I47),"") | AD43: =IF(ISNUMBER(CHOOSE($Z$3,'Janvier'!M47,'Février'!M47,'Mars'!M47,'Avril'!M47,'Mai'!M47,'Juin'!M47,'Juillet'!M47,'Août'!M47,'Septembre'!M47,'Octobre'!M47,'Novembre'!M47,'Décembre'!M47)),CHOOSE($Z$3,'Janvier'!M47,'Février'!M47,'Mars'!M47,'Avril'!M47,'Mai'!M47,'Juin'!M47,'Juillet'!M47,'Août'!M47,'Septembre'!M47,'Octobre'!M47,'Novembre'!M47,'Décembre'!M47),"") | AE43: =IF(ISNUMBER(CHOOSE($Z$3,'Janvier'!Q47,'Février'!Q47,'Mars'!Q47,'Avril'!Q47,'Mai'!Q47,'Juin'!Q47,'Juillet'!Q47,'Août'!Q47,'Septembre'!Q47,'Octobre'!Q47,'Novembre'!Q47,'Décembre'!Q47)),CHOOSE($Z$3,'Janvier'!Q47,'Février'!Q47,'Mars'!Q47,'Avril'!Q47,'Mai'!Q47,'Juin'!Q47,'Juillet'!Q47,'Août'!Q47,'Septembre'!Q47,'Octobre'!Q47,'Novembre'!Q47,'Décembre'!Q47),"") | AF43: =IF(ISNUMBER(CHOOSE($Z$3,'Janvier'!T47,'Février'!T47,'Mars'!T47,'Avril'!T47,'Mai'!T47,'Juin'!T47,'Juillet'!T47,'Août'!T47,'Septembre'!T47,'Octobre'!T47,'Novembre'!T47,'Décembre'!T47)),CHOOSE($Z$3,'Janvier'!T47,'Février'!T47,'Mars'!T47,'Avril'!T47,'Mai'!T47,'Juin'!T47,'Juillet'!T47,'Août'!T47,'Septembre'!T47,'Octobre'!T47,'Novembre'!T47,'Décembre'!T47),"") | AG43: =IF(ISNUMBER(CHOOSE($Z$3,'Janvier'!U47,'Février'!U47,'Mars'!U47,'Avril'!U47,'Mai'!U47,'Juin'!U47,'Juillet'!U47,'Août'!U47,'Septembre'!U47,'Octobre'!U47,'Novembre'!U47,'Décembre'!U47)),CHOOSE($Z$3,'Janvier'!U47,'Février'!U47,'Mars'!U47,'Avril'!U47,'Mai'!U47,'Juin'!U47,'Juillet'!U47,'Août'!U47,'Septembre'!U47,'Octobre'!U47,'Novembre'!U47,'Décembre'!U47),"") | AH43: =IF(ISNUMBER(CHOOSE($Z$3,'Janvier'!V47,'Février'!V47,'Mars'!V47,'Avril'!V47,'Mai'!V47,'Juin'!V47,'Juillet'!V47,'Août'!V47,'Septembre'!V47,'Octobre'!V47,'Novembre'!V47,'Décembre'!V47)),CHOOSE($Z$3,'Janvier'!V47,'Février'!V47,'Mars'!V47,'Avril'!V47,'Mai'!V47,'Juin'!V47,'Juillet'!V47,'Août'!V47,'Septembre'!V47,'Octobre'!V47,'Novembre'!V47,'Décembre'!V47),"") | AI43: =IF(ISNUMBER(CHOOSE($Z$3,'Janvier'!W47,'Février'!W47,'Mars'!W47,'Avril'!W47,'Mai'!W47,'Juin'!W47,'Juillet'!W47,'Août'!W47,'Septembre'!W47,'Octobre'!W47,'Novembre'!W47,'Décembre'!W47)),CHOOSE($Z$3,'Janvier'!W47,'Février'!W47,'Mars'!W47,'Avril'!W47,'Mai'!W47,'Juin'!W47,'Juillet'!W47,'Août'!W47,'Septembre'!W47,'Octobre'!W47,'Novembre'!W47,'Décembre'!W47),"") | AJ43: =IF(Produits!$A$46="","",Produits!$D$46) | AK43: =IF(ISNUMBER(CHOOSE($Z$3,'Janvier'!X47,'Février'!X47,'Mars'!X47,'Avril'!X47,'Mai'!X47,'Juin'!X47,'Juillet'!X47,'Août'!X47,'Septembre'!X47,'Octobre'!X47,'Novembre'!X47,'Décembre'!X47)),CHOOSE($Z$3,'Janvier'!X47,'Février'!X47,'Mars'!X47,'Avril'!X47,'Mai'!X47,'Juin'!X47,'Juillet'!X47,'Août'!X47,'Septembre'!X47,'Octobre'!X47,'Novembre'!X47,'Décembre'!X47),"") | AL43: =IF(AND(ISNUMBER(AI43),ISNUMBER(AJ43)),IF(AI43<=AJ43,1,0),0) | AM43: =IF(OR(AA43="",AK43=""),-1,AK43+ROW()/1000000)
A44: =AA23 | C44: =IF(OR(AB23="",MAX(AB23,AC23,AD23,AE23)=0),"",REPT("█",MAX(1,ROUND(AB23/MAX(AB23,AC23,AD23,AE23)*6,0)))) | D44: =IF(OR(AC23="",MAX(AB23,AC23,AD23,AE23)=0),"",REPT("█",MAX(1,ROUND(AC23/MAX(AB23,AC23,AD23,AE23)*6,0)))) | E44: =IF(OR(AD23="",MAX(AB23,AC23,AD23,AE23)=0),"",REPT("█",MAX(1,ROUND(AD23/MAX(AB23,AC23,AD23,AE23)*6,0)))) | F44: =IF(OR(AE23="",MAX(AB23,AC23,AD23,AE23)=0),"",REPT("█",MAX(1,ROUND(AE23/MAX(AB23,AC23,AD23,AE23)*6,0)))) | G44: =IF(COUNT(AB23,AC23,AD23,AE23)<2,"",IF(IF(AE23<>"",AE23,IF(AD23<>"",AD23,IF(AC23<>"",AC23,IF(AB23<>"",AB23,""))))>IF(AB23<>"",AB23,IF(AC23<>"",AC23,IF(AD23<>"",AD23,AE23))),"▲",IF(IF(AE23<>"",AE23,IF(AD23<>"",AD23,IF(AC23<>"",AC23,IF(AB23<>"",AB23,""))))<IF(AB23<>"",AB23,IF(AC23<>"",AC23,IF(AD23<>"",AD23,AE23))),"▼","="))) | H44: =AI23 | I44: =AJ23 | J44: =IF(AL23=1,"À COMMANDER",IF(AA23="","","")) | AA44: =IF(Produits!$A$47="","",Produits!$A$47) | AB44: =IF(ISNUMBER(CHOOSE($Z$3,'Janvier'!E48,'Février'!E48,'Mars'!E48,'Avril'!E48,'Mai'!E48,'Juin'!E48,'Juillet'!E48,'Août'!E48,'Septembre'!E48,'Octobre'!E48,'Novembre'!E48,'Décembre'!E48)),CHOOSE($Z$3,'Janvier'!E48,'Février'!E48,'Mars'!E48,'Avril'!E48,'Mai'!E48,'Juin'!E48,'Juillet'!E48,'Août'!E48,'Septembre'!E48,'Octobre'!E48,'Novembre'!E48,'Décembre'!E48),"") | AC44: =IF(ISNUMBER(CHOOSE($Z$3,'Janvier'!I48,'Février'!I48,'Mars'!I48,'Avril'!I48,'Mai'!I48,'Juin'!I48,'Juillet'!I48,'Août'!I48,'Septembre'!I48,'Octobre'!I48,'Novembre'!I48,'Décembre'!I48)),CHOOSE($Z$3,'Janvier'!I48,'Février'!I48,'Mars'!I48,'Avril'!I48,'Mai'!I48,'Juin'!I48,'Juillet'!I48,'Août'!I48,'Septembre'!I48,'Octobre'!I48,'Novembre'!I48,'Décembre'!I48),"") | AD44: =IF(ISNUMBER(CHOOSE($Z$3,'Janvier'!M48,'Février'!M48,'Mars'!M48,'Avril'!M48,'Mai'!M48,'Juin'!M48,'Juillet'!M48,'Août'!M48,'Septembre'!M48,'Octobre'!M48,'Novembre'!M48,'Décembre'!M48)),CHOOSE($Z$3,'Janvier'!M48,'Février'!M48,'Mars'!M48,'Avril'!M48,'Mai'!M48,'Juin'!M48,'Juillet'!M48,'Août'!M48,'Septembre'!M48,'Octobre'!M48,'Novembre'!M48,'Décembre'!M48),"") | AE44: =IF(ISNUMBER(CHOOSE($Z$3,'Janvier'!Q48,'Février'!Q48,'Mars'!Q48,'Avril'!Q48,'Mai'!Q48,'Juin'!Q48,'Juillet'!Q48,'Août'!Q48,'Septembre'!Q48,'Octobre'!Q48,'Novembre'!Q48,'Décembre'!Q48)),CHOOSE($Z$3,'Janvier'!Q48,'Février'!Q48,'Mars'!Q48,'Avril'!Q48,'Mai'!Q48,'Juin'!Q48,'Juillet'!Q48,'Août'!Q48,'Septembre'!Q48,'Octobre'!Q48,'Novembre'!Q48,'Décembre'!Q48),"") | AF44: =IF(ISNUMBER(CHOOSE($Z$3,'Janvier'!T48,'Février'!T48,'Mars'!T48,'Avril'!T48,'Mai'!T48,'Juin'!T48,'Juillet'!T48,'Août'!T48,'Septembre'!T48,'Octobre'!T48,'Novembre'!T48,'Décembre'!T48)),CHOOSE($Z$3,'Janvier'!T48,'Février'!T48,'Mars'!T48,'Avril'!T48,'Mai'!T48,'Juin'!T48,'Juillet'!T48,'Août'!T48,'Septembre'!T48,'Octobre'!T48,'Novembre'!T48,'Décembre'!T48),"") | AG44: =IF(ISNUMBER(CHOOSE($Z$3,'Janvier'!U48,'Février'!U48,'Mars'!U48,'Avril'!U48,'Mai'!U48,'Juin'!U48,'Juillet'!U48,'Août'!U48,'Septembre'!U48,'Octobre'!U48,'Novembre'!U48,'Décembre'!U48)),CHOOSE($Z$3,'Janvier'!U48,'Février'!U48,'Mars'!U48,'Avril'!U48,'Mai'!U48,'Juin'!U48,'Juillet'!U48,'Août'!U48,'Septembre'!U48,'Octobre'!U48,'Novembre'!U48,'Décembre'!U48),"") | AH44: =IF(ISNUMBER(CHOOSE($Z$3,'Janvier'!V48,'Février'!V48,'Mars'!V48,'Avril'!V48,'Mai'!V48,'Juin'!V48,'Juillet'!V48,'Août'!V48,'Septembre'!V48,'Octobre'!V48,'Novembre'!V48,'Décembre'!V48)),CHOOSE($Z$3,'Janvier'!V48,'Février'!V48,'Mars'!V48,'Avril'!V48,'Mai'!V48,'Juin'!V48,'Juillet'!V48,'Août'!V48,'Septembre'!V48,'Octobre'!V48,'Novembre'!V48,'Décembre'!V48),"") | AI44: =IF(ISNUMBER(CHOOSE($Z$3,'Janvier'!W48,'Février'!W48,'Mars'!W48,'Avril'!W48,'Mai'!W48,'Juin'!W48,'Juillet'!W48,'Août'!W48,'Septembre'!W48,'Octobre'!W48,'Novembre'!W48,'Décembre'!W48)),CHOOSE($Z$3,'Janvier'!W48,'Février'!W48,'Mars'!W48,'Avril'!W48,'Mai'!W48,'Juin'!W48,'Juillet'!W48,'Août'!W48,'Septembre'!W48,'Octobre'!W48,'Novembre'!W48,'Décembre'!W48),"") | AJ44: =IF(Produits!$A$47="","",Produits!$D$47) | AK44: =IF(ISNUMBER(CHOOSE($Z$3,'Janvier'!X48,'Février'!X48,'Mars'!X48,'Avril'!X48,'Mai'!X48,'Juin'!X48,'Juillet'!X48,'Août'!X48,'Septembre'!X48,'Octobre'!X48,'Novembre'!X48,'Décembre'!X48)),CHOOSE($Z$3,'Janvier'!X48,'Février'!X48,'Mars'!X48,'Avril'!X48,'Mai'!X48,'Juin'!X48,'Juillet'!X48,'Août'!X48,'Septembre'!X48,'Octobre'!X48,'Novembre'!X48,'Décembre'!X48),"") | AL44: =IF(AND(ISNUMBER(AI44),ISNUMBER(AJ44)),IF(AI44<=AJ44,1,0),0) | AM44: =IF(OR(AA44="",AK44=""),-1,AK44+ROW()/1000000)
A45: =AA24 | C45: =IF(OR(AB24="",MAX(AB24,AC24,AD24,AE24)=0),"",REPT("█",MAX(1,ROUND(AB24/MAX(AB24,AC24,AD24,AE24)*6,0)))) | D45: =IF(OR(AC24="",MAX(AB24,AC24,AD24,AE24)=0),"",REPT("█",MAX(1,ROUND(AC24/MAX(AB24,AC24,AD24,AE24)*6,0)))) | E45: =IF(OR(AD24="",MAX(AB24,AC24,AD24,AE24)=0),"",REPT("█",MAX(1,ROUND(AD24/MAX(AB24,AC24,AD24,AE24)*6,0)))) | F45: =IF(OR(AE24="",MAX(AB24,AC24,AD24,AE24)=0),"",REPT("█",MAX(1,ROUND(AE24/MAX(AB24,AC24,AD24,AE24)*6,0)))) | G45: =IF(COUNT(AB24,AC24,AD24,AE24)<2,"",IF(IF(AE24<>"",AE24,IF(AD24<>"",AD24,IF(AC24<>"",AC24,IF(AB24<>"",AB24,""))))>IF(AB24<>"",AB24,IF(AC24<>"",AC24,IF(AD24<>"",AD24,AE24))),"▲",IF(IF(AE24<>"",AE24,IF(AD24<>"",AD24,IF(AC24<>"",AC24,IF(AB24<>"",AB24,""))))<IF(AB24<>"",AB24,IF(AC24<>"",AC24,IF(AD24<>"",AD24,AE24))),"▼","="))) | H45: =AI24 | I45: =AJ24 | J45: =IF(AL24=1,"À COMMANDER",IF(AA24="","","")) | AA45: =IF(Produits!$A$48="","",Produits!$A$48) | AB45: =IF(ISNUMBER(CHOOSE($Z$3,'Janvier'!E49,'Février'!E49,'Mars'!E49,'Avril'!E49,'Mai'!E49,'Juin'!E49,'Juillet'!E49,'Août'!E49,'Septembre'!E49,'Octobre'!E49,'Novembre'!E49,'Décembre'!E49)),CHOOSE($Z$3,'Janvier'!E49,'Février'!E49,'Mars'!E49,'Avril'!E49,'Mai'!E49,'Juin'!E49,'Juillet'!E49,'Août'!E49,'Septembre'!E49,'Octobre'!E49,'Novembre'!E49,'Décembre'!E49),"") | AC45: =IF(ISNUMBER(CHOOSE($Z$3,'Janvier'!I49,'Février'!I49,'Mars'!I49,'Avril'!I49,'Mai'!I49,'Juin'!I49,'Juillet'!I49,'Août'!I49,'Septembre'!I49,'Octobre'!I49,'Novembre'!I49,'Décembre'!I49)),CHOOSE($Z$3,'Janvier'!I49,'Février'!I49,'Mars'!I49,'Avril'!I49,'Mai'!I49,'Juin'!I49,'Juillet'!I49,'Août'!I49,'Septembre'!I49,'Octobre'!I49,'Novembre'!I49,'Décembre'!I49),"") | AD45: =IF(ISNUMBER(CHOOSE($Z$3,'Janvier'!M49,'Février'!M49,'Mars'!M49,'Avril'!M49,'Mai'!M49,'Juin'!M49,'Juillet'!M49,'Août'!M49,'Septembre'!M49,'Octobre'!M49,'Novembre'!M49,'Décembre'!M49)),CHOOSE($Z$3,'Janvier'!M49,'Février'!M49,'Mars'!M49,'Avril'!M49,'Mai'!M49,'Juin'!M49,'Juillet'!M49,'Août'!M49,'Septembre'!M49,'Octobre'!M49,'Novembre'!M49,'Décembre'!M49),"") | AE45: =IF(ISNUMBER(CHOOSE($Z$3,'Janvier'!Q49,'Février'!Q49,'Mars'!Q49,'Avril'!Q49,'Mai'!Q49,'Juin'!Q49,'Juillet'!Q49,'Août'!Q49,'Septembre'!Q49,'Octobre'!Q49,'Novembre'!Q49,'Décembre'!Q49)),CHOOSE($Z$3,'Janvier'!Q49,'Février'!Q49,'Mars'!Q49,'Avril'!Q49,'Mai'!Q49,'Juin'!Q49,'Juillet'!Q49,'Août'!Q49,'Septembre'!Q49,'Octobre'!Q49,'Novembre'!Q49,'Décembre'!Q49),"") | AF45: =IF(ISNUMBER(CHOOSE($Z$3,'Janvier'!T49,'Février'!T49,'Mars'!T49,'Avril'!T49,'Mai'!T49,'Juin'!T49,'Juillet'!T49,'Août'!T49,'Septembre'!T49,'Octobre'!T49,'Novembre'!T49,'Décembre'!T49)),CHOOSE($Z$3,'Janvier'!T49,'Février'!T49,'Mars'!T49,'Avril'!T49,'Mai'!T49,'Juin'!T49,'Juillet'!T49,'Août'!T49,'Septembre'!T49,'Octobre'!T49,'Novembre'!T49,'Décembre'!T49),"") | AG45: =IF(ISNUMBER(CHOOSE($Z$3,'Janvier'!U49,'Février'!U49,'Mars'!U49,'Avril'!U49,'Mai'!U49,'Juin'!U49,'Juillet'!U49,'Août'!U49,'Septembre'!U49,'Octobre'!U49,'Novembre'!U49,'Décembre'!U49)),CHOOSE($Z$3,'Janvier'!U49,'Février'!U49,'Mars'!U49,'Avril'!U49,'Mai'!U49,'Juin'!U49,'Juillet'!U49,'Août'!U49,'Septembre'!U49,'Octobre'!U49,'Novembre'!U49,'Décembre'!U49),"") | AH45: =IF(ISNUMBER(CHOOSE($Z$3,'Janvier'!V49,'Février'!V49,'Mars'!V49,'Avril'!V49,'Mai'!V49,'Juin'!V49,'Juillet'!V49,'Août'!V49,'Septembre'!V49,'Octobre'!V49,'Novembre'!V49,'Décembre'!V49)),CHOOSE($Z$3,'Janvier'!V49,'Février'!V49,'Mars'!V49,'Avril'!V49,'Mai'!V49,'Juin'!V49,'Juillet'!V49,'Août'!V49,'Septembre'!V49,'Octobre'!V49,'Novembre'!V49,'Décembre'!V49),"") | AI45: =IF(ISNUMBER(CHOOSE($Z$3,'Janvier'!W49,'Février'!W49,'Mars'!W49,'Avril'!W49,'Mai'!W49,'Juin'!W49,'Juillet'!W49,'Août'!W49,'Septembre'!W49,'Octobre'!W49,'Novembre'!W49,'Décembre'!W49)),CHOOSE($Z$3,'Janvier'!W49,'Février'!W49,'Mars'!W49,'Avril'!W49,'Mai'!W49,'Juin'!W49,'Juillet'!W49,'Août'!W49,'Septembre'!W49,'Octobre'!W49,'Novembre'!W49,'Décembre'!W49),"") | AJ45: =IF(Produits!$A$48="","",Produits!$D$48) | AK45: =IF(ISNUMBER(CHOOSE($Z$3,'Janvier'!X49,'Février'!X49,'Mars'!X49,'Avril'!X49,'Mai'!X49,'Juin'!X49,'Juillet'!X49,'Août'!X49,'Septembre'!X49,'Octobre'!X49,'Novembre'!X49,'Décembre'!X49)),CHOOSE($Z$3,'Janvier'!X49,'Février'!X49,'Mars'!X49,'Avril'!X49,'Mai'!X49,'Juin'!X49,'Juillet'!X49,'Août'!X49,'Septembre'!X49,'Octobre'!X49,'Novembre'!X49,'Décembre'!X49),"") | AL45: =IF(AND(ISNUMBER(AI45),ISNUMBER(AJ45)),IF(AI45<=AJ45,1,0),0) | AM45: =IF(OR(AA45="",AK45=""),-1,AK45+ROW()/1000000)
A46: =AA25 | C46: =IF(OR(AB25="",MAX(AB25,AC25,AD25,AE25)=0),"",REPT("█",MAX(1,ROUND(AB25/MAX(AB25,AC25,AD25,AE25)*6,0)))) | D46: =IF(OR(AC25="",MAX(AB25,AC25,AD25,AE25)=0),"",REPT("█",MAX(1,ROUND(AC25/MAX(AB25,AC25,AD25,AE25)*6,0)))) | E46: =IF(OR(AD25="",MAX(AB25,AC25,AD25,AE25)=0),"",REPT("█",MAX(1,ROUND(AD25/MAX(AB25,AC25,AD25,AE25)*6,0)))) | F46: =IF(OR(AE25="",MAX(AB25,AC25,AD25,AE25)=0),"",REPT("█",MAX(1,ROUND(AE25/MAX(AB25,AC25,AD25,AE25)*6,0)))) | G46: =IF(COUNT(AB25,AC25,AD25,AE25)<2,"",IF(IF(AE25<>"",AE25,IF(AD25<>"",AD25,IF(AC25<>"",AC25,IF(AB25<>"",AB25,""))))>IF(AB25<>"",AB25,IF(AC25<>"",AC25,IF(AD25<>"",AD25,AE25))),"▲",IF(IF(AE25<>"",AE25,IF(AD25<>"",AD25,IF(AC25<>"",AC25,IF(AB25<>"",AB25,""))))<IF(AB25<>"",AB25,IF(AC25<>"",AC25,IF(AD25<>"",AD25,AE25))),"▼","="))) | H46: =AI25 | I46: =AJ25 | J46: =IF(AL25=1,"À COMMANDER",IF(AA25="","","")) | AA46: =IF(Produits!$A$49="","",Produits!$A$49) | AB46: =IF(ISNUMBER(CHOOSE($Z$3,'Janvier'!E50,'Février'!E50,'Mars'!E50,'Avril'!E50,'Mai'!E50,'Juin'!E50,'Juillet'!E50,'Août'!E50,'Septembre'!E50,'Octobre'!E50,'Novembre'!E50,'Décembre'!E50)),CHOOSE($Z$3,'Janvier'!E50,'Février'!E50,'Mars'!E50,'Avril'!E50,'Mai'!E50,'Juin'!E50,'Juillet'!E50,'Août'!E50,'Septembre'!E50,'Octobre'!E50,'Novembre'!E50,'Décembre'!E50),"") | AC46: =IF(ISNUMBER(CHOOSE($Z$3,'Janvier'!I50,'Février'!I50,'Mars'!I50,'Avril'!I50,'Mai'!I50,'Juin'!I50,'Juillet'!I50,'Août'!I50,'Septembre'!I50,'Octobre'!I50,'Novembre'!I50,'Décembre'!I50)),CHOOSE($Z$3,'Janvier'!I50,'Février'!I50,'Mars'!I50,'Avril'!I50,'Mai'!I50,'Juin'!I50,'Juillet'!I50,'Août'!I50,'Septembre'!I50,'Octobre'!I50,'Novembre'!I50,'Décembre'!I50),"") | AD46: =IF(ISNUMBER(CHOOSE($Z$3,'Janvier'!M50,'Février'!M50,'Mars'!M50,'Avril'!M50,'Mai'!M50,'Juin'!M50,'Juillet'!M50,'Août'!M50,'Septembre'!M50,'Octobre'!M50,'Novembre'!M50,'Décembre'!M50)),CHOOSE($Z$3,'Janvier'!M50,'Février'!M50,'Mars'!M50,'Avril'!M50,'Mai'!M50,'Juin'!M50,'Juillet'!M50,'Août'!M50,'Septembre'!M50,'Octobre'!M50,'Novembre'!M50,'Décembre'!M50),"") | AE46: =IF(ISNUMBER(CHOOSE($Z$3,'Janvier'!Q50,'Février'!Q50,'Mars'!Q50,'Avril'!Q50,'Mai'!Q50,'Juin'!Q50,'Juillet'!Q50,'Août'!Q50,'Septembre'!Q50,'Octobre'!Q50,'Novembre'!Q50,'Décembre'!Q50)),CHOOSE($Z$3,'Janvier'!Q50,'Février'!Q50,'Mars'!Q50,'Avril'!Q50,'Mai'!Q50,'Juin'!Q50,'Juillet'!Q50,'Août'!Q50,'Septembre'!Q50,'Octobre'!Q50,'Novembre'!Q50,'Décembre'!Q50),"") | AF46: =IF(ISNUMBER(CHOOSE($Z$3,'Janvier'!T50,'Février'!T50,'Mars'!T50,'Avril'!T50,'Mai'!T50,'Juin'!T50,'Juillet'!T50,'Août'!T50,'Septembre'!T50,'Octobre'!T50,'Novembre'!T50,'Décembre'!T50)),CHOOSE($Z$3,'Janvier'!T50,'Février'!T50,'Mars'!T50,'Avril'!T50,'Mai'!T50,'Juin'!T50,'Juillet'!T50,'Août'!T50,'Septembre'!T50,'Octobre'!T50,'Novembre'!T50,'Décembre'!T50),"") | AG46: =IF(ISNUMBER(CHOOSE($Z$3,'Janvier'!U50,'Février'!U50,'Mars'!U50,'Avril'!U50,'Mai'!U50,'Juin'!U50,'Juillet'!U50,'Août'!U50,'Septembre'!U50,'Octobre'!U50,'Novembre'!U50,'Décembre'!U50)),CHOOSE($Z$3,'Janvier'!U50,'Février'!U50,'Mars'!U50,'Avril'!U50,'Mai'!U50,'Juin'!U50,'Juillet'!U50,'Août'!U50,'Septembre'!U50,'Octobre'!U50,'Novembre'!U50,'Décembre'!U50),"") | AH46: =IF(ISNUMBER(CHOOSE($Z$3,'Janvier'!V50,'Février'!V50,'Mars'!V50,'Avril'!V50,'Mai'!V50,'Juin'!V50,'Juillet'!V50,'Août'!V50,'Septembre'!V50,'Octobre'!V50,'Novembre'!V50,'Décembre'!V50)),CHOOSE($Z$3,'Janvier'!V50,'Février'!V50,'Mars'!V50,'Avril'!V50,'Mai'!V50,'Juin'!V50,'Juillet'!V50,'Août'!V50,'Septembre'!V50,'Octobre'!V50,'Novembre'!V50,'Décembre'!V50),"") | AI46: =IF(ISNUMBER(CHOOSE($Z$3,'Janvier'!W50,'Février'!W50,'Mars'!W50,'Avril'!W50,'Mai'!W50,'Juin'!W50,'Juillet'!W50,'Août'!W50,'Septembre'!W50,'Octobre'!W50,'Novembre'!W50,'Décembre'!W50)),CHOOSE($Z$3,'Janvier'!W50,'Février'!W50,'Mars'!W50,'Avril'!W50,'Mai'!W50,'Juin'!W50,'Juillet'!W50,'Août'!W50,'Septembre'!W50,'Octobre'!W50,'Novembre'!W50,'Décembre'!W50),"") | AJ46: =IF(Produits!$A$49="","",Produits!$D$49) | AK46: =IF(ISNUMBER(CHOOSE($Z$3,'Janvier'!X50,'Février'!X50,'Mars'!X50,'Avril'!X50,'Mai'!X50,'Juin'!X50,'Juillet'!X50,'Août'!X50,'Septembre'!X50,'Octobre'!X50,'Novembre'!X50,'Décembre'!X50)),CHOOSE($Z$3,'Janvier'!X50,'Février'!X50,'Mars'!X50,'Avril'!X50,'Mai'!X50,'Juin'!X50,'Juillet'!X50,'Août'!X50,'Septembre'!X50,'Octobre'!X50,'Novembre'!X50,'Décembre'!X50),"") | AL46: =IF(AND(ISNUMBER(AI46),ISNUMBER(AJ46)),IF(AI46<=AJ46,1,0),0) | AM46: =IF(OR(AA46="",AK46=""),-1,AK46+ROW()/1000000)
A47: =AA26 | C47: =IF(OR(AB26="",MAX(AB26,AC26,AD26,AE26)=0),"",REPT("█",MAX(1,ROUND(AB26/MAX(AB26,AC26,AD26,AE26)*6,0)))) | D47: =IF(OR(AC26="",MAX(AB26,AC26,AD26,AE26)=0),"",REPT("█",MAX(1,ROUND(AC26/MAX(AB26,AC26,AD26,AE26)*6,0)))) | E47: =IF(OR(AD26="",MAX(AB26,AC26,AD26,AE26)=0),"",REPT("█",MAX(1,ROUND(AD26/MAX(AB26,AC26,AD26,AE26)*6,0)))) | F47: =IF(OR(AE26="",MAX(AB26,AC26,AD26,AE26)=0),"",REPT("█",MAX(1,ROUND(AE26/MAX(AB26,AC26,AD26,AE26)*6,0)))) | G47: =IF(COUNT(AB26,AC26,AD26,AE26)<2,"",IF(IF(AE26<>"",AE26,IF(AD26<>"",AD26,IF(AC26<>"",AC26,IF(AB26<>"",AB26,""))))>IF(AB26<>"",AB26,IF(AC26<>"",AC26,IF(AD26<>"",AD26,AE26))),"▲",IF(IF(AE26<>"",AE26,IF(AD26<>"",AD26,IF(AC26<>"",AC26,IF(AB26<>"",AB26,""))))<IF(AB26<>"",AB26,IF(AC26<>"",AC26,IF(AD26<>"",AD26,AE26))),"▼","="))) | H47: =AI26 | I47: =AJ26 | J47: =IF(AL26=1,"À COMMANDER",IF(AA26="","","")) | AA47: =IF(Produits!$A$50="","",Produits!$A$50) | AB47: =IF(ISNUMBER(CHOOSE($Z$3,'Janvier'!E51,'Février'!E51,'Mars'!E51,'Avril'!E51,'Mai'!E51,'Juin'!E51,'Juillet'!E51,'Août'!E51,'Septembre'!E51,'Octobre'!E51,'Novembre'!E51,'Décembre'!E51)),CHOOSE($Z$3,'Janvier'!E51,'Février'!E51,'Mars'!E51,'Avril'!E51,'Mai'!E51,'Juin'!E51,'Juillet'!E51,'Août'!E51,'Septembre'!E51,'Octobre'!E51,'Novembre'!E51,'Décembre'!E51),"") | AC47: =IF(ISNUMBER(CHOOSE($Z$3,'Janvier'!I51,'Février'!I51,'Mars'!I51,'Avril'!I51,'Mai'!I51,'Juin'!I51,'Juillet'!I51,'Août'!I51,'Septembre'!I51,'Octobre'!I51,'Novembre'!I51,'Décembre'!I51)),CHOOSE($Z$3,'Janvier'!I51,'Février'!I51,'Mars'!I51,'Avril'!I51,'Mai'!I51,'Juin'!I51,'Juillet'!I51,'Août'!I51,'Septembre'!I51,'Octobre'!I51,'Novembre'!I51,'Décembre'!I51),"") | AD47: =IF(ISNUMBER(CHOOSE($Z$3,'Janvier'!M51,'Février'!M51,'Mars'!M51,'Avril'!M51,'Mai'!M51,'Juin'!M51,'Juillet'!M51,'Août'!M51,'Septembre'!M51,'Octobre'!M51,'Novembre'!M51,'Décembre'!M51)),CHOOSE($Z$3,'Janvier'!M51,'Février'!M51,'Mars'!M51,'Avril'!M51,'Mai'!M51,'Juin'!M51,'Juillet'!M51,'Août'!M51,'Septembre'!M51,'Octobre'!M51,'Novembre'!M51,'Décembre'!M51),"") | AE47: =IF(ISNUMBER(CHOOSE($Z$3,'Janvier'!Q51,'Février'!Q51,'Mars'!Q51,'Avril'!Q51,'Mai'!Q51,'Juin'!Q51,'Juillet'!Q51,'Août'!Q51,'Septembre'!Q51,'Octobre'!Q51,'Novembre'!Q51,'Décembre'!Q51)),CHOOSE($Z$3,'Janvier'!Q51,'Février'!Q51,'Mars'!Q51,'Avril'!Q51,'Mai'!Q51,'Juin'!Q51,'Juillet'!Q51,'Août'!Q51,'Septembre'!Q51,'Octobre'!Q51,'Novembre'!Q51,'Décembre'!Q51),"") | AF47: =IF(ISNUMBER(CHOOSE($Z$3,'Janvier'!T51,'Février'!T51,'Mars'!T51,'Avril'!T51,'Mai'!T51,'Juin'!T51,'Juillet'!T51,'Août'!T51,'Septembre'!T51,'Octobre'!T51,'Novembre'!T51,'Décembre'!T51)),CHOOSE($Z$3,'Janvier'!T51,'Février'!T51,'Mars'!T51,'Avril'!T51,'Mai'!T51,'Juin'!T51,'Juillet'!T51,'Août'!T51,'Septembre'!T51,'Octobre'!T51,'Novembre'!T51,'Décembre'!T51),"") | AG47: =IF(ISNUMBER(CHOOSE($Z$3,'Janvier'!U51,'Février'!U51,'Mars'!U51,'Avril'!U51,'Mai'!U51,'Juin'!U51,'Juillet'!U51,'Août'!U51,'Septembre'!U51,'Octobre'!U51,'Novembre'!U51,'Décembre'!U51)),CHOOSE($Z$3,'Janvier'!U51,'Février'!U51,'Mars'!U51,'Avril'!U51,'Mai'!U51,'Juin'!U51,'Juillet'!U51,'Août'!U51,'Septembre'!U51,'Octobre'!U51,'Novembre'!U51,'Décembre'!U51),"") | AH47: =IF(ISNUMBER(CHOOSE($Z$3,'Janvier'!V51,'Février'!V51,'Mars'!V51,'Avril'!V51,'Mai'!V51,'Juin'!V51,'Juillet'!V51,'Août'!V51,'Septembre'!V51,'Octobre'!V51,'Novembre'!V51,'Décembre'!V51)),CHOOSE($Z$3,'Janvier'!V51,'Février'!V51,'Mars'!V51,'Avril'!V51,'Mai'!V51,'Juin'!V51,'Juillet'!V51,'Août'!V51,'Septembre'!V51,'Octobre'!V51,'Novembre'!V51,'Décembre'!V51),"") | AI47: =IF(ISNUMBER(CHOOSE($Z$3,'Janvier'!W51,'Février'!W51,'Mars'!W51,'Avril'!W51,'Mai'!W51,'Juin'!W51,'Juillet'!W51,'Août'!W51,'Septembre'!W51,'Octobre'!W51,'Novembre'!W51,'Décembre'!W51)),CHOOSE($Z$3,'Janvier'!W51,'Février'!W51,'Mars'!W51,'Avril'!W51,'Mai'!W51,'Juin'!W51,'Juillet'!W51,'Août'!W51,'Septembre'!W51,'Octobre'!W51,'Novembre'!W51,'Décembre'!W51),"") | AJ47: =IF(Produits!$A$50="","",Produits!$D$50) | AK47: =IF(ISNUMBER(CHOOSE($Z$3,'Janvier'!X51,'Février'!X51,'Mars'!X51,'Avril'!X51,'Mai'!X51,'Juin'!X51,'Juillet'!X51,'Août'!X51,'Septembre'!X51,'Octobre'!X51,'Novembre'!X51,'Décembre'!X51)),CHOOSE($Z$3,'Janvier'!X51,'Février'!X51,'Mars'!X51,'Avril'!X51,'Mai'!X51,'Juin'!X51,'Juillet'!X51,'Août'!X51,'Septembre'!X51,'Octobre'!X51,'Novembre'!X51,'Décembre'!X51),"") | AL47: =IF(AND(ISNUMBER(AI47),ISNUMBER(AJ47)),IF(AI47<=AJ47,1,0),0) | AM47: =IF(OR(AA47="",AK47=""),-1,AK47+ROW()/1000000)
A48: =AA27 | C48: =IF(OR(AB27="",MAX(AB27,AC27,AD27,AE27)=0),"",REPT("█",MAX(1,ROUND(AB27/MAX(AB27,AC27,AD27,AE27)*6,0)))) | D48: =IF(OR(AC27="",MAX(AB27,AC27,AD27,AE27)=0),"",REPT("█",MAX(1,ROUND(AC27/MAX(AB27,AC27,AD27,AE27)*6,0)))) | E48: =IF(OR(AD27="",MAX(AB27,AC27,AD27,AE27)=0),"",REPT("█",MAX(1,ROUND(AD27/MAX(AB27,AC27,AD27,AE27)*6,0)))) | F48: =IF(OR(AE27="",MAX(AB27,AC27,AD27,AE27)=0),"",REPT("█",MAX(1,ROUND(AE27/MAX(AB27,AC27,AD27,AE27)*6,0)))) | G48: =IF(COUNT(AB27,AC27,AD27,AE27)<2,"",IF(IF(AE27<>"",AE27,IF(AD27<>"",AD27,IF(AC27<>"",AC27,IF(AB27<>"",AB27,""))))>IF(AB27<>"",AB27,IF(AC27<>"",AC27,IF(AD27<>"",AD27,AE27))),"▲",IF(IF(AE27<>"",AE27,IF(AD27<>"",AD27,IF(AC27<>"",AC27,IF(AB27<>"",AB27,""))))<IF(AB27<>"",AB27,IF(AC27<>"",AC27,IF(AD27<>"",AD27,AE27))),"▼","="))) | H48: =AI27 | I48: =AJ27 | J48: =IF(AL27=1,"À COMMANDER",IF(AA27="","","")) | AA48: =IF(Produits!$A$51="","",Produits!$A$51) | AB48: =IF(ISNUMBER(CHOOSE($Z$3,'Janvier'!E52,'Février'!E52,'Mars'!E52,'Avril'!E52,'Mai'!E52,'Juin'!E52,'Juillet'!E52,'Août'!E52,'Septembre'!E52,'Octobre'!E52,'Novembre'!E52,'Décembre'!E52)),CHOOSE($Z$3,'Janvier'!E52,'Février'!E52,'Mars'!E52,'Avril'!E52,'Mai'!E52,'Juin'!E52,'Juillet'!E52,'Août'!E52,'Septembre'!E52,'Octobre'!E52,'Novembre'!E52,'Décembre'!E52),"") | AC48: =IF(ISNUMBER(CHOOSE($Z$3,'Janvier'!I52,'Février'!I52,'Mars'!I52,'Avril'!I52,'Mai'!I52,'Juin'!I52,'Juillet'!I52,'Août'!I52,'Septembre'!I52,'Octobre'!I52,'Novembre'!I52,'Décembre'!I52)),CHOOSE($Z$3,'Janvier'!I52,'Février'!I52,'Mars'!I52,'Avril'!I52,'Mai'!I52,'Juin'!I52,'Juillet'!I52,'Août'!I52,'Septembre'!I52,'Octobre'!I52,'Novembre'!I52,'Décembre'!I52),"") | AD48: =IF(ISNUMBER(CHOOSE($Z$3,'Janvier'!M52,'Février'!M52,'Mars'!M52,'Avril'!M52,'Mai'!M52,'Juin'!M52,'Juillet'!M52,'Août'!M52,'Septembre'!M52,'Octobre'!M52,'Novembre'!M52,'Décembre'!M52)),CHOOSE($Z$3,'Janvier'!M52,'Février'!M52,'Mars'!M52,'Avril'!M52,'Mai'!M52,'Juin'!M52,'Juillet'!M52,'Août'!M52,'Septembre'!M52,'Octobre'!M52,'Novembre'!M52,'Décembre'!M52),"") | AE48: =IF(ISNUMBER(CHOOSE($Z$3,'Janvier'!Q52,'Février'!Q52,'Mars'!Q52,'Avril'!Q52,'Mai'!Q52,'Juin'!Q52,'Juillet'!Q52,'Août'!Q52,'Septembre'!Q52,'Octobre'!Q52,'Novembre'!Q52,'Décembre'!Q52)),CHOOSE($Z$3,'Janvier'!Q52,'Février'!Q52,'Mars'!Q52,'Avril'!Q52,'Mai'!Q52,'Juin'!Q52,'Juillet'!Q52,'Août'!Q52,'Septembre'!Q52,'Octobre'!Q52,'Novembre'!Q52,'Décembre'!Q52),"") | AF48: =IF(ISNUMBER(CHOOSE($Z$3,'Janvier'!T52,'Février'!T52,'Mars'!T52,'Avril'!T52,'Mai'!T52,'Juin'!T52,'Juillet'!T52,'Août'!T52,'Septembre'!T52,'Octobre'!T52,'Novembre'!T52,'Décembre'!T52)),CHOOSE($Z$3,'Janvier'!T52,'Février'!T52,'Mars'!T52,'Avril'!T52,'Mai'!T52,'Juin'!T52,'Juillet'!T52,'Août'!T52,'Septembre'!T52,'Octobre'!T52,'Novembre'!T52,'Décembre'!T52),"") | AG48: =IF(ISNUMBER(CHOOSE($Z$3,'Janvier'!U52,'Février'!U52,'Mars'!U52,'Avril'!U52,'Mai'!U52,'Juin'!U52,'Juillet'!U52,'Août'!U52,'Septembre'!U52,'Octobre'!U52,'Novembre'!U52,'Décembre'!U52)),CHOOSE($Z$3,'Janvier'!U52,'Février'!U52,'Mars'!U52,'Avril'!U52,'Mai'!U52,'Juin'!U52,'Juillet'!U52,'Août'!U52,'Septembre'!U52,'Octobre'!U52,'Novembre'!U52,'Décembre'!U52),"") | AH48: =IF(ISNUMBER(CHOOSE($Z$3,'Janvier'!V52,'Février'!V52,'Mars'!V52,'Avril'!V52,'Mai'!V52,'Juin'!V52,'Juillet'!V52,'Août'!V52,'Septembre'!V52,'Octobre'!V52,'Novembre'!V52,'Décembre'!V52)),CHOOSE($Z$3,'Janvier'!V52,'Février'!V52,'Mars'!V52,'Avril'!V52,'Mai'!V52,'Juin'!V52,'Juillet'!V52,'Août'!V52,'Septembre'!V52,'Octobre'!V52,'Novembre'!V52,'Décembre'!V52),"") | AI48: =IF(ISNUMBER(CHOOSE($Z$3,'Janvier'!W52,'Février'!W52,'Mars'!W52,'Avril'!W52,'Mai'!W52,'Juin'!W52,'Juillet'!W52,'Août'!W52,'Septembre'!W52,'Octobre'!W52,'Novembre'!W52,'Décembre'!W52)),CHOOSE($Z$3,'Janvier'!W52,'Février'!W52,'Mars'!W52,'Avril'!W52,'Mai'!W52,'Juin'!W52,'Juillet'!W52,'Août'!W52,'Septembre'!W52,'Octobre'!W52,'Novembre'!W52,'Décembre'!W52),"") | AJ48: =IF(Produits!$A$51="","",Produits!$D$51) | AK48: =IF(ISNUMBER(CHOOSE($Z$3,'Janvier'!X52,'Février'!X52,'Mars'!X52,'Avril'!X52,'Mai'!X52,'Juin'!X52,'Juillet'!X52,'Août'!X52,'Septembre'!X52,'Octobre'!X52,'Novembre'!X52,'Décembre'!X52)),CHOOSE($Z$3,'Janvier'!X52,'Février'!X52,'Mars'!X52,'Avril'!X52,'Mai'!X52,'Juin'!X52,'Juillet'!X52,'Août'!X52,'Septembre'!X52,'Octobre'!X52,'Novembre'!X52,'Décembre'!X52),"") | AL48: =IF(AND(ISNUMBER(AI48),ISNUMBER(AJ48)),IF(AI48<=AJ48,1,0),0) | AM48: =IF(OR(AA48="",AK48=""),-1,AK48+ROW()/1000000)
A49: =AA28 | C49: =IF(OR(AB28="",MAX(AB28,AC28,AD28,AE28)=0),"",REPT("█",MAX(1,ROUND(AB28/MAX(AB28,AC28,AD28,AE28)*6,0)))) | D49: =IF(OR(AC28="",MAX(AB28,AC28,AD28,AE28)=0),"",REPT("█",MAX(1,ROUND(AC28/MAX(AB28,AC28,AD28,AE28)*6,0)))) | E49: =IF(OR(AD28="",MAX(AB28,AC28,AD28,AE28)=0),"",REPT("█",MAX(1,ROUND(AD28/MAX(AB28,AC28,AD28,AE28)*6,0)))) | F49: =IF(OR(AE28="",MAX(AB28,AC28,AD28,AE28)=0),"",REPT("█",MAX(1,ROUND(AE28/MAX(AB28,AC28,AD28,AE28)*6,0)))) | G49: =IF(COUNT(AB28,AC28,AD28,AE28)<2,"",IF(IF(AE28<>"",AE28,IF(AD28<>"",AD28,IF(AC28<>"",AC28,IF(AB28<>"",AB28,""))))>IF(AB28<>"",AB28,IF(AC28<>"",AC28,IF(AD28<>"",AD28,AE28))),"▲",IF(IF(AE28<>"",AE28,IF(AD28<>"",AD28,IF(AC28<>"",AC28,IF(AB28<>"",AB28,""))))<IF(AB28<>"",AB28,IF(AC28<>"",AC28,IF(AD28<>"",AD28,AE28))),"▼","="))) | H49: =AI28 | I49: =AJ28 | J49: =IF(AL28=1,"À COMMANDER",IF(AA28="","","")) | AA49: =IF(Produits!$A$52="","",Produits!$A$52) | AB49: =IF(ISNUMBER(CHOOSE($Z$3,'Janvier'!E53,'Février'!E53,'Mars'!E53,'Avril'!E53,'Mai'!E53,'Juin'!E53,'Juillet'!E53,'Août'!E53,'Septembre'!E53,'Octobre'!E53,'Novembre'!E53,'Décembre'!E53)),CHOOSE($Z$3,'Janvier'!E53,'Février'!E53,'Mars'!E53,'Avril'!E53,'Mai'!E53,'Juin'!E53,'Juillet'!E53,'Août'!E53,'Septembre'!E53,'Octobre'!E53,'Novembre'!E53,'Décembre'!E53),"") | AC49: =IF(ISNUMBER(CHOOSE($Z$3,'Janvier'!I53,'Février'!I53,'Mars'!I53,'Avril'!I53,'Mai'!I53,'Juin'!I53,'Juillet'!I53,'Août'!I53,'Septembre'!I53,'Octobre'!I53,'Novembre'!I53,'Décembre'!I53)),CHOOSE($Z$3,'Janvier'!I53,'Février'!I53,'Mars'!I53,'Avril'!I53,'Mai'!I53,'Juin'!I53,'Juillet'!I53,'Août'!I53,'Septembre'!I53,'Octobre'!I53,'Novembre'!I53,'Décembre'!I53),"") | AD49: =IF(ISNUMBER(CHOOSE($Z$3,'Janvier'!M53,'Février'!M53,'Mars'!M53,'Avril'!M53,'Mai'!M53,'Juin'!M53,'Juillet'!M53,'Août'!M53,'Septembre'!M53,'Octobre'!M53,'Novembre'!M53,'Décembre'!M53)),CHOOSE($Z$3,'Janvier'!M53,'Février'!M53,'Mars'!M53,'Avril'!M53,'Mai'!M53,'Juin'!M53,'Juillet'!M53,'Août'!M53,'Septembre'!M53,'Octobre'!M53,'Novembre'!M53,'Décembre'!M53),"") | AE49: =IF(ISNUMBER(CHOOSE($Z$3,'Janvier'!Q53,'Février'!Q53,'Mars'!Q53,'Avril'!Q53,'Mai'!Q53,'Juin'!Q53,'Juillet'!Q53,'Août'!Q53,'Septembre'!Q53,'Octobre'!Q53,'Novembre'!Q53,'Décembre'!Q53)),CHOOSE($Z$3,'Janvier'!Q53,'Février'!Q53,'Mars'!Q53,'Avril'!Q53,'Mai'!Q53,'Juin'!Q53,'Juillet'!Q53,'Août'!Q53,'Septembre'!Q53,'Octobre'!Q53,'Novembre'!Q53,'Décembre'!Q53),"") | AF49: =IF(ISNUMBER(CHOOSE($Z$3,'Janvier'!T53,'Février'!T53,'Mars'!T53,'Avril'!T53,'Mai'!T53,'Juin'!T53,'Juillet'!T53,'Août'!T53,'Septembre'!T53,'Octobre'!T53,'Novembre'!T53,'Décembre'!T53)),CHOOSE($Z$3,'Janvier'!T53,'Février'!T53,'Mars'!T53,'Avril'!T53,'Mai'!T53,'Juin'!T53,'Juillet'!T53,'Août'!T53,'Septembre'!T53,'Octobre'!T53,'Novembre'!T53,'Décembre'!T53),"") | AG49: =IF(ISNUMBER(CHOOSE($Z$3,'Janvier'!U53,'Février'!U53,'Mars'!U53,'Avril'!U53,'Mai'!U53,'Juin'!U53,'Juillet'!U53,'Août'!U53,'Septembre'!U53,'Octobre'!U53,'Novembre'!U53,'Décembre'!U53)),CHOOSE($Z$3,'Janvier'!U53,'Février'!U53,'Mars'!U53,'Avril'!U53,'Mai'!U53,'Juin'!U53,'Juillet'!U53,'Août'!U53,'Septembre'!U53,'Octobre'!U53,'Novembre'!U53,'Décembre'!U53),"") | AH49: =IF(ISNUMBER(CHOOSE($Z$3,'Janvier'!V53,'Février'!V53,'Mars'!V53,'Avril'!V53,'Mai'!V53,'Juin'!V53,'Juillet'!V53,'Août'!V53,'Septembre'!V53,'Octobre'!V53,'Novembre'!V53,'Décembre'!V53)),CHOOSE($Z$3,'Janvier'!V53,'Février'!V53,'Mars'!V53,'Avril'!V53,'Mai'!V53,'Juin'!V53,'Juillet'!V53,'Août'!V53,'Septembre'!V53,'Octobre'!V53,'Novembre'!V53,'Décembre'!V53),"") | AI49: =IF(ISNUMBER(CHOOSE($Z$3,'Janvier'!W53,'Février'!W53,'Mars'!W53,'Avril'!W53,'Mai'!W53,'Juin'!W53,'Juillet'!W53,'Août'!W53,'Septembre'!W53,'Octobre'!W53,'Novembre'!W53,'Décembre'!W53)),CHOOSE($Z$3,'Janvier'!W53,'Février'!W53,'Mars'!W53,'Avril'!W53,'Mai'!W53,'Juin'!W53,'Juillet'!W53,'Août'!W53,'Septembre'!W53,'Octobre'!W53,'Novembre'!W53,'Décembre'!W53),"") | AJ49: =IF(Produits!$A$52="","",Produits!$D$52) | AK49: =IF(ISNUMBER(CHOOSE($Z$3,'Janvier'!X53,'Février'!X53,'Mars'!X53,'Avril'!X53,'Mai'!X53,'Juin'!X53,'Juillet'!X53,'Août'!X53,'Septembre'!X53,'Octobre'!X53,'Novembre'!X53,'Décembre'!X53)),CHOOSE($Z$3,'Janvier'!X53,'Février'!X53,'Mars'!X53,'Avril'!X53,'Mai'!X53,'Juin'!X53,'Juillet'!X53,'Août'!X53,'Septembre'!X53,'Octobre'!X53,'Novembre'!X53,'Décembre'!X53),"") | AL49: =IF(AND(ISNUMBER(AI49),ISNUMBER(AJ49)),IF(AI49<=AJ49,1,0),0) | AM49: =IF(OR(AA49="",AK49=""),-1,AK49+ROW()/1000000)
A50: =AA29 | C50: =IF(OR(AB29="",MAX(AB29,AC29,AD29,AE29)=0),"",REPT("█",MAX(1,ROUND(AB29/MAX(AB29,AC29,AD29,AE29)*6,0)))) | D50: =IF(OR(AC29="",MAX(AB29,AC29,AD29,AE29)=0),"",REPT("█",MAX(1,ROUND(AC29/MAX(AB29,AC29,AD29,AE29)*6,0)))) | E50: =IF(OR(AD29="",MAX(AB29,AC29,AD29,AE29)=0),"",REPT("█",MAX(1,ROUND(AD29/MAX(AB29,AC29,AD29,AE29)*6,0)))) | F50: =IF(OR(AE29="",MAX(AB29,AC29,AD29,AE29)=0),"",REPT("█",MAX(1,ROUND(AE29/MAX(AB29,AC29,AD29,AE29)*6,0)))) | G50: =IF(COUNT(AB29,AC29,AD29,AE29)<2,"",IF(IF(AE29<>"",AE29,IF(AD29<>"",AD29,IF(AC29<>"",AC29,IF(AB29<>"",AB29,""))))>IF(AB29<>"",AB29,IF(AC29<>"",AC29,IF(AD29<>"",AD29,AE29))),"▲",IF(IF(AE29<>"",AE29,IF(AD29<>"",AD29,IF(AC29<>"",AC29,IF(AB29<>"",AB29,""))))<IF(AB29<>"",AB29,IF(AC29<>"",AC29,IF(AD29<>"",AD29,AE29))),"▼","="))) | H50: =AI29 | I50: =AJ29 | J50: =IF(AL29=1,"À COMMANDER",IF(AA29="","","")) | AA50: =IF(Produits!$A$54="","",Produits!$A$54) | AB50: =IF(ISNUMBER(CHOOSE($Z$3,'Janvier'!E55,'Février'!E55,'Mars'!E55,'Avril'!E55,'Mai'!E55,'Juin'!E55,'Juillet'!E55,'Août'!E55,'Septembre'!E55,'Octobre'!E55,'Novembre'!E55,'Décembre'!E55)),CHOOSE($Z$3,'Janvier'!E55,'Février'!E55,'Mars'!E55,'Avril'!E55,'Mai'!E55,'Juin'!E55,'Juillet'!E55,'Août'!E55,'Septembre'!E55,'Octobre'!E55,'Novembre'!E55,'Décembre'!E55),"") | AC50: =IF(ISNUMBER(CHOOSE($Z$3,'Janvier'!I55,'Février'!I55,'Mars'!I55,'Avril'!I55,'Mai'!I55,'Juin'!I55,'Juillet'!I55,'Août'!I55,'Septembre'!I55,'Octobre'!I55,'Novembre'!I55,'Décembre'!I55)),CHOOSE($Z$3,'Janvier'!I55,'Février'!I55,'Mars'!I55,'Avril'!I55,'Mai'!I55,'Juin'!I55,'Juillet'!I55,'Août'!I55,'Septembre'!I55,'Octobre'!I55,'Novembre'!I55,'Décembre'!I55),"") | AD50: =IF(ISNUMBER(CHOOSE($Z$3,'Janvier'!M55,'Février'!M55,'Mars'!M55,'Avril'!M55,'Mai'!M55,'Juin'!M55,'Juillet'!M55,'Août'!M55,'Septembre'!M55,'Octobre'!M55,'Novembre'!M55,'Décembre'!M55)),CHOOSE($Z$3,'Janvier'!M55,'Février'!M55,'Mars'!M55,'Avril'!M55,'Mai'!M55,'Juin'!M55,'Juillet'!M55,'Août'!M55,'Septembre'!M55,'Octobre'!M55,'Novembre'!M55,'Décembre'!M55),"") | AE50: =IF(ISNUMBER(CHOOSE($Z$3,'Janvier'!Q55,'Février'!Q55,'Mars'!Q55,'Avril'!Q55,'Mai'!Q55,'Juin'!Q55,'Juillet'!Q55,'Août'!Q55,'Septembre'!Q55,'Octobre'!Q55,'Novembre'!Q55,'Décembre'!Q55)),CHOOSE($Z$3,'Janvier'!Q55,'Février'!Q55,'Mars'!Q55,'Avril'!Q55,'Mai'!Q55,'Juin'!Q55,'Juillet'!Q55,'Août'!Q55,'Septembre'!Q55,'Octobre'!Q55,'Novembre'!Q55,'Décembre'!Q55),"") | AF50: =IF(ISNUMBER(CHOOSE($Z$3,'Janvier'!T55,'Février'!T55,'Mars'!T55,'Avril'!T55,'Mai'!T55,'Juin'!T55,'Juillet'!T55,'Août'!T55,'Septembre'!T55,'Octobre'!T55,'Novembre'!T55,'Décembre'!T55)),CHOOSE($Z$3,'Janvier'!T55,'Février'!T55,'Mars'!T55,'Avril'!T55,'Mai'!T55,'Juin'!T55,'Juillet'!T55,'Août'!T55,'Septembre'!T55,'Octobre'!T55,'Novembre'!T55,'Décembre'!T55),"") | AG50: =IF(ISNUMBER(CHOOSE($Z$3,'Janvier'!U55,'Février'!U55,'Mars'!U55,'Avril'!U55,'Mai'!U55,'Juin'!U55,'Juillet'!U55,'Août'!U55,'Septembre'!U55,'Octobre'!U55,'Novembre'!U55,'Décembre'!U55)),CHOOSE($Z$3,'Janvier'!U55,'Février'!U55,'Mars'!U55,'Avril'!U55,'Mai'!U55,'Juin'!U55,'Juillet'!U55,'Août'!U55,'Septembre'!U55,'Octobre'!U55,'Novembre'!U55,'Décembre'!U55),"") | AH50: =IF(ISNUMBER(CHOOSE($Z$3,'Janvier'!V55,'Février'!V55,'Mars'!V55,'Avril'!V55,'Mai'!V55,'Juin'!V55,'Juillet'!V55,'Août'!V55,'Septembre'!V55,'Octobre'!V55,'Novembre'!V55,'Décembre'!V55)),CHOOSE($Z$3,'Janvier'!V55,'Février'!V55,'Mars'!V55,'Avril'!V55,'Mai'!V55,'Juin'!V55,'Juillet'!V55,'Août'!V55,'Septembre'!V55,'Octobre'!V55,'Novembre'!V55,'Décembre'!V55),"") | AI50: =IF(ISNUMBER(CHOOSE($Z$3,'Janvier'!W55,'Février'!W55,'Mars'!W55,'Avril'!W55,'Mai'!W55,'Juin'!W55,'Juillet'!W55,'Août'!W55,'Septembre'!W55,'Octobre'!W55,'Novembre'!W55,'Décembre'!W55)),CHOOSE($Z$3,'Janvier'!W55,'Février'!W55,'Mars'!W55,'Avril'!W55,'Mai'!W55,'Juin'!W55,'Juillet'!W55,'Août'!W55,'Septembre'!W55,'Octobre'!W55,'Novembre'!W55,'Décembre'!W55),"") | AJ50: =IF(Produits!$A$54="","",Produits!$D$54) | AK50: =IF(ISNUMBER(CHOOSE($Z$3,'Janvier'!X55,'Février'!X55,'Mars'!X55,'Avril'!X55,'Mai'!X55,'Juin'!X55,'Juillet'!X55,'Août'!X55,'Septembre'!X55,'Octobre'!X55,'Novembre'!X55,'Décembre'!X55)),CHOOSE($Z$3,'Janvier'!X55,'Février'!X55,'Mars'!X55,'Avril'!X55,'Mai'!X55,'Juin'!X55,'Juillet'!X55,'Août'!X55,'Septembre'!X55,'Octobre'!X55,'Novembre'!X55,'Décembre'!X55),"") | AL50: =IF(AND(ISNUMBER(AI50),ISNUMBER(AJ50)),IF(AI50<=AJ50,1,0),0) | AM50: =IF(OR(AA50="",AK50=""),-1,AK50+ROW()/1000000)
A51: =AA30 | C51: =IF(OR(AB30="",MAX(AB30,AC30,AD30,AE30)=0),"",REPT("█",MAX(1,ROUND(AB30/MAX(AB30,AC30,AD30,AE30)*6,0)))) | D51: =IF(OR(AC30="",MAX(AB30,AC30,AD30,AE30)=0),"",REPT("█",MAX(1,ROUND(AC30/MAX(AB30,AC30,AD30,AE30)*6,0)))) | E51: =IF(OR(AD30="",MAX(AB30,AC30,AD30,AE30)=0),"",REPT("█",MAX(1,ROUND(AD30/MAX(AB30,AC30,AD30,AE30)*6,0)))) | F51: =IF(OR(AE30="",MAX(AB30,AC30,AD30,AE30)=0),"",REPT("█",MAX(1,ROUND(AE30/MAX(AB30,AC30,AD30,AE30)*6,0)))) | G51: =IF(COUNT(AB30,AC30,AD30,AE30)<2,"",IF(IF(AE30<>"",AE30,IF(AD30<>"",AD30,IF(AC30<>"",AC30,IF(AB30<>"",AB30,""))))>IF(AB30<>"",AB30,IF(AC30<>"",AC30,IF(AD30<>"",AD30,AE30))),"▲",IF(IF(AE30<>"",AE30,IF(AD30<>"",AD30,IF(AC30<>"",AC30,IF(AB30<>"",AB30,""))))<IF(AB30<>"",AB30,IF(AC30<>"",AC30,IF(AD30<>"",AD30,AE30))),"▼","="))) | H51: =AI30 | I51: =AJ30 | J51: =IF(AL30=1,"À COMMANDER",IF(AA30="","","")) | AA51: =IF(Produits!$A$55="","",Produits!$A$55) | AB51: =IF(ISNUMBER(CHOOSE($Z$3,'Janvier'!E56,'Février'!E56,'Mars'!E56,'Avril'!E56,'Mai'!E56,'Juin'!E56,'Juillet'!E56,'Août'!E56,'Septembre'!E56,'Octobre'!E56,'Novembre'!E56,'Décembre'!E56)),CHOOSE($Z$3,'Janvier'!E56,'Février'!E56,'Mars'!E56,'Avril'!E56,'Mai'!E56,'Juin'!E56,'Juillet'!E56,'Août'!E56,'Septembre'!E56,'Octobre'!E56,'Novembre'!E56,'Décembre'!E56),"") | AC51: =IF(ISNUMBER(CHOOSE($Z$3,'Janvier'!I56,'Février'!I56,'Mars'!I56,'Avril'!I56,'Mai'!I56,'Juin'!I56,'Juillet'!I56,'Août'!I56,'Septembre'!I56,'Octobre'!I56,'Novembre'!I56,'Décembre'!I56)),CHOOSE($Z$3,'Janvier'!I56,'Février'!I56,'Mars'!I56,'Avril'!I56,'Mai'!I56,'Juin'!I56,'Juillet'!I56,'Août'!I56,'Septembre'!I56,'Octobre'!I56,'Novembre'!I56,'Décembre'!I56),"") | AD51: =IF(ISNUMBER(CHOOSE($Z$3,'Janvier'!M56,'Février'!M56,'Mars'!M56,'Avril'!M56,'Mai'!M56,'Juin'!M56,'Juillet'!M56,'Août'!M56,'Septembre'!M56,'Octobre'!M56,'Novembre'!M56,'Décembre'!M56)),CHOOSE($Z$3,'Janvier'!M56,'Février'!M56,'Mars'!M56,'Avril'!M56,'Mai'!M56,'Juin'!M56,'Juillet'!M56,'Août'!M56,'Septembre'!M56,'Octobre'!M56,'Novembre'!M56,'Décembre'!M56),"") | AE51: =IF(ISNUMBER(CHOOSE($Z$3,'Janvier'!Q56,'Février'!Q56,'Mars'!Q56,'Avril'!Q56,'Mai'!Q56,'Juin'!Q56,'Juillet'!Q56,'Août'!Q56,'Septembre'!Q56,'Octobre'!Q56,'Novembre'!Q56,'Décembre'!Q56)),CHOOSE($Z$3,'Janvier'!Q56,'Février'!Q56,'Mars'!Q56,'Avril'!Q56,'Mai'!Q56,'Juin'!Q56,'Juillet'!Q56,'Août'!Q56,'Septembre'!Q56,'Octobre'!Q56,'Novembre'!Q56,'Décembre'!Q56),"") | AF51: =IF(ISNUMBER(CHOOSE($Z$3,'Janvier'!T56,'Février'!T56,'Mars'!T56,'Avril'!T56,'Mai'!T56,'Juin'!T56,'Juillet'!T56,'Août'!T56,'Septembre'!T56,'Octobre'!T56,'Novembre'!T56,'Décembre'!T56)),CHOOSE($Z$3,'Janvier'!T56,'Février'!T56,'Mars'!T56,'Avril'!T56,'Mai'!T56,'Juin'!T56,'Juillet'!T56,'Août'!T56,'Septembre'!T56,'Octobre'!T56,'Novembre'!T56,'Décembre'!T56),"") | AG51: =IF(ISNUMBER(CHOOSE($Z$3,'Janvier'!U56,'Février'!U56,'Mars'!U56,'Avril'!U56,'Mai'!U56,'Juin'!U56,'Juillet'!U56,'Août'!U56,'Septembre'!U56,'Octobre'!U56,'Novembre'!U56,'Décembre'!U56)),CHOOSE($Z$3,'Janvier'!U56,'Février'!U56,'Mars'!U56,'Avril'!U56,'Mai'!U56,'Juin'!U56,'Juillet'!U56,'Août'!U56,'Septembre'!U56,'Octobre'!U56,'Novembre'!U56,'Décembre'!U56),"") | AH51: =IF(ISNUMBER(CHOOSE($Z$3,'Janvier'!V56,'Février'!V56,'Mars'!V56,'Avril'!V56,'Mai'!V56,'Juin'!V56,'Juillet'!V56,'Août'!V56,'Septembre'!V56,'Octobre'!V56,'Novembre'!V56,'Décembre'!V56)),CHOOSE($Z$3,'Janvier'!V56,'Février'!V56,'Mars'!V56,'Avril'!V56,'Mai'!V56,'Juin'!V56,'Juillet'!V56,'Août'!V56,'Septembre'!V56,'Octobre'!V56,'Novembre'!V56,'Décembre'!V56),"") | AI51: =IF(ISNUMBER(CHOOSE($Z$3,'Janvier'!W56,'Février'!W56,'Mars'!W56,'Avril'!W56,'Mai'!W56,'Juin'!W56,'Juillet'!W56,'Août'!W56,'Septembre'!W56,'Octobre'!W56,'Novembre'!W56,'Décembre'!W56)),CHOOSE($Z$3,'Janvier'!W56,'Février'!W56,'Mars'!W56,'Avril'!W56,'Mai'!W56,'Juin'!W56,'Juillet'!W56,'Août'!W56,'Septembre'!W56,'Octobre'!W56,'Novembre'!W56,'Décembre'!W56),"") | AJ51: =IF(Produits!$A$55="","",Produits!$D$55) | AK51: =IF(ISNUMBER(CHOOSE($Z$3,'Janvier'!X56,'Février'!X56,'Mars'!X56,'Avril'!X56,'Mai'!X56,'Juin'!X56,'Juillet'!X56,'Août'!X56,'Septembre'!X56,'Octobre'!X56,'Novembre'!X56,'Décembre'!X56)),CHOOSE($Z$3,'Janvier'!X56,'Février'!X56,'Mars'!X56,'Avril'!X56,'Mai'!X56,'Juin'!X56,'Juillet'!X56,'Août'!X56,'Septembre'!X56,'Octobre'!X56,'Novembre'!X56,'Décembre'!X56),"") | AL51: =IF(AND(ISNUMBER(AI51),ISNUMBER(AJ51)),IF(AI51<=AJ51,1,0),0) | AM51: =IF(OR(AA51="",AK51=""),-1,AK51+ROW()/1000000)
A52: =AA31 | C52: =IF(OR(AB31="",MAX(AB31,AC31,AD31,AE31)=0),"",REPT("█",MAX(1,ROUND(AB31/MAX(AB31,AC31,AD31,AE31)*6,0)))) | D52: =IF(OR(AC31="",MAX(AB31,AC31,AD31,AE31)=0),"",REPT("█",MAX(1,ROUND(AC31/MAX(AB31,AC31,AD31,AE31)*6,0)))) | E52: =IF(OR(AD31="",MAX(AB31,AC31,AD31,AE31)=0),"",REPT("█",MAX(1,ROUND(AD31/MAX(AB31,AC31,AD31,AE31)*6,0)))) | F52: =IF(OR(AE31="",MAX(AB31,AC31,AD31,AE31)=0),"",REPT("█",MAX(1,ROUND(AE31/MAX(AB31,AC31,AD31,AE31)*6,0)))) | G52: =IF(COUNT(AB31,AC31,AD31,AE31)<2,"",IF(IF(AE31<>"",AE31,IF(AD31<>"",AD31,IF(AC31<>"",AC31,IF(AB31<>"",AB31,""))))>IF(AB31<>"",AB31,IF(AC31<>"",AC31,IF(AD31<>"",AD31,AE31))),"▲",IF(IF(AE31<>"",AE31,IF(AD31<>"",AD31,IF(AC31<>"",AC31,IF(AB31<>"",AB31,""))))<IF(AB31<>"",AB31,IF(AC31<>"",AC31,IF(AD31<>"",AD31,AE31))),"▼","="))) | H52: =AI31 | I52: =AJ31 | J52: =IF(AL31=1,"À COMMANDER",IF(AA31="","","")) | AA52: =IF(Produits!$A$56="","",Produits!$A$56) | AB52: =IF(ISNUMBER(CHOOSE($Z$3,'Janvier'!E57,'Février'!E57,'Mars'!E57,'Avril'!E57,'Mai'!E57,'Juin'!E57,'Juillet'!E57,'Août'!E57,'Septembre'!E57,'Octobre'!E57,'Novembre'!E57,'Décembre'!E57)),CHOOSE($Z$3,'Janvier'!E57,'Février'!E57,'Mars'!E57,'Avril'!E57,'Mai'!E57,'Juin'!E57,'Juillet'!E57,'Août'!E57,'Septembre'!E57,'Octobre'!E57,'Novembre'!E57,'Décembre'!E57),"") | AC52: =IF(ISNUMBER(CHOOSE($Z$3,'Janvier'!I57,'Février'!I57,'Mars'!I57,'Avril'!I57,'Mai'!I57,'Juin'!I57,'Juillet'!I57,'Août'!I57,'Septembre'!I57,'Octobre'!I57,'Novembre'!I57,'Décembre'!I57)),CHOOSE($Z$3,'Janvier'!I57,'Février'!I57,'Mars'!I57,'Avril'!I57,'Mai'!I57,'Juin'!I57,'Juillet'!I57,'Août'!I57,'Septembre'!I57,'Octobre'!I57,'Novembre'!I57,'Décembre'!I57),"") | AD52: =IF(ISNUMBER(CHOOSE($Z$3,'Janvier'!M57,'Février'!M57,'Mars'!M57,'Avril'!M57,'Mai'!M57,'Juin'!M57,'Juillet'!M57,'Août'!M57,'Septembre'!M57,'Octobre'!M57,'Novembre'!M57,'Décembre'!M57)),CHOOSE($Z$3,'Janvier'!M57,'Février'!M57,'Mars'!M57,'Avril'!M57,'Mai'!M57,'Juin'!M57,'Juillet'!M57,'Août'!M57,'Septembre'!M57,'Octobre'!M57,'Novembre'!M57,'Décembre'!M57),"") | AE52: =IF(ISNUMBER(CHOOSE($Z$3,'Janvier'!Q57,'Février'!Q57,'Mars'!Q57,'Avril'!Q57,'Mai'!Q57,'Juin'!Q57,'Juillet'!Q57,'Août'!Q57,'Septembre'!Q57,'Octobre'!Q57,'Novembre'!Q57,'Décembre'!Q57)),CHOOSE($Z$3,'Janvier'!Q57,'Février'!Q57,'Mars'!Q57,'Avril'!Q57,'Mai'!Q57,'Juin'!Q57,'Juillet'!Q57,'Août'!Q57,'Septembre'!Q57,'Octobre'!Q57,'Novembre'!Q57,'Décembre'!Q57),"") | AF52: =IF(ISNUMBER(CHOOSE($Z$3,'Janvier'!T57,'Février'!T57,'Mars'!T57,'Avril'!T57,'Mai'!T57,'Juin'!T57,'Juillet'!T57,'Août'!T57,'Septembre'!T57,'Octobre'!T57,'Novembre'!T57,'Décembre'!T57)),CHOOSE($Z$3,'Janvier'!T57,'Février'!T57,'Mars'!T57,'Avril'!T57,'Mai'!T57,'Juin'!T57,'Juillet'!T57,'Août'!T57,'Septembre'!T57,'Octobre'!T57,'Novembre'!T57,'Décembre'!T57),"") | AG52: =IF(ISNUMBER(CHOOSE($Z$3,'Janvier'!U57,'Février'!U57,'Mars'!U57,'Avril'!U57,'Mai'!U57,'Juin'!U57,'Juillet'!U57,'Août'!U57,'Septembre'!U57,'Octobre'!U57,'Novembre'!U57,'Décembre'!U57)),CHOOSE($Z$3,'Janvier'!U57,'Février'!U57,'Mars'!U57,'Avril'!U57,'Mai'!U57,'Juin'!U57,'Juillet'!U57,'Août'!U57,'Septembre'!U57,'Octobre'!U57,'Novembre'!U57,'Décembre'!U57),"") | AH52: =IF(ISNUMBER(CHOOSE($Z$3,'Janvier'!V57,'Février'!V57,'Mars'!V57,'Avril'!V57,'Mai'!V57,'Juin'!V57,'Juillet'!V57,'Août'!V57,'Septembre'!V57,'Octobre'!V57,'Novembre'!V57,'Décembre'!V57)),CHOOSE($Z$3,'Janvier'!V57,'Février'!V57,'Mars'!V57,'Avril'!V57,'Mai'!V57,'Juin'!V57,'Juillet'!V57,'Août'!V57,'Septembre'!V57,'Octobre'!V57,'Novembre'!V57,'Décembre'!V57),"") | AI52: =IF(ISNUMBER(CHOOSE($Z$3,'Janvier'!W57,'Février'!W57,'Mars'!W57,'Avril'!W57,'Mai'!W57,'Juin'!W57,'Juillet'!W57,'Août'!W57,'Septembre'!W57,'Octobre'!W57,'Novembre'!W57,'Décembre'!W57)),CHOOSE($Z$3,'Janvier'!W57,'Février'!W57,'Mars'!W57,'Avril'!W57,'Mai'!W57,'Juin'!W57,'Juillet'!W57,'Août'!W57,'Septembre'!W57,'Octobre'!W57,'Novembre'!W57,'Décembre'!W57),"") | AJ52: =IF(Produits!$A$56="","",Produits!$D$56) | AK52: =IF(ISNUMBER(CHOOSE($Z$3,'Janvier'!X57,'Février'!X57,'Mars'!X57,'Avril'!X57,'Mai'!X57,'Juin'!X57,'Juillet'!X57,'Août'!X57,'Septembre'!X57,'Octobre'!X57,'Novembre'!X57,'Décembre'!X57)),CHOOSE($Z$3,'Janvier'!X57,'Février'!X57,'Mars'!X57,'Avril'!X57,'Mai'!X57,'Juin'!X57,'Juillet'!X57,'Août'!X57,'Septembre'!X57,'Octobre'!X57,'Novembre'!X57,'Décembre'!X57),"") | AL52: =IF(AND(ISNUMBER(AI52),ISNUMBER(AJ52)),IF(AI52<=AJ52,1,0),0) | AM52: =IF(OR(AA52="",AK52=""),-1,AK52+ROW()/1000000)
